Workbook

Sheet Profit
A1: Month | B1: Year | C1: Lessons Sales | D1: Books | E1: Instructor Payment | F1: Expenses | G1: Staff Salaries | H1: Expired Hours (Legacy) | I1: Distributed Profit | J1: Transfered to Savings | K1: Gross Profit | L1: Net Profit | M1: Cumulative | O1: Cash Available
A2: 7 | B2: 2022 | C2: =Sumproduct(Sales!$F$2:$F999,month(Sales!$A$2:$A999)=A2,year(Sales!$A$2:$A999)=B2) -> 1171.63 | D2: =Sumproduct('Amazon Royalties'!$E$2:$E999,month('Amazon Royalties'!$B$2:$B999)=A2,year('Amazon Royalties'!$B$2:$B999)=B2) -> 78.357601 | E2: =Sumproduct(Sales!$K$2:$K999,month(Sales!$A$2:$A999)=A2,year(Sales!$A$2:$A999)=B2) -> 750 | F2: =Sumproduct(Expenses!$B$2:$B999,Month(Expenses!$A$2:$A999)=A2,year(Expenses!$A$2:$A999)=B2) -> 59.31 | G2: =Sumproduct('Staff Salaries'!$B$3:$B999,month('Staff Salaries'!$A$3:$A999)=$A2,year('Staff Salaries'!$A$3:$A999)=$B2) -> 300 | H2: =IFERROR(__xludf.DUMMYFUNCTION("sumproduct(importrange(""https://docs.google.com/spreadsheets/d/15CJ-h55pYD1KSEfDJoQc5rhrr0QtLCfpr6KnyxjMee4/edit#gid=71971023"",""Expired!E2:E""),Month(importrange(""https://docs.google.com/spreadsheets/d/15CJ-h55pYD1KSEfDJoQc5rhrr0QtLCfpr6KnyxjMee4/edit"&"#gid=71971023"",""Expired!a2:a""))=A2,year(importrange(""https://docs.google.com/spreadsheets/d/15CJ-h55pYD1KSEfDJoQc5rhrr0QtLCfpr6KnyxjMee4/edit#gid=71971023"",""Expired!a2:a""))=B2)"),0.0) -> 0 | I2: =sumproduct('Profit Distributions'!$B$2:$B999,Year('Profit Distributions'!$A$2:$A999)=B2,Month('Profit Distributions'!$A$2:$A999)=A2,'Profit Distributions'!$C$2:$C999<>"Savings") -> 0 | J2: =sumproduct('Profit Distributions'!$B$2:$B999,Year('Profit Distributions'!$A$2:$A999)=B2,Month('Profit Distributions'!$A$2:$A999)=A2,'Profit Distributions'!$C$2:$C999="Savings") -> 0 | K2: =C2+D2-F2-G2-E2+H2 -> 140.6776 | L2: =K2-J2 -> 140.6776 | M2: =L2-I2 -> 140.6776 | O2: =IFERROR(__xludf.DUMMYFUNCTION("INDEX(M:M, MAX(FILTER(ROW(M:M), ISNUMBER(M:M))))+'Profit Distributions'!$G$3+'Staff Total'!$D$2"),-4985.266742111924) -> -4985.2667
A3: 8 | B3: 2022 | C3: =Sumproduct(Sales!$F$2:$F999,month(Sales!$A$2:$A999)=A3,year(Sales!$A$2:$A999)=B3) -> 1576.13 | D3: =Sumproduct('Amazon Royalties'!$E$2:$E999,month('Amazon Royalties'!$B$2:$B999)=A3,year('Amazon Royalties'!$B$2:$B999)=B3) -> 67.87038 | E3: =Sumproduct(Sales!$K$2:$K999,month(Sales!$A$2:$A999)=A3,year(Sales!$A$2:$A999)=B3) -> 945 | F3: =Sumproduct(Expenses!$B$2:$B999,Month(Expenses!$A$2:$A999)=A3,year(Expenses!$A$2:$A999)=B3) -> 298.52 | G3: =Sumproduct('Staff Salaries'!$B$3:$B999,month('Staff Salaries'!$A$3:$A999)=$A3,year('Staff Salaries'!$A$3:$A999)=$B3) -> 300 | H3: =IFERROR(__xludf.DUMMYFUNCTION("sumproduct(importrange(""https://docs.google.com/spreadsheets/d/15CJ-h55pYD1KSEfDJoQc5rhrr0QtLCfpr6KnyxjMee4/edit#gid=71971023"",""Expired!E2:E""),Month(importrange(""https://docs.google.com/spreadsheets/d/15CJ-h55pYD1KSEfDJoQc5rhrr0QtLCfpr6KnyxjMee4/edit"&"#gid=71971023"",""Expired!a2:a""))=A3,year(importrange(""https://docs.google.com/spreadsheets/d/15CJ-h55pYD1KSEfDJoQc5rhrr0QtLCfpr6KnyxjMee4/edit#gid=71971023"",""Expired!a2:a""))=B3)"),0.0) -> 0 | I3: =sumproduct('Profit Distributions'!$B$2:$B999,Year('Profit Distributions'!$A$2:$A999)=B3,Month('Profit Distributions'!$A$2:$A999)=A3,'Profit Distributions'!$C$2:$C999<>"Savings") -> 0 | J3: =sumproduct('Profit Distributions'!$B$2:$B999,Year('Profit Distributions'!$A$2:$A999)=B3,Month('Profit Distributions'!$A$2:$A999)=A3,'Profit Distributions'!$C$2:$C999="Savings") -> 0 | K3: =C3+D3-F3-G3-E3+H3 -> 100.48038 | L3: =K3-J3 -> 100.48038 | M3: =L3+M2-I3 -> 241.15798
A4: 9 | B4: 2022 | C4: =Sumproduct(Sales!$F$2:$F999,month(Sales!$A$2:$A999)=A4,year(Sales!$A$2:$A999)=B4) -> 1312.72 | D4: =Sumproduct('Amazon Royalties'!$E$2:$E999,month('Amazon Royalties'!$B$2:$B999)=A4,year('Amazon Royalties'!$B$2:$B999)=B4) -> 72.406828 | E4: =Sumproduct(Sales!$K$2:$K999,month(Sales!$A$2:$A999)=A4,year(Sales!$A$2:$A999)=B4) -> 855 | F4: =Sumproduct(Expenses!$B$2:$B999,Month(Expenses!$A$2:$A999)=A4,year(Expenses!$A$2:$A999)=B4) -> 228.3 | G4: =Sumproduct('Staff Salaries'!$B$3:$B999,month('Staff Salaries'!$A$3:$A999)=$A4,year('Staff Salaries'!$A$3:$A999)=$B4) -> 300 | H4: =IFERROR(__xludf.DUMMYFUNCTION("sumproduct(importrange(""https://docs.google.com/spreadsheets/d/15CJ-h55pYD1KSEfDJoQc5rhrr0QtLCfpr6KnyxjMee4/edit#gid=71971023"",""Expired!E2:E""),Month(importrange(""https://docs.google.com/spreadsheets/d/15CJ-h55pYD1KSEfDJoQc5rhrr0QtLCfpr6KnyxjMee4/edit"&"#gid=71971023"",""Expired!a2:a""))=A4,year(importrange(""https://docs.google.com/spreadsheets/d/15CJ-h55pYD1KSEfDJoQc5rhrr0QtLCfpr6KnyxjMee4/edit#gid=71971023"",""Expired!a2:a""))=B4)"),0.0) -> 0 | I4: =sumproduct('Profit Distributions'!$B$2:$B999,Year('Profit Distributions'!$A$2:$A999)=B4,Month('Profit Distributions'!$A$2:$A999)=A4,'Profit Distributions'!$C$2:$C999<>"Savings") -> 0 | J4: =sumproduct('Profit Distributions'!$B$2:$B999,Year('Profit Distributions'!$A$2:$A999)=B4,Month('Profit Distributions'!$A$2:$A999)=A4,'Profit Distributions'!$C$2:$C999="Savings") -> 0 | K4: =C4+D4-F4-G4-E4+H4 -> 1.826828 | L4: =K4-J4 -> 1.826828 | M4: =L4+M3-I4 -> 242.98481
A5: 10 | B5: 2022 | C5: =Sumproduct(Sales!$F$2:$F999,month(Sales!$A$2:$A999)=A5,year(Sales!$A$2:$A999)=B5) -> 1510.96 | D5: =Sumproduct('Amazon Royalties'!$E$2:$E999,month('Amazon Royalties'!$B$2:$B999)=A5,year('Amazon Royalties'!$B$2:$B999)=B5) -> 79.820326 | E5: =Sumproduct(Sales!$K$2:$K999,month(Sales!$A$2:$A999)=A5,year(Sales!$A$2:$A999)=B5) -> 1020 | F5: =Sumproduct(Expenses!$B$2:$B999,Month(Expenses!$A$2:$A999)=A5,year(Expenses!$A$2:$A999)=B5) -> 217.4 | G5: =Sumproduct('Staff Salaries'!$B$3:$B999,month('Staff Salaries'!$A$3:$A999)=$A5,year('Staff Salaries'!$A$3:$A999)=$B5) -> 300 | H5: =IFERROR(__xludf.DUMMYFUNCTION("sumproduct(importrange(""https://docs.google.com/spreadsheets/d/15CJ-h55pYD1KSEfDJoQc5rhrr0QtLCfpr6KnyxjMee4/edit#gid=71971023"",""Expired!E2:E""),Month(importrange(""https://docs.google.com/spreadsheets/d/15CJ-h55pYD1KSEfDJoQc5rhrr0QtLCfpr6KnyxjMee4/edit"&"#gid=71971023"",""Expired!a2:a""))=A5,year(importrange(""https://docs.google.com/spreadsheets/d/15CJ-h55pYD1KSEfDJoQc5rhrr0QtLCfpr6KnyxjMee4/edit#gid=71971023"",""Expired!a2:a""))=B5)"),0.0) -> 0 | I5: =sumproduct('Profit Distributions'!$B$2:$B999,Year('Profit Distributions'!$A$2:$A999)=B5,Month('Profit Distributions'!$A$2:$A999)=A5,'Profit Distributions'!$C$2:$C999<>"Savings") -> 0 | J5: =sumproduct('Profit Distributions'!$B$2:$B999,Year('Profit Distributions'!$A$2:$A999)=B5,Month('Profit Distributions'!$A$2:$A999)=A5,'Profit Distributions'!$C$2:$C999="Savings") -> 0 | K5: =C5+D5-F5-G5-E5+H5 -> 53.380326 | L5: =K5-J5 -> 53.380326 | M5: =L5+M4-I5 -> 296.36513
A6: 11 | B6: 2022 | C6: =Sumproduct(Sales!$F$2:$F999,month(Sales!$A$2:$A999)=A6,year(Sales!$A$2:$A999)=B6) -> 1077.53 | D6: =Sumproduct('Amazon Royalties'!$E$2:$E999,month('Amazon Royalties'!$B$2:$B999)=A6,year('Amazon Royalties'!$B$2:$B999)=B6) -> 82.575785 | E6: =Sumproduct(Sales!$K$2:$K999,month(Sales!$A$2:$A999)=A6,year(Sales!$A$2:$A999)=B6) -> 570 | F6: =Sumproduct(Expenses!$B$2:$B999,Month(Expenses!$A$2:$A999)=A6,year(Expenses!$A$2:$A999)=B6) -> 175.97 | G6: =Sumproduct('Staff Salaries'!$B$3:$B999,month('Staff Salaries'!$A$3:$A999)=$A6,year('Staff Salaries'!$A$3:$A999)=$B6) -> 300 | H6: =IFERROR(__xludf.DUMMYFUNCTION("sumproduct(importrange(""https://docs.google.com/spreadsheets/d/15CJ-h55pYD1KSEfDJoQc5rhrr0QtLCfpr6KnyxjMee4/edit#gid=71971023"",""Expired!E2:E""),Month(importrange(""https://docs.google.com/spreadsheets/d/15CJ-h55pYD1KSEfDJoQc5rhrr0QtLCfpr6KnyxjMee4/edit"&"#gid=71971023"",""Expired!a2:a""))=A6,year(importrange(""https://docs.google.com/spreadsheets/d/15CJ-h55pYD1KSEfDJoQc5rhrr0QtLCfpr6KnyxjMee4/edit#gid=71971023"",""Expired!a2:a""))=B6)"),0.0) -> 0 | I6: =sumproduct('Profit Distributions'!$B$2:$B999,Year('Profit Distributions'!$A$2:$A999)=B6,Month('Profit Distributions'!$A$2:$A999)=A6,'Profit Distributions'!$C$2:$C999<>"Savings") -> 0 | J6: =sumproduct('Profit Distributions'!$B$2:$B999,Year('Profit Distributions'!$A$2:$A999)=B6,Month('Profit Distributions'!$A$2:$A999)=A6,'Profit Distributions'!$C$2:$C999="Savings") -> 0 | K6: =C6+D6-F6-G6-E6+H6 -> 114.13578 | L6: =K6-J6 -> 114.13578 | M6: =L6+M5-I6 -> 410.50092
A7: 12 | B7: 2022 | C7: =Sumproduct(Sales!$F$2:$F999,month(Sales!$A$2:$A999)=A7,year(Sales!$A$2:$A999)=B7) -> 1433.11 | D7: =Sumproduct('Amazon Royalties'!$E$2:$E999,month('Amazon Royalties'!$B$2:$B999)=A7,year('Amazon Royalties'!$B$2:$B999)=B7) -> 109.97503 | E7: =Sumproduct(Sales!$K$2:$K999,month(Sales!$A$2:$A999)=A7,year(Sales!$A$2:$A999)=B7) -> 1140 | F7: =Sumproduct(Expenses!$B$2:$B999,Month(Expenses!$A$2:$A999)=A7,year(Expenses!$A$2:$A999)=B7) -> 577.77 | G7: =Sumproduct('Staff Salaries'!$B$3:$B999,month('Staff Salaries'!$A$3:$A999)=$A7,year('Staff Salaries'!$A$3:$A999)=$B7) -> 300 | H7: =IFERROR(__xludf.DUMMYFUNCTION("sumproduct(importrange(""https://docs.google.com/spreadsheets/d/15CJ-h55pYD1KSEfDJoQc5rhrr0QtLCfpr6KnyxjMee4/edit#gid=71971023"",""Expired!E2:E""),Month(importrange(""https://docs.google.com/spreadsheets/d/15CJ-h55pYD1KSEfDJoQc5rhrr0QtLCfpr6KnyxjMee4/edit"&"#gid=71971023"",""Expired!a2:a""))=A7,year(importrange(""https://docs.google.com/spreadsheets/d/15CJ-h55pYD1KSEfDJoQc5rhrr0QtLCfpr6KnyxjMee4/edit#gid=71971023"",""Expired!a2:a""))=B7)"),0.0) -> 0 | I7: =sumproduct('Profit Distributions'!$B$2:$B999,Year('Profit Distributions'!$A$2:$A999)=B7,Month('Profit Distributions'!$A$2:$A999)=A7,'Profit Distributions'!$C$2:$C999<>"Savings") -> 0 | J7: =sumproduct('Profit Distributions'!$B$2:$B999,Year('Profit Distributions'!$A$2:$A999)=B7,Month('Profit Distributions'!$A$2:$A999)=A7,'Profit Distributions'!$C$2:$C999="Savings") -> 0 | K7: =C7+D7-F7-G7-E7+H7 -> -474.68497 | L7: =K7-J7 -> -474.68497 | M7: =L7+M6-I7 -> -64.184052
A8: 1 | B8: 2023 | C8: =Sumproduct(Sales!$F$2:$F999,month(Sales!$A$2:$A999)=A8,year(Sales!$A$2:$A999)=B8) -> 4994.92 | D8: =Sumproduct('Amazon Royalties'!$E$2:$E999,month('Amazon Royalties'!$B$2:$B999)=A8,year('Amazon Royalties'!$B$2:$B999)=B8) -> 49.221648 | E8: =Sumproduct(Sales!$K$2:$K999,month(Sales!$A$2:$A999)=A8,year(Sales!$A$2:$A999)=B8) -> 2415 | F8: =Sumproduct(Expenses!$B$2:$B999,Month(Expenses!$A$2:$A999)=A8,year(Expenses!$A$2:$A999)=B8) -> 222.7 | G8: =Sumproduct('Staff Salaries'!$B$3:$B999,month('Staff Salaries'!$A$3:$A999)=$A8,year('Staff Salaries'!$A$3:$A999)=$B8) -> 300 | H8: =IFERROR(__xludf.DUMMYFUNCTION("sumproduct(importrange(""https://docs.google.com/spreadsheets/d/15CJ-h55pYD1KSEfDJoQc5rhrr0QtLCfpr6KnyxjMee4/edit#gid=71971023"",""Expired!E2:E""),Month(importrange(""https://docs.google.com/spreadsheets/d/15CJ-h55pYD1KSEfDJoQc5rhrr0QtLCfpr6KnyxjMee4/edit"&"#gid=71971023"",""Expired!a2:a""))=A8,year(importrange(""https://docs.google.com/spreadsheets/d/15CJ-h55pYD1KSEfDJoQc5rhrr0QtLCfpr6KnyxjMee4/edit#gid=71971023"",""Expired!a2:a""))=B8)"),0.0) -> 0 | I8: =sumproduct('Profit Distributions'!$B$2:$B999,Year('Profit Distributions'!$A$2:$A999)=B8,Month('Profit Distributions'!$A$2:$A999)=A8,'Profit Distributions'!$C$2:$C999<>"Savings") -> 0 | J8: =sumproduct('Profit Distributions'!$B$2:$B999,Year('Profit Distributions'!$A$2:$A999)=B8,Month('Profit Distributions'!$A$2:$A999)=A8,'Profit Distributions'!$C$2:$C999="Savings") -> 0 | K8: =C8+D8-F8-G8-E8+H8 -> 2106.4416 | L8: =K8-J8 -> 2106.4416 | M8: =L8+M7-I8 -> 2042.2576
A9: 2 | B9: 2023 | C9: =Sumproduct(Sales!$F$2:$F999,month(Sales!$A$2:$A999)=A9,year(Sales!$A$2:$A999)=B9) -> 3661.85 | D9: =Sumproduct('Amazon Royalties'!$E$2:$E999,month('Amazon Royalties'!$B$2:$B999)=A9,year('Amazon Royalties'!$B$2:$B999)=B9) -> 66.627678 | E9: =Sumproduct(Sales!$K$2:$K999,month(Sales!$A$2:$A999)=A9,year(Sales!$A$2:$A999)=B9) -> 1800 | F9: =Sumproduct(Expenses!$B$2:$B999,Month(Expenses!$A$2:$A999)=A9,year(Expenses!$A$2:$A999)=B9) -> 171.16 | G9: =Sumproduct('Staff Salaries'!$B$3:$B999,month('Staff Salaries'!$A$3:$A999)=$A9,year('Staff Salaries'!$A$3:$A999)=$B9) -> 300 | H9: =IFERROR(__xludf.DUMMYFUNCTION("sumproduct(importrange(""https://docs.google.com/spreadsheets/d/15CJ-h55pYD1KSEfDJoQc5rhrr0QtLCfpr6KnyxjMee4/edit#gid=71971023"",""Expired!E2:E""),Month(importrange(""https://docs.google.com/spreadsheets/d/15CJ-h55pYD1KSEfDJoQc5rhrr0QtLCfpr6KnyxjMee4/edit"&"#gid=71971023"",""Expired!a2:a""))=A9,year(importrange(""https://docs.google.com/spreadsheets/d/15CJ-h55pYD1KSEfDJoQc5rhrr0QtLCfpr6KnyxjMee4/edit#gid=71971023"",""Expired!a2:a""))=B9)"),0.0) -> 0 | I9: =sumproduct('Profit Distributions'!$B$2:$B999,Year('Profit Distributions'!$A$2:$A999)=B9,Month('Profit Distributions'!$A$2:$A999)=A9,'Profit Distributions'!$C$2:$C999<>"Savings") -> 1100 | J9: =sumproduct('Profit Distributions'!$B$2:$B999,Year('Profit Distributions'!$A$2:$A999)=B9,Month('Profit Distributions'!$A$2:$A999)=A9,'Profit Distributions'!$C$2:$C999="Savings") -> 0 | K9: =C9+D9-F9-G9-E9+H9 -> 1457.3177 | L9: =K9-J9 -> 1457.3177 | M9: =L9+M8-I9 -> 2399.5753
A10: 3 | B10: 2023 | C10: =Sumproduct(Sales!$F$2:$F999,month(Sales!$A$2:$A999)=A10,year(Sales!$A$2:$A999)=B10) -> 2499.48 | D10: =Sumproduct('Amazon Royalties'!$E$2:$E999,month('Amazon Royalties'!$B$2:$B999)=A10,year('Amazon Royalties'!$B$2:$B999)=B10) -> 170.29945 | E10: =Sumproduct(Sales!$K$2:$K999,month(Sales!$A$2:$A999)=A10,year(Sales!$A$2:$A999)=B10) -> 1500 | F10: =Sumproduct(Expenses!$B$2:$B999,Month(Expenses!$A$2:$A999)=A10,year(Expenses!$A$2:$A999)=B10) -> 303.93 | G10: =Sumproduct('Staff Salaries'!$B$3:$B999,month('Staff Salaries'!$A$3:$A999)=$A10,year('Staff Salaries'!$A$3:$A999)=$B10) -> 300 | H10: =IFERROR(__xludf.DUMMYFUNCTION("sumproduct(importrange(""https://docs.google.com/spreadsheets/d/15CJ-h55pYD1KSEfDJoQc5rhrr0QtLCfpr6KnyxjMee4/edit#gid=71971023"",""Expired!E2:E""),Month(importrange(""https://docs.google.com/spreadsheets/d/15CJ-h55pYD1KSEfDJoQc5rhrr0QtLCfpr6KnyxjMee4/edit"&"#gid=71971023"",""Expired!a2:a""))=A10,year(importrange(""https://docs.google.com/spreadsheets/d/15CJ-h55pYD1KSEfDJoQc5rhrr0QtLCfpr6KnyxjMee4/edit#gid=71971023"",""Expired!a2:a""))=B10)"),0.0) -> 0 | I10: =sumproduct('Profit Distributions'!$B$2:$B999,Year('Profit Distributions'!$A$2:$A999)=B10,Month('Profit Distributions'!$A$2:$A999)=A10,'Profit Distributions'!$C$2:$C999<>"Savings") -> 1100 | J10: =sumproduct('Profit Distributions'!$B$2:$B999,Year('Profit Distributions'!$A$2:$A999)=B10,Month('Profit Distributions'!$A$2:$A999)=A10,'Profit Distributions'!$C$2:$C999="Savings") -> 0 | K10: =C10+D10-F10-G10-E10+H10 -> 565.84945 | L10: =K10-J10 -> 565.84945 | M10: =L10+M9-I10 -> 1865.4247
A11: 4 | B11: 2023 | C11: =Sumproduct(Sales!$F$2:$F999,month(Sales!$A$2:$A999)=A11,year(Sales!$A$2:$A999)=B11) -> 2657.56 | D11: =Sumproduct('Amazon Royalties'!$E$2:$E999,month('Amazon Royalties'!$B$2:$B999)=A11,year('Amazon Royalties'!$B$2:$B999)=B11) -> 98.90229 | E11: =Sumproduct(Sales!$K$2:$K999,month(Sales!$A$2:$A999)=A11,year(Sales!$A$2:$A999)=B11) -> 1800 | F11: =Sumproduct(Expenses!$B$2:$B999,Month(Expenses!$A$2:$A999)=A11,year(Expenses!$A$2:$A999)=B11) -> 178.3 | G11: =Sumproduct('Staff Salaries'!$B$3:$B999,month('Staff Salaries'!$A$3:$A999)=$A11,year('Staff Salaries'!$A$3:$A999)=$B11) -> 300 | H11: =IFERROR(__xludf.DUMMYFUNCTION("sumproduct(importrange(""https://docs.google.com/spreadsheets/d/15CJ-h55pYD1KSEfDJoQc5rhrr0QtLCfpr6KnyxjMee4/edit#gid=71971023"",""Expired!E2:E""),Month(importrange(""https://docs.google.com/spreadsheets/d/15CJ-h55pYD1KSEfDJoQc5rhrr0QtLCfpr6KnyxjMee4/edit"&"#gid=71971023"",""Expired!a2:a""))=A11,year(importrange(""https://docs.google.com/spreadsheets/d/15CJ-h55pYD1KSEfDJoQc5rhrr0QtLCfpr6KnyxjMee4/edit#gid=71971023"",""Expired!a2:a""))=B11)"),0.0) -> 0 | I11: =sumproduct('Profit Distributions'!$B$2:$B999,Year('Profit Distributions'!$A$2:$A999)=B11,Month('Profit Distributions'!$A$2:$A999)=A11,'Profit Distributions'!$C$2:$C999<>"Savings") -> 0 | J11: =sumproduct('Profit Distributions'!$B$2:$B999,Year('Profit Distributions'!$A$2:$A999)=B11,Month('Profit Distributions'!$A$2:$A999)=A11,'Profit Distributions'!$C$2:$C999="Savings") -> 0 | K11: =C11+D11-F11-G11-E11+H11 -> 478.16229 | L11: =K11-J11 -> 478.16229 | M11: =L11+M10-I11 -> 2343.587
A12: 5 | B12: 2023 | C12: =Sumproduct(Sales!$F$2:$F999,month(Sales!$A$2:$A999)=A12,year(Sales!$A$2:$A999)=B12) -> 2633.81 | D12: =Sumproduct('Amazon Royalties'!$E$2:$E999,month('Amazon Royalties'!$B$2:$B999)=A12,year('Amazon Royalties'!$B$2:$B999)=B12) -> 75.94143 | E12: =Sumproduct(Sales!$K$2:$K999,month(Sales!$A$2:$A999)=A12,year(Sales!$A$2:$A999)=B12) -> 1845 | F12: =Sumproduct(Expenses!$B$2:$B999,Month(Expenses!$A$2:$A999)=A12,year(Expenses!$A$2:$A999)=B12) -> 351.75 | G12: =Sumproduct('Staff Salaries'!$B$3:$B999,month('Staff Salaries'!$A$3:$A999)=$A12,year('Staff Salaries'!$A$3:$A999)=$B12) -> 300 | H12: =IFERROR(__xludf.DUMMYFUNCTION("sumproduct(importrange(""https://docs.google.com/spreadsheets/d/15CJ-h55pYD1KSEfDJoQc5rhrr0QtLCfpr6KnyxjMee4/edit#gid=71971023"",""Expired!E2:E""),Month(importrange(""https://docs.google.com/spreadsheets/d/15CJ-h55pYD1KSEfDJoQc5rhrr0QtLCfpr6KnyxjMee4/edit"&"#gid=71971023"",""Expired!a2:a""))=A12,year(importrange(""https://docs.google.com/spreadsheets/d/15CJ-h55pYD1KSEfDJoQc5rhrr0QtLCfpr6KnyxjMee4/edit#gid=71971023"",""Expired!a2:a""))=B12)"),90.0) -> 90 | I12: =sumproduct('Profit Distributions'!$B$2:$B999,Year('Profit Distributions'!$A$2:$A999)=B12,Month('Profit Distributions'!$A$2:$A999)=A12,'Profit Distributions'!$C$2:$C999<>"Savings") -> 1400 | J12: =sumproduct('Profit Distributions'!$B$2:$B999,Year('Profit Distributions'!$A$2:$A999)=B12,Month('Profit Distributions'!$A$2:$A999)=A12,'Profit Distributions'!$C$2:$C999="Savings") -> 0 | K12: =C12+D12-F12-G12-E12+H12 -> 303.00143 | L12: =K12-J12 -> 303.00143 | M12: =L12+M11-I12 -> 1246.5884
A13: 6 | B13: 2023 | C13: =Sumproduct(Sales!$F$2:$F999,month(Sales!$A$2:$A999)=A13,year(Sales!$A$2:$A999)=B13) -> 1009.09 | D13: =Sumproduct('Amazon Royalties'!$E$2:$E999,month('Amazon Royalties'!$B$2:$B999)=A13,year('Amazon Royalties'!$B$2:$B999)=B13) -> 103.64184 | E13: =Sumproduct(Sales!$K$2:$K999,month(Sales!$A$2:$A999)=A13,year(Sales!$A$2:$A999)=B13) -> 255 | F13: =Sumproduct(Expenses!$B$2:$B999,Month(Expenses!$A$2:$A999)=A13,year(Expenses!$A$2:$A999)=B13) -> 211.7 | G13: =Sumproduct('Staff Salaries'!$B$3:$B999,month('Staff Salaries'!$A$3:$A999)=$A13,year('Staff Salaries'!$A$3:$A999)=$B13) -> 300 | H13: =IFERROR(__xludf.DUMMYFUNCTION("sumproduct(importrange(""https://docs.google.com/spreadsheets/d/15CJ-h55pYD1KSEfDJoQc5rhrr0QtLCfpr6KnyxjMee4/edit#gid=71971023"",""Expired!E2:E""),Month(importrange(""https://docs.google.com/spreadsheets/d/15CJ-h55pYD1KSEfDJoQc5rhrr0QtLCfpr6KnyxjMee4/edit"&"#gid=71971023"",""Expired!a2:a""))=A13,year(importrange(""https://docs.google.com/spreadsheets/d/15CJ-h55pYD1KSEfDJoQc5rhrr0QtLCfpr6KnyxjMee4/edit#gid=71971023"",""Expired!a2:a""))=B13)"),0.0) -> 0 | I13: =sumproduct('Profit Distributions'!$B$2:$B999,Year('Profit Distributions'!$A$2:$A999)=B13,Month('Profit Distributions'!$A$2:$A999)=A13,'Profit Distributions'!$C$2:$C999<>"Savings") -> 0 | J13: =sumproduct('Profit Distributions'!$B$2:$B999,Year('Profit Distributions'!$A$2:$A999)=B13,Month('Profit Distributions'!$A$2:$A999)=A13,'Profit Distributions'!$C$2:$C999="Savings") -> 0 | K13: =C13+D13-F13-G13-E13+H13 -> 346.03184 | L13: =K13-J13 -> 346.03184 | M13: =L13+M12-I13 -> 1592.6203
A14: 7 | B14: 2023 | C14: =Sumproduct(Sales!$F$2:$F999,month(Sales!$A$2:$A999)=A14,year(Sales!$A$2:$A999)=B14) -> 2546.8161 | D14: =Sumproduct('Amazon Royalties'!$E$2:$E999,month('Amazon Royalties'!$B$2:$B999)=A14,year('Amazon Royalties'!$B$2:$B999)=B14) -> 83.72371 | E14: =Sumproduct(Sales!$K$2:$K999,month(Sales!$A$2:$A999)=A14,year(Sales!$A$2:$A999)=B14) -> 240 | F14: =Sumproduct(Expenses!$B$2:$B999,Month(Expenses!$A$2:$A999)=A14,year(Expenses!$A$2:$A999)=B14) -> 233.48 | G14: =Sumproduct('Staff Salaries'!$B$3:$B999,month('Staff Salaries'!$A$3:$A999)=$A14,year('Staff Salaries'!$A$3:$A999)=$B14) -> 300 | H14: =IFERROR(__xludf.DUMMYFUNCTION("sumproduct(importrange(""https://docs.google.com/spreadsheets/d/15CJ-h55pYD1KSEfDJoQc5rhrr0QtLCfpr6KnyxjMee4/edit#gid=71971023"",""Expired!E2:E""),Month(importrange(""https://docs.google.com/spreadsheets/d/15CJ-h55pYD1KSEfDJoQc5rhrr0QtLCfpr6KnyxjMee4/edit"&"#gid=71971023"",""Expired!a2:a""))=A14,year(importrange(""https://docs.google.com/spreadsheets/d/15CJ-h55pYD1KSEfDJoQc5rhrr0QtLCfpr6KnyxjMee4/edit#gid=71971023"",""Expired!a2:a""))=B14)"),0.0) -> 0 | I14: =sumproduct('Profit Distributions'!$B$2:$B999,Year('Profit Distributions'!$A$2:$A999)=B14,Month('Profit Distributions'!$A$2:$A999)=A14,'Profit Distributions'!$C$2:$C999<>"Savings") -> 274 | J14: =sumproduct('Profit Distributions'!$B$2:$B999,Year('Profit Distributions'!$A$2:$A999)=B14,Month('Profit Distributions'!$A$2:$A999)=A14,'Profit Distributions'!$C$2:$C999="Savings") -> 0 | K14: =C14+D14-F14-G14-E14+H14 -> 1857.0598 | L14: =K14-J14 -> 1857.0598 | M14: =L14+M13-I14 -> 3175.6801
A15: 8 | B15: 2023 | C15: =Sumproduct(Sales!$F$2:$F999,month(Sales!$A$2:$A999)=A15,year(Sales!$A$2:$A999)=B15) -> 3586.524 | D15: =Sumproduct('Amazon Royalties'!$E$2:$E999,month('Amazon Royalties'!$B$2:$B999)=A15,year('Amazon Royalties'!$B$2:$B999)=B15) -> 81.022032 | E15: ='Teacher Salaries'!V16 -> 971.25 | F15: =Sumproduct(Expenses!$B$2:$B999,Month(Expenses!$A$2:$A999)=A15,year(Expenses!$A$2:$A999)=B15) -> 420.98 | G15: =Sumproduct('Staff Salaries'!$B$3:$B999,month('Staff Salaries'!$A$3:$A999)=$A15,year('Staff Salaries'!$A$3:$A999)=$B15) -> 0 | H15: =IFERROR(__xludf.DUMMYFUNCTION("sumproduct(importrange(""https://docs.google.com/spreadsheets/d/15CJ-h55pYD1KSEfDJoQc5rhrr0QtLCfpr6KnyxjMee4/edit#gid=71971023"",""Expired!E2:E""),Month(importrange(""https://docs.google.com/spreadsheets/d/15CJ-h55pYD1KSEfDJoQc5rhrr0QtLCfpr6KnyxjMee4/edit"&"#gid=71971023"",""Expired!a2:a""))=A15,year(importrange(""https://docs.google.com/spreadsheets/d/15CJ-h55pYD1KSEfDJoQc5rhrr0QtLCfpr6KnyxjMee4/edit#gid=71971023"",""Expired!a2:a""))=B15)"),405.0) -> 405 | I15: =sumproduct('Profit Distributions'!$B$2:$B999,Year('Profit Distributions'!$A$2:$A999)=B15,Month('Profit Distributions'!$A$2:$A999)=A15,'Profit Distributions'!$C$2:$C999<>"Savings") -> 1800 | J15: =sumproduct('Profit Distributions'!$B$2:$B999,Year('Profit Distributions'!$A$2:$A999)=B15,Month('Profit Distributions'!$A$2:$A999)=A15,'Profit Distributions'!$C$2:$C999="Savings") -> 1600 | K15: =C15+D15-F15-G15-E15+H15 -> 2680.316 | L15: =K15-J15 -> 1080.316 | M15: =L15+M14-I15 -> 2455.9962
A16: 9 | B16: 2023 | C16: =Sumproduct(Sales!$F$2:$F999,month(Sales!$A$2:$A999)=A16,year(Sales!$A$2:$A999)=B16) -> 2256.8178 | D16: =Sumproduct('Amazon Royalties'!$E$2:$E999,month('Amazon Royalties'!$B$2:$B999)=A16,year('Amazon Royalties'!$B$2:$B999)=B16) -> 107.45421 | E16: ='Teacher Salaries'!V17 -> 1600 | F16: =Sumproduct(Expenses!$B$2:$B999,Month(Expenses!$A$2:$A999)=A16,year(Expenses!$A$2:$A999)=B16) -> 226.46 | G16: =Sumproduct('Staff Salaries'!$B$3:$B999,month('Staff Salaries'!$A$3:$A999)=$A16,year('Staff Salaries'!$A$3:$A999)=$B16) -> 0 | H16: =IFERROR(__xludf.DUMMYFUNCTION("sumproduct(importrange(""https://docs.google.com/spreadsheets/d/15CJ-h55pYD1KSEfDJoQc5rhrr0QtLCfpr6KnyxjMee4/edit#gid=71971023"",""Expired!E2:E""),Month(importrange(""https://docs.google.com/spreadsheets/d/15CJ-h55pYD1KSEfDJoQc5rhrr0QtLCfpr6KnyxjMee4/edit"&"#gid=71971023"",""Expired!a2:a""))=A16,year(importrange(""https://docs.google.com/spreadsheets/d/15CJ-h55pYD1KSEfDJoQc5rhrr0QtLCfpr6KnyxjMee4/edit#gid=71971023"",""Expired!a2:a""))=B16)"),0.0) -> 0 | I16: =sumproduct('Profit Distributions'!$B$2:$B999,Year('Profit Distributions'!$A$2:$A999)=B16,Month('Profit Distributions'!$A$2:$A999)=A16,'Profit Distributions'!$C$2:$C999<>"Savings") -> 2674 | J16: =sumproduct('Profit Distributions'!$B$2:$B999,Year('Profit Distributions'!$A$2:$A999)=B16,Month('Profit Distributions'!$A$2:$A999)=A16,'Profit Distributions'!$C$2:$C999="Savings") -> 0 | K16: =C16+D16-F16-G16-E16+H16 -> 537.81201 | L16: =K16-J16 -> 537.81201 | M16: =L16+M15-I16 -> 319.80818
A17: 10 | B17: 2023 | C17: =Sumproduct(Sales!$F$2:$F999,month(Sales!$A$2:$A999)=A17,year(Sales!$A$2:$A999)=B17) -> 3826.5466 | D17: =Sumproduct('Amazon Royalties'!$E$2:$E999,month('Amazon Royalties'!$B$2:$B999)=A17,year('Amazon Royalties'!$B$2:$B999)=B17) -> 92.757525 | E17: ='Teacher Salaries'!V18 -> 1600 | F17: =Sumproduct(Expenses!$B$2:$B999,Month(Expenses!$A$2:$A999)=A17,year(Expenses!$A$2:$A999)=B17) -> 205.66 | G17: =Sumproduct('Staff Salaries'!$B$3:$B999,month('Staff Salaries'!$A$3:$A999)=$A17,year('Staff Salaries'!$A$3:$A999)=$B17) -> 0 | H17: =IFERROR(__xludf.DUMMYFUNCTION("sumproduct(importrange(""https://docs.google.com/spreadsheets/d/15CJ-h55pYD1KSEfDJoQc5rhrr0QtLCfpr6KnyxjMee4/edit#gid=71971023"",""Expired!E2:E""),Month(importrange(""https://docs.google.com/spreadsheets/d/15CJ-h55pYD1KSEfDJoQc5rhrr0QtLCfpr6KnyxjMee4/edit"&"#gid=71971023"",""Expired!a2:a""))=A17,year(importrange(""https://docs.google.com/spreadsheets/d/15CJ-h55pYD1KSEfDJoQc5rhrr0QtLCfpr6KnyxjMee4/edit#gid=71971023"",""Expired!a2:a""))=B17)"),0.0) -> 0 | I17: =sumproduct('Profit Distributions'!$B$2:$B999,Year('Profit Distributions'!$A$2:$A999)=B17,Month('Profit Distributions'!$A$2:$A999)=A17,'Profit Distributions'!$C$2:$C999<>"Savings") -> 0 | J17: =sumproduct('Profit Distributions'!$B$2:$B999,Year('Profit Distributions'!$A$2:$A999)=B17,Month('Profit Distributions'!$A$2:$A999)=A17,'Profit Distributions'!$C$2:$C999="Savings") -> 0 | K17: =C17+D17-F17-G17-E17+H17 -> 2113.6442 | L17: =K17-J17 -> 2113.6442 | M17: =L17+M16-I17 -> 2433.4523
A18: 11 | B18: 2023 | C18: =Sumproduct(Sales!$F$2:$F999,month(Sales!$A$2:$A999)=A18,year(Sales!$A$2:$A999)=B18) -> 3221.9333 | D18: =Sumproduct('Amazon Royalties'!$E$2:$E999,month('Amazon Royalties'!$B$2:$B999)=A18,year('Amazon Royalties'!$B$2:$B999)=B18) -> 99.983457 | E18: ='Teacher Salaries'!V19 -> 1722 | F18: =Sumproduct(Expenses!$B$2:$B999,Month(Expenses!$A$2:$A999)=A18,year(Expenses!$A$2:$A999)=B18) -> 521.62 | G18: =Sumproduct('Staff Salaries'!$B$3:$B999,month('Staff Salaries'!$A$3:$A999)=$A18,year('Staff Salaries'!$A$3:$A999)=$B18) -> 0 | H18: =IFERROR(__xludf.DUMMYFUNCTION("sumproduct(importrange(""https://docs.google.com/spreadsheets/d/15CJ-h55pYD1KSEfDJoQc5rhrr0QtLCfpr6KnyxjMee4/edit#gid=71971023"",""Expired!E2:E""),Month(importrange(""https://docs.google.com/spreadsheets/d/15CJ-h55pYD1KSEfDJoQc5rhrr0QtLCfpr6KnyxjMee4/edit"&"#gid=71971023"",""Expired!a2:a""))=A18,year(importrange(""https://docs.google.com/spreadsheets/d/15CJ-h55pYD1KSEfDJoQc5rhrr0QtLCfpr6KnyxjMee4/edit#gid=71971023"",""Expired!a2:a""))=B18)"),0.0) -> 0 | I18: =sumproduct('Profit Distributions'!$B$2:$B999,Year('Profit Distributions'!$A$2:$A999)=B18,Month('Profit Distributions'!$A$2:$A999)=A18,'Profit Distributions'!$C$2:$C999<>"Savings") -> 2240 | J18: =sumproduct('Profit Distributions'!$B$2:$B999,Year('Profit Distributions'!$A$2:$A999)=B18,Month('Profit Distributions'!$A$2:$A999)=A18,'Profit Distributions'!$C$2:$C999="Savings") -> 200 | K18: =C18+D18-F18-G18-E18+H18 -> 1078.2968 | L18: =K18-J18 -> 878.29678 | M18: =L18+M17-I18 -> 1071.7491
A19: 12 | B19: 2023 | C19: =Sumproduct(Sales!$F$2:$F999,month(Sales!$A$2:$A999)=A19,year(Sales!$A$2:$A999)=B19) -> 2770.8581 | D19: =Sumproduct('Amazon Royalties'!$E$2:$E999,month('Amazon Royalties'!$B$2:$B999)=A19,year('Amazon Royalties'!$B$2:$B999)=B19) -> 57.873277 | E19: ='Teacher Salaries'!V20 -> 1976 | F19: =Sumproduct(Expenses!$B$2:$B999,Month(Expenses!$A$2:$A999)=A19,year(Expenses!$A$2:$A999)=B19) -> 209.99 | G19: =Sumproduct('Staff Salaries'!$B$3:$B999,month('Staff Salaries'!$A$3:$A999)=$A19,year('Staff Salaries'!$A$3:$A999)=$B19) -> 0 | H19: =IFERROR(__xludf.DUMMYFUNCTION("sumproduct(importrange(""https://docs.google.com/spreadsheets/d/15CJ-h55pYD1KSEfDJoQc5rhrr0QtLCfpr6KnyxjMee4/edit#gid=71971023"",""Expired!E2:E""),Month(importrange(""https://docs.google.com/spreadsheets/d/15CJ-h55pYD1KSEfDJoQc5rhrr0QtLCfpr6KnyxjMee4/edit"&"#gid=71971023"",""Expired!a2:a""))=A19,year(importrange(""https://docs.google.com/spreadsheets/d/15CJ-h55pYD1KSEfDJoQc5rhrr0QtLCfpr6KnyxjMee4/edit#gid=71971023"",""Expired!a2:a""))=B19)"),0.0) -> 0 | I19: =sumproduct('Profit Distributions'!$B$2:$B999,Year('Profit Distributions'!$A$2:$A999)=B19,Month('Profit Distributions'!$A$2:$A999)=A19,'Profit Distributions'!$C$2:$C999<>"Savings") -> 644 | J19: =sumproduct('Profit Distributions'!$B$2:$B999,Year('Profit Distributions'!$A$2:$A999)=B19,Month('Profit Distributions'!$A$2:$A999)=A19,'Profit Distributions'!$C$2:$C999="Savings") -> 0 | K19: =C19+D19-F19-G19-E19+H19 -> 642.74134 | L19: =K19-J19 -> 642.74134 | M19: =L19+M18-I19 -> 1070.4905
A20: 1 | B20: 2024 | C20: =Sumproduct(Sales!$F$2:$F999,month(Sales!$A$2:$A999)=A20,year(Sales!$A$2:$A999)=B20) -> 6476.5989 | D20: =Sumproduct('Amazon Royalties'!$E$2:$E999,month('Amazon Royalties'!$B$2:$B999)=A20,year('Amazon Royalties'!$B$2:$B999)=B20) -> 88.206357 | E20: ='Teacher Salaries'!V21 -> 2160 | F20: =Sumproduct(Expenses!$B$2:$B999,Month(Expenses!$A$2:$A999)=A20,year(Expenses!$A$2:$A999)=B20) -> 573.46 | G20: =Sumproduct('Staff Salaries'!$B$3:$B999,month('Staff Salaries'!$A$3:$A999)=$A20,year('Staff Salaries'!$A$3:$A999)=$B20) -> 150 | H20: =IFERROR(__xludf.DUMMYFUNCTION("sumproduct(importrange(""https://docs.google.com/spreadsheets/d/15CJ-h55pYD1KSEfDJoQc5rhrr0QtLCfpr6KnyxjMee4/edit#gid=71971023"",""Expired!E2:E""),Month(importrange(""https://docs.google.com/spreadsheets/d/15CJ-h55pYD1KSEfDJoQc5rhrr0QtLCfpr6KnyxjMee4/edit"&"#gid=71971023"",""Expired!a2:a""))=A20,year(importrange(""https://docs.google.com/spreadsheets/d/15CJ-h55pYD1KSEfDJoQc5rhrr0QtLCfpr6KnyxjMee4/edit#gid=71971023"",""Expired!a2:a""))=B20)"),0.0) -> 0 | I20: =sumproduct('Profit Distributions'!$B$2:$B999,Year('Profit Distributions'!$A$2:$A999)=B20,Month('Profit Distributions'!$A$2:$A999)=A20,'Profit Distributions'!$C$2:$C999<>"Savings") -> 550 | J20: =sumproduct('Profit Distributions'!$B$2:$B999,Year('Profit Distributions'!$A$2:$A999)=B20,Month('Profit Distributions'!$A$2:$A999)=A20,'Profit Distributions'!$C$2:$C999="Savings") -> 2700 | K20: =C20+D20-F20-G20-E20+H20 -> 3681.3452 | L20: =K20-J20 -> 981.34524 | M20: =L20+M19-I20 -> 1501.8357
A21: 2 | B21: 2024 | C21: =Sumproduct(Sales!$F$2:$F999,month(Sales!$A$2:$A999)=A21,year(Sales!$A$2:$A999)=B21) -> 3662.2423 | D21: =Sumproduct('Amazon Royalties'!$E$2:$E999,month('Amazon Royalties'!$B$2:$B999)=A21,year('Amazon Royalties'!$B$2:$B999)=B21) -> 165.03497 | E21: ='Teacher Salaries'!V22 -> 2096 | F21: =Sumproduct(Expenses!$B$2:$B999,Month(Expenses!$A$2:$A999)=A21,year(Expenses!$A$2:$A999)=B21) -> 223.76 | G21: =Sumproduct('Staff Salaries'!$B$3:$B999,month('Staff Salaries'!$A$3:$A999)=$A21,year('Staff Salaries'!$A$3:$A999)=$B21) -> 150 | H21: =IFERROR(__xludf.DUMMYFUNCTION("sumproduct(importrange(""https://docs.google.com/spreadsheets/d/15CJ-h55pYD1KSEfDJoQc5rhrr0QtLCfpr6KnyxjMee4/edit#gid=71971023"",""Expired!E2:E""),Month(importrange(""https://docs.google.com/spreadsheets/d/15CJ-h55pYD1KSEfDJoQc5rhrr0QtLCfpr6KnyxjMee4/edit"&"#gid=71971023"",""Expired!a2:a""))=A21,year(importrange(""https://docs.google.com/spreadsheets/d/15CJ-h55pYD1KSEfDJoQc5rhrr0QtLCfpr6KnyxjMee4/edit#gid=71971023"",""Expired!a2:a""))=B21)"),0.0) -> 0 | I21: =sumproduct('Profit Distributions'!$B$2:$B999,Year('Profit Distributions'!$A$2:$A999)=B21,Month('Profit Distributions'!$A$2:$A999)=A21,'Profit Distributions'!$C$2:$C999<>"Savings") -> 1000 | J21: =sumproduct('Profit Distributions'!$B$2:$B999,Year('Profit Distributions'!$A$2:$A999)=B21,Month('Profit Distributions'!$A$2:$A999)=A21,'Profit Distributions'!$C$2:$C999="Savings") -> 0 | K21: =C21+D21-F21-G21-E21+H21 -> 1357.5173 | L21: =K21-J21 -> 1357.5173 | M21: =L21+M20-I21 -> 1859.353
A22: 3 | B22: 2024 | C22: =Sumproduct(Sales!$F$2:$F999,month(Sales!$A$2:$A999)=A22,year(Sales!$A$2:$A999)=B22) -> 5508.3743 | D22: =Sumproduct('Amazon Royalties'!$E$2:$E999,month('Amazon Royalties'!$B$2:$B999)=A22,year('Amazon Royalties'!$B$2:$B999)=B22) -> 106.67002 | E22: ='Teacher Salaries'!V23 -> 2112 | F22: =Sumproduct(Expenses!$B$2:$B999,Month(Expenses!$A$2:$A999)=A22,year(Expenses!$A$2:$A999)=B22) -> 60.99 | G22: =Sumproduct('Staff Salaries'!$B$3:$B999,month('Staff Salaries'!$A$3:$A999)=$A22,year('Staff Salaries'!$A$3:$A999)=$B22) -> 150 | H22: =IFERROR(__xludf.DUMMYFUNCTION("sumproduct(importrange(""https://docs.google.com/spreadsheets/d/15CJ-h55pYD1KSEfDJoQc5rhrr0QtLCfpr6KnyxjMee4/edit#gid=71971023"",""Expired!E2:E""),Month(importrange(""https://docs.google.com/spreadsheets/d/15CJ-h55pYD1KSEfDJoQc5rhrr0QtLCfpr6KnyxjMee4/edit"&"#gid=71971023"",""Expired!a2:a""))=A22,year(importrange(""https://docs.google.com/spreadsheets/d/15CJ-h55pYD1KSEfDJoQc5rhrr0QtLCfpr6KnyxjMee4/edit#gid=71971023"",""Expired!a2:a""))=B22)"),0.0) -> 0 | I22: =sumproduct('Profit Distributions'!$B$2:$B999,Year('Profit Distributions'!$A$2:$A999)=B22,Month('Profit Distributions'!$A$2:$A999)=A22,'Profit Distributions'!$C$2:$C999<>"Savings") -> 808 | J22: =sumproduct('Profit Distributions'!$B$2:$B999,Year('Profit Distributions'!$A$2:$A999)=B22,Month('Profit Distributions'!$A$2:$A999)=A22,'Profit Distributions'!$C$2:$C999="Savings") -> 0 | K22: =C22+D22-F22-G22-E22+H22 -> 3292.0543 | L22: =K22-J22 -> 3292.0543 | M22: =L22+M21-I22 -> 4343.4073
A23: 4 | B23: 2024 | C23: =Sumproduct(Sales!$F$2:$F999,month(Sales!$A$2:$A999)=A23,year(Sales!$A$2:$A999)=B23) -> 4961.0471 | D23: =Sumproduct('Amazon Royalties'!$E$2:$E999,month('Amazon Royalties'!$B$2:$B999)=A23,year('Amazon Royalties'!$B$2:$B999)=B23) -> 85.422372 | E23: ='Teacher Salaries'!V24 -> 2136 | F23: =Sumproduct(Expenses!$B$2:$B999,Month(Expenses!$A$2:$A999)=A23,year(Expenses!$A$2:$A999)=B23) -> 169.99 | G23: =Sumproduct('Staff Salaries'!$B$3:$B999,month('Staff Salaries'!$A$3:$A999)=$A23,year('Staff Salaries'!$A$3:$A999)=$B23) -> 150 | H23: =IFERROR(__xludf.DUMMYFUNCTION("sumproduct(importrange(""https://docs.google.com/spreadsheets/d/15CJ-h55pYD1KSEfDJoQc5rhrr0QtLCfpr6KnyxjMee4/edit#gid=71971023"",""Expired!E2:E""),Month(importrange(""https://docs.google.com/spreadsheets/d/15CJ-h55pYD1KSEfDJoQc5rhrr0QtLCfpr6KnyxjMee4/edit"&"#gid=71971023"",""Expired!a2:a""))=A23,year(importrange(""https://docs.google.com/spreadsheets/d/15CJ-h55pYD1KSEfDJoQc5rhrr0QtLCfpr6KnyxjMee4/edit#gid=71971023"",""Expired!a2:a""))=B23)"),0.0) -> 0 | I23: =sumproduct('Profit Distributions'!$B$2:$B999,Year('Profit Distributions'!$A$2:$A999)=B23,Month('Profit Distributions'!$A$2:$A999)=A23,'Profit Distributions'!$C$2:$C999<>"Savings") -> 1000 | J23: =sumproduct('Profit Distributions'!$B$2:$B999,Year('Profit Distributions'!$A$2:$A999)=B23,Month('Profit Distributions'!$A$2:$A999)=A23,'Profit Distributions'!$C$2:$C999="Savings") -> 0 | K23: =C23+D23-F23-G23-E23+H23 -> 2590.4795 | L23: =K23-J23 -> 2590.4795 | M23: =L23+M22-I23 -> 5933.8868
A24: 5 | B24: 2024 | C24: =Sumproduct(Sales!$F$2:$F999,month(Sales!$A$2:$A999)=A24,year(Sales!$A$2:$A999)=B24) -> 4280.876 | D24: =Sumproduct('Amazon Royalties'!$E$2:$E999,month('Amazon Royalties'!$B$2:$B999)=A24,year('Amazon Royalties'!$B$2:$B999)=B24) -> 58.024046 | E24: ='Teacher Salaries'!V25 -> 2479 | F24: =Sumproduct(Expenses!$B$2:$B999,Month(Expenses!$A$2:$A999)=A24,year(Expenses!$A$2:$A999)=B24) -> 258.31 | G24: =Sumproduct('Staff Salaries'!$B$3:$B999,month('Staff Salaries'!$A$3:$A999)=$A24,year('Staff Salaries'!$A$3:$A999)=$B24) -> 150 | H24: =IFERROR(__xludf.DUMMYFUNCTION("sumproduct(importrange(""https://docs.google.com/spreadsheets/d/15CJ-h55pYD1KSEfDJoQc5rhrr0QtLCfpr6KnyxjMee4/edit#gid=71971023"",""Expired!E2:E""),Month(importrange(""https://docs.google.com/spreadsheets/d/15CJ-h55pYD1KSEfDJoQc5rhrr0QtLCfpr6KnyxjMee4/edit"&"#gid=71971023"",""Expired!a2:a""))=A24,year(importrange(""https://docs.google.com/spreadsheets/d/15CJ-h55pYD1KSEfDJoQc5rhrr0QtLCfpr6KnyxjMee4/edit#gid=71971023"",""Expired!a2:a""))=B24)"),0.0) -> 0 | I24: =sumproduct('Profit Distributions'!$B$2:$B999,Year('Profit Distributions'!$A$2:$A999)=B24,Month('Profit Distributions'!$A$2:$A999)=A24,'Profit Distributions'!$C$2:$C999<>"Savings") -> 6742 | J24: =sumproduct('Profit Distributions'!$B$2:$B999,Year('Profit Distributions'!$A$2:$A999)=B24,Month('Profit Distributions'!$A$2:$A999)=A24,'Profit Distributions'!$C$2:$C999="Savings") -> 640 | K24: =C24+D24-F24-G24-E24+H24 -> 1451.59 | L24: =K24-J24 -> 811.59003 | M24: =L24+M23-I24 -> 3.4768206
A25: 6 | B25: 2024 | C25: =Sumproduct(Sales!$F$2:$F999,month(Sales!$A$2:$A999)=A25,year(Sales!$A$2:$A999)=B25) -> 3360.93 | D25: =Sumproduct('Amazon Royalties'!$E$2:$E999,month('Amazon Royalties'!$B$2:$B999)=A25,year('Amazon Royalties'!$B$2:$B999)=B25) -> 131.37343 | E25: ='Teacher Salaries'!V26 -> 2487 | F25: =Sumproduct(Expenses!$B$2:$B999,Month(Expenses!$A$2:$A999)=A25,year(Expenses!$A$2:$A999)=B25) -> 216.99 | G25: =Sumproduct('Staff Salaries'!$B$3:$B999,month('Staff Salaries'!$A$3:$A999)=$A25,year('Staff Salaries'!$A$3:$A999)=$B25) -> 1592 | H25: =IFERROR(__xludf.DUMMYFUNCTION("sumproduct(importrange(""https://docs.google.com/spreadsheets/d/15CJ-h55pYD1KSEfDJoQc5rhrr0QtLCfpr6KnyxjMee4/edit#gid=71971023"",""Expired!E2:E""),Month(importrange(""https://docs.google.com/spreadsheets/d/15CJ-h55pYD1KSEfDJoQc5rhrr0QtLCfpr6KnyxjMee4/edit"&"#gid=71971023"",""Expired!a2:a""))=A25,year(importrange(""https://docs.google.com/spreadsheets/d/15CJ-h55pYD1KSEfDJoQc5rhrr0QtLCfpr6KnyxjMee4/edit#gid=71971023"",""Expired!a2:a""))=B25)"),0.0) -> 0 | I25: =sumproduct('Profit Distributions'!$B$2:$B999,Year('Profit Distributions'!$A$2:$A999)=B25,Month('Profit Distributions'!$A$2:$A999)=A25,'Profit Distributions'!$C$2:$C999<>"Savings") -> 0 | J25: =sumproduct('Profit Distributions'!$B$2:$B999,Year('Profit Distributions'!$A$2:$A999)=B25,Month('Profit Distributions'!$A$2:$A999)=A25,'Profit Distributions'!$C$2:$C999="Savings") -> 0 | K25: =C25+D25-F25-G25-E25+H25 -> -803.68655 | L25: =K25-J25 -> -803.68655 | M25: =L25+M24-I25 -> -800.20973
A26: 7 | B26: 2024 | C26: =Sumproduct(Sales!$F$2:$F999,month(Sales!$A$2:$A999)=A26,year(Sales!$A$2:$A999)=B26) -> 3307.98 | D26: =Sumproduct('Amazon Royalties'!$E$2:$E999,month('Amazon Royalties'!$B$2:$B999)=A26,year('Amazon Royalties'!$B$2:$B999)=B26) -> 68.396454 | E26: ='Teacher Salaries'!V27 -> 2255 | F26: =Sumproduct(Expenses!$B$2:$B999,Month(Expenses!$A$2:$A999)=A26,year(Expenses!$A$2:$A999)=B26) -> 326.99 | G26: =Sumproduct('Staff Salaries'!$B$3:$B999,month('Staff Salaries'!$A$3:$A999)=$A26,year('Staff Salaries'!$A$3:$A999)=$B26) -> 1622 | H26: =IFERROR(__xludf.DUMMYFUNCTION("sumproduct(importrange(""https://docs.google.com/spreadsheets/d/15CJ-h55pYD1KSEfDJoQc5rhrr0QtLCfpr6KnyxjMee4/edit#gid=71971023"",""Expired!E2:E""),Month(importrange(""https://docs.google.com/spreadsheets/d/15CJ-h55pYD1KSEfDJoQc5rhrr0QtLCfpr6KnyxjMee4/edit"&"#gid=71971023"",""Expired!a2:a""))=A26,year(importrange(""https://docs.google.com/spreadsheets/d/15CJ-h55pYD1KSEfDJoQc5rhrr0QtLCfpr6KnyxjMee4/edit#gid=71971023"",""Expired!a2:a""))=B26)"),0.0) -> 0 | I26: =sumproduct('Profit Distributions'!$B$2:$B999,Year('Profit Distributions'!$A$2:$A999)=B26,Month('Profit Distributions'!$A$2:$A999)=A26,'Profit Distributions'!$C$2:$C999<>"Savings") -> 0 | J26: =sumproduct('Profit Distributions'!$B$2:$B999,Year('Profit Distributions'!$A$2:$A999)=B26,Month('Profit Distributions'!$A$2:$A999)=A26,'Profit Distributions'!$C$2:$C999="Savings") -> 0 | K26: =C26+D26-F26-G26-E26+H26 -> -827.61351 | L26: =K26-J26 -> -827.61351 | M26: =L26+M25-I26 -> -1627.8232
A27: 8 | B27: 2024 | C27: =Sumproduct(Sales!$F$2:$F999,month(Sales!$A$2:$A999)=A27,year(Sales!$A$2:$A999)=B27) -> 5210.0269 | D27: =Sumproduct('Amazon Royalties'!$E$2:$E999,month('Amazon Royalties'!$B$2:$B999)=A27,year('Amazon Royalties'!$B$2:$B999)=B27) -> 72.54076 | E27: ='Teacher Salaries'!V28 -> 2413 | F27: =Sumproduct(Expenses!$B$2:$B999,Month(Expenses!$A$2:$A999)=A27,year(Expenses!$A$2:$A999)=B27) -> 134.1 | G27: =Sumproduct('Staff Salaries'!$B$3:$B999,month('Staff Salaries'!$A$3:$A999)=$A27,year('Staff Salaries'!$A$3:$A999)=$B27) -> 2736 | H27: =IFERROR(__xludf.DUMMYFUNCTION("sumproduct(importrange(""https://docs.google.com/spreadsheets/d/15CJ-h55pYD1KSEfDJoQc5rhrr0QtLCfpr6KnyxjMee4/edit#gid=71971023"",""Expired!E2:E""),Month(importrange(""https://docs.google.com/spreadsheets/d/15CJ-h55pYD1KSEfDJoQc5rhrr0QtLCfpr6KnyxjMee4/edit"&"#gid=71971023"",""Expired!a2:a""))=A27,year(importrange(""https://docs.google.com/spreadsheets/d/15CJ-h55pYD1KSEfDJoQc5rhrr0QtLCfpr6KnyxjMee4/edit#gid=71971023"",""Expired!a2:a""))=B27)"),0.0) -> 0 | I27: =sumproduct('Profit Distributions'!$B$2:$B999,Year('Profit Distributions'!$A$2:$A999)=B27,Month('Profit Distributions'!$A$2:$A999)=A27,'Profit Distributions'!$C$2:$C999<>"Savings") -> 0 | J27: =sumproduct('Profit Distributions'!$B$2:$B999,Year('Profit Distributions'!$A$2:$A999)=B27,Month('Profit Distributions'!$A$2:$A999)=A27,'Profit Distributions'!$C$2:$C999="Savings") -> 0 | K27: =C27+D27-F27-G27-E27+H27 -> -0.53229221 | L27: =K27-J27 -> -0.53229221 | M27: =L27+M26-I27 -> -1628.3555
A28: 9 | B28: 2024 | C28: =Sumproduct(Sales!$F$2:$F999,month(Sales!$A$2:$A999)=A28,year(Sales!$A$2:$A999)=B28) -> 4643.6149 | D28: =Sumproduct('Amazon Royalties'!$E$2:$E999,month('Amazon Royalties'!$B$2:$B999)=A28,year('Amazon Royalties'!$B$2:$B999)=B28) -> 72.45979 | E28: ='Teacher Salaries'!V29 -> 2618 | F28: =Sumproduct(Expenses!$B$2:$B999,Month(Expenses!$A$2:$A999)=A28,year(Expenses!$A$2:$A999)=B28) -> 243.99 | G28: =Sumproduct('Staff Salaries'!$B$3:$B999,month('Staff Salaries'!$A$3:$A999)=$A28,year('Staff Salaries'!$A$3:$A999)=$B28) -> 1865 | H28: =IFERROR(__xludf.DUMMYFUNCTION("sumproduct(importrange(""https://docs.google.com/spreadsheets/d/15CJ-h55pYD1KSEfDJoQc5rhrr0QtLCfpr6KnyxjMee4/edit#gid=71971023"",""Expired!E2:E""),Month(importrange(""https://docs.google.com/spreadsheets/d/15CJ-h55pYD1KSEfDJoQc5rhrr0QtLCfpr6KnyxjMee4/edit"&"#gid=71971023"",""Expired!a2:a""))=A28,year(importrange(""https://docs.google.com/spreadsheets/d/15CJ-h55pYD1KSEfDJoQc5rhrr0QtLCfpr6KnyxjMee4/edit#gid=71971023"",""Expired!a2:a""))=B28)"),0.0) -> 0 | I28: =sumproduct('Profit Distributions'!$B$2:$B999,Year('Profit Distributions'!$A$2:$A999)=B28,Month('Profit Distributions'!$A$2:$A999)=A28,'Profit Distributions'!$C$2:$C999<>"Savings") -> 0 | J28: =sumproduct('Profit Distributions'!$B$2:$B999,Year('Profit Distributions'!$A$2:$A999)=B28,Month('Profit Distributions'!$A$2:$A999)=A28,'Profit Distributions'!$C$2:$C999="Savings") -> 0 | K28: =C28+D28-F28-G28-E28+H28 -> -10.915288 | L28: =K28-J28 -> -10.915288 | M28: =L28+M27-I28 -> -1639.2708
A29: 10 | B29: 2024 | C29: =Sumproduct(Sales!$F$2:$F999,month(Sales!$A$2:$A999)=A29,year(Sales!$A$2:$A999)=B29) -> 5389.3621 | D29: =Sumproduct('Amazon Royalties'!$E$2:$E999,month('Amazon Royalties'!$B$2:$B999)=A29,year('Amazon Royalties'!$B$2:$B999)=B29) -> 61.672832 | E29: ='Teacher Salaries'!V30 -> 2903 | F29: =Sumproduct(Expenses!$B$2:$B999,Month(Expenses!$A$2:$A999)=A29,year(Expenses!$A$2:$A999)=B29) -> 216.15 | G29: =Sumproduct('Staff Salaries'!$B$3:$B999,month('Staff Salaries'!$A$3:$A999)=$A29,year('Staff Salaries'!$A$3:$A999)=$B29) -> 1600 | H29: =IFERROR(__xludf.DUMMYFUNCTION("sumproduct(importrange(""https://docs.google.com/spreadsheets/d/15CJ-h55pYD1KSEfDJoQc5rhrr0QtLCfpr6KnyxjMee4/edit#gid=71971023"",""Expired!E2:E""),Month(importrange(""https://docs.google.com/spreadsheets/d/15CJ-h55pYD1KSEfDJoQc5rhrr0QtLCfpr6KnyxjMee4/edit"&"#gid=71971023"",""Expired!a2:a""))=A29,year(importrange(""https://docs.google.com/spreadsheets/d/15CJ-h55pYD1KSEfDJoQc5rhrr0QtLCfpr6KnyxjMee4/edit#gid=71971023"",""Expired!a2:a""))=B29)"),0.0) -> 0 | I29: =sumproduct('Profit Distributions'!$B$2:$B999,Year('Profit Distributions'!$A$2:$A999)=B29,Month('Profit Distributions'!$A$2:$A999)=A29,'Profit Distributions'!$C$2:$C999<>"Savings") -> 0 | J29: =sumproduct('Profit Distributions'!$B$2:$B999,Year('Profit Distributions'!$A$2:$A999)=B29,Month('Profit Distributions'!$A$2:$A999)=A29,'Profit Distributions'!$C$2:$C999="Savings") -> 0 | K29: =C29+D29-F29-G29-E29+H29 -> 731.88498 | L29: =K29-J29 -> 731.88498 | M29: =L29+M28-I29 -> -907.38584
A30: 11 | B30: 2024 | C30: =Sumproduct(Sales!$F$2:$F999,month(Sales!$A$2:$A999)=A30,year(Sales!$A$2:$A999)=B30) -> 3662.09 | D30: =Sumproduct('Amazon Royalties'!$E$2:$E999,month('Amazon Royalties'!$B$2:$B999)=A30,year('Amazon Royalties'!$B$2:$B999)=B30) -> 86.125913 | E30: ='Teacher Salaries'!V31 -> 2991 | F30: =Sumproduct(Expenses!$B$2:$B999,Month(Expenses!$A$2:$A999)=A30,year(Expenses!$A$2:$A999)=B30) -> 230.8 | G30: =Sumproduct('Staff Salaries'!$B$3:$B999,month('Staff Salaries'!$A$3:$A999)=$A30,year('Staff Salaries'!$A$3:$A999)=$B30) -> 1600 | H30: =IFERROR(__xludf.DUMMYFUNCTION("sumproduct(importrange(""https://docs.google.com/spreadsheets/d/15CJ-h55pYD1KSEfDJoQc5rhrr0QtLCfpr6KnyxjMee4/edit#gid=71971023"",""Expired!E2:E""),Month(importrange(""https://docs.google.com/spreadsheets/d/15CJ-h55pYD1KSEfDJoQc5rhrr0QtLCfpr6KnyxjMee4/edit"&"#gid=71971023"",""Expired!a2:a""))=A30,year(importrange(""https://docs.google.com/spreadsheets/d/15CJ-h55pYD1KSEfDJoQc5rhrr0QtLCfpr6KnyxjMee4/edit#gid=71971023"",""Expired!a2:a""))=B30)"),0.0) -> 0 | I30: =sumproduct('Profit Distributions'!$B$2:$B999,Year('Profit Distributions'!$A$2:$A999)=B30,Month('Profit Distributions'!$A$2:$A999)=A30,'Profit Distributions'!$C$2:$C999<>"Savings") -> 0 | J30: =sumproduct('Profit Distributions'!$B$2:$B999,Year('Profit Distributions'!$A$2:$A999)=B30,Month('Profit Distributions'!$A$2:$A999)=A30,'Profit Distributions'!$C$2:$C999="Savings") -> 0 | K30: =C30+D30-F30-G30-E30+H30 -> -1073.5841 | L30: =K30-J30 -> -1073.5841 | M30: =L30+M29-I30 -> -1980.9699
A31: 12 | B31: 2024 | C31: =Sumproduct(Sales!$F$2:$F999,month(Sales!$A$2:$A999)=A31,year(Sales!$A$2:$A999)=B31) -> 4073.8 | D31: =Sumproduct('Amazon Royalties'!$E$2:$E999,month('Amazon Royalties'!$B$2:$B999)=A31,year('Amazon Royalties'!$B$2:$B999)=B31) -> 124.84247 | E31: ='Teacher Salaries'!V32 -> 3047 | F31: =Sumproduct(Expenses!$B$2:$B999,Month(Expenses!$A$2:$A999)=A31,year(Expenses!$A$2:$A999)=B31) -> 419.11 | G31: =Sumproduct('Staff Salaries'!$B$3:$B999,month('Staff Salaries'!$A$3:$A999)=$A31,year('Staff Salaries'!$A$3:$A999)=$B31) -> 1700 | H31: =IFERROR(__xludf.DUMMYFUNCTION("sumproduct(importrange(""https://docs.google.com/spreadsheets/d/15CJ-h55pYD1KSEfDJoQc5rhrr0QtLCfpr6KnyxjMee4/edit#gid=71971023"",""Expired!E2:E""),Month(importrange(""https://docs.google.com/spreadsheets/d/15CJ-h55pYD1KSEfDJoQc5rhrr0QtLCfpr6KnyxjMee4/edit"&"#gid=71971023"",""Expired!a2:a""))=A31,year(importrange(""https://docs.google.com/spreadsheets/d/15CJ-h55pYD1KSEfDJoQc5rhrr0QtLCfpr6KnyxjMee4/edit#gid=71971023"",""Expired!a2:a""))=B31)"),0.0) -> 0 | I31: =sumproduct('Profit Distributions'!$B$2:$B999,Year('Profit Distributions'!$A$2:$A999)=B31,Month('Profit Distributions'!$A$2:$A999)=A31,'Profit Distributions'!$C$2:$C999<>"Savings") -> 0 | J31: =sumproduct('Profit Distributions'!$B$2:$B999,Year('Profit Distributions'!$A$2:$A999)=B31,Month('Profit Distributions'!$A$2:$A999)=A31,'Profit Distributions'!$C$2:$C999="Savings") -> 0 | K31: =C31+D31-F31-G31-E31+H31 -> -967.46753 | L31: =K31-J31 -> -967.46753 | M31: =L31+M30-I31 -> -2948.4375
A32: 1 | B32: 2025 | C32: =Sumproduct(Sales!$F$2:$F999,month(Sales!$A$2:$A999)=A32,year(Sales!$A$2:$A999)=B32) -> 7034.14 | D32: =Sumproduct('Amazon Royalties'!$E$2:$E999,month('Amazon Royalties'!$B$2:$B999)=A32,year('Amazon Royalties'!$B$2:$B999)=B32) -> 102.67837 | E32: ='Teacher Salaries'!V33 -> 3157 | F32: =Sumproduct(Expenses!$B$2:$B999,Month(Expenses!$A$2:$A999)=A32,year(Expenses!$A$2:$A999)=B32) -> 502.03 | G32: =Sumproduct('Staff Salaries'!$B$3:$B999,month('Staff Salaries'!$A$3:$A999)=$A32,year('Staff Salaries'!$A$3:$A999)=$B32) -> 1700 | H32: =IFERROR(__xludf.DUMMYFUNCTION("sumproduct(importrange(""https://docs.google.com/spreadsheets/d/15CJ-h55pYD1KSEfDJoQc5rhrr0QtLCfpr6KnyxjMee4/edit#gid=71971023"",""Expired!E2:E""),Month(importrange(""https://docs.google.com/spreadsheets/d/15CJ-h55pYD1KSEfDJoQc5rhrr0QtLCfpr6KnyxjMee4/edit"&"#gid=71971023"",""Expired!a2:a""))=A32,year(importrange(""https://docs.google.com/spreadsheets/d/15CJ-h55pYD1KSEfDJoQc5rhrr0QtLCfpr6KnyxjMee4/edit#gid=71971023"",""Expired!a2:a""))=B32)"),0.0) -> 0 | I32: =sumproduct('Profit Distributions'!$B$2:$B999,Year('Profit Distributions'!$A$2:$A999)=B32,Month('Profit Distributions'!$A$2:$A999)=A32,'Profit Distributions'!$C$2:$C999<>"Savings") -> 0 | J32: =sumproduct('Profit Distributions'!$B$2:$B999,Year('Profit Distributions'!$A$2:$A999)=B32,Month('Profit Distributions'!$A$2:$A999)=A32,'Profit Distributions'!$C$2:$C999="Savings") -> 0 | K32: =C32+D32-F32-G32-E32+H32 -> 1777.7884 | L32: =K32-J32 -> 1777.7884 | M32: =L32+M31-I32 -> -1170.6491
A33: 2 | B33: 2025 | C33: =Sumproduct(Sales!$F$2:$F999,month(Sales!$A$2:$A999)=A33,year(Sales!$A$2:$A999)=B33) -> 3304.26 | D33: =Sumproduct('Amazon Royalties'!$E$2:$E999,month('Amazon Royalties'!$B$2:$B999)=A33,year('Amazon Royalties'!$B$2:$B999)=B33) -> 120.80777 | E33: ='Teacher Salaries'!V34 -> 3025 | F33: =Sumproduct(Expenses!$B$2:$B999,Month(Expenses!$A$2:$A999)=A33,year(Expenses!$A$2:$A999)=B33) -> 175.98 | G33: =Sumproduct('Staff Salaries'!$B$3:$B999,month('Staff Salaries'!$A$3:$A999)=$A33,year('Staff Salaries'!$A$3:$A999)=$B33) -> 1700 | H33: =IFERROR(__xludf.DUMMYFUNCTION("sumproduct(importrange(""https://docs.google.com/spreadsheets/d/15CJ-h55pYD1KSEfDJoQc5rhrr0QtLCfpr6KnyxjMee4/edit#gid=71971023"",""Expired!E2:E""),Month(importrange(""https://docs.google.com/spreadsheets/d/15CJ-h55pYD1KSEfDJoQc5rhrr0QtLCfpr6KnyxjMee4/edit"&"#gid=71971023"",""Expired!a2:a""))=A33,year(importrange(""https://docs.google.com/spreadsheets/d/15CJ-h55pYD1KSEfDJoQc5rhrr0QtLCfpr6KnyxjMee4/edit#gid=71971023"",""Expired!a2:a""))=B33)"),0.0) -> 0 | I33: =sumproduct('Profit Distributions'!$B$2:$B999,Year('Profit Distributions'!$A$2:$A999)=B33,Month('Profit Distributions'!$A$2:$A999)=A33,'Profit Distributions'!$C$2:$C999<>"Savings") -> 0 | J33: =sumproduct('Profit Distributions'!$B$2:$B999,Year('Profit Distributions'!$A$2:$A999)=B33,Month('Profit Distributions'!$A$2:$A999)=A33,'Profit Distributions'!$C$2:$C999="Savings") -> 0 | K33: =C33+D33-F33-G33-E33+H33 -> -1475.9122 | L33: =K33-J33 -> -1475.9122 | M33: =L33+M32-I33 -> -2646.5613
A34: 3 | B34: 2025 | C34: =Sumproduct(Sales!$F$2:$F999,month(Sales!$A$2:$A999)=A34,year(Sales!$A$2:$A999)=B34) -> 5362.18 | D34: =Sumproduct('Amazon Royalties'!$E$2:$E999,month('Amazon Royalties'!$B$2:$B999)=A34,year('Amazon Royalties'!$B$2:$B999)=B34) -> 71.816917 | E34: ='Teacher Salaries'!V35 -> 3277 | F34: =Sumproduct(Expenses!$B$2:$B999,Month(Expenses!$A$2:$A999)=A34,year(Expenses!$A$2:$A999)=B34) -> 135.98 | G34: =Sumproduct('Staff Salaries'!$B$3:$B999,month('Staff Salaries'!$A$3:$A999)=$A34,year('Staff Salaries'!$A$3:$A999)=$B34) -> 1700 | H34: =IFERROR(__xludf.DUMMYFUNCTION("sumproduct(importrange(""https://docs.google.com/spreadsheets/d/15CJ-h55pYD1KSEfDJoQc5rhrr0QtLCfpr6KnyxjMee4/edit#gid=71971023"",""Expired!E2:E""),Month(importrange(""https://docs.google.com/spreadsheets/d/15CJ-h55pYD1KSEfDJoQc5rhrr0QtLCfpr6KnyxjMee4/edit"&"#gid=71971023"",""Expired!a2:a""))=A34,year(importrange(""https://docs.google.com/spreadsheets/d/15CJ-h55pYD1KSEfDJoQc5rhrr0QtLCfpr6KnyxjMee4/edit#gid=71971023"",""Expired!a2:a""))=B34)"),0.0) -> 0 | I34: =sumproduct('Profit Distributions'!$B$2:$B999,Year('Profit Distributions'!$A$2:$A999)=B34,Month('Profit Distributions'!$A$2:$A999)=A34,'Profit Distributions'!$C$2:$C999<>"Savings") -> 0 | J34: =sumproduct('Profit Distributions'!$B$2:$B999,Year('Profit Distributions'!$A$2:$A999)=B34,Month('Profit Distributions'!$A$2:$A999)=A34,'Profit Distributions'!$C$2:$C999="Savings") -> 0 | K34: =C34+D34-F34-G34-E34+H34 -> 321.01692 | L34: =K34-J34 -> 321.01692 | M34: =L34+M33-I34 -> -2325.5444
A35: 4 | B35: 2025 | C35: =Sumproduct(Sales!$F$2:$F999,month(Sales!$A$2:$A999)=A35,year(Sales!$A$2:$A999)=B35) -> 4293.83 | D35: =Sumproduct('Amazon Royalties'!$E$2:$E999,month('Amazon Royalties'!$B$2:$B999)=A35,year('Amazon Royalties'!$B$2:$B999)=B35) -> 155.64116 | E35: ='Teacher Salaries'!V36 -> 3178 | F35: =Sumproduct(Expenses!$B$2:$B999,Month(Expenses!$A$2:$A999)=A35,year(Expenses!$A$2:$A999)=B35) -> 146.98 | G35: =Sumproduct('Staff Salaries'!$B$3:$B999,month('Staff Salaries'!$A$3:$A999)=$A35,year('Staff Salaries'!$A$3:$A999)=$B35) -> 1700 | H35: =IFERROR(__xludf.DUMMYFUNCTION("sumproduct(importrange(""https://docs.google.com/spreadsheets/d/15CJ-h55pYD1KSEfDJoQc5rhrr0QtLCfpr6KnyxjMee4/edit#gid=71971023"",""Expired!E2:E""),Month(importrange(""https://docs.google.com/spreadsheets/d/15CJ-h55pYD1KSEfDJoQc5rhrr0QtLCfpr6KnyxjMee4/edit"&"#gid=71971023"",""Expired!a2:a""))=A35,year(importrange(""https://docs.google.com/spreadsheets/d/15CJ-h55pYD1KSEfDJoQc5rhrr0QtLCfpr6KnyxjMee4/edit#gid=71971023"",""Expired!a2:a""))=B35)"),0.0) -> 0 | I35: =sumproduct('Profit Distributions'!$B$2:$B999,Year('Profit Distributions'!$A$2:$A999)=B35,Month('Profit Distributions'!$A$2:$A999)=A35,'Profit Distributions'!$C$2:$C999<>"Savings") -> 0 | J35: =sumproduct('Profit Distributions'!$B$2:$B999,Year('Profit Distributions'!$A$2:$A999)=B35,Month('Profit Distributions'!$A$2:$A999)=A35,'Profit Distributions'!$C$2:$C999="Savings") -> 0 | K35: =C35+D35-F35-G35-E35+H35 -> -575.50884 | L35: =K35-J35 -> -575.50884 | M35: =L35+M34-I35 -> -2901.0532
A36: 5 | B36: 2025 | C36: =Sumproduct(Sales!$F$2:$F999,month(Sales!$A$2:$A999)=A36,year(Sales!$A$2:$A999)=B36) -> 3945.89 | D36: =Sumproduct('Amazon Royalties'!$E$2:$E999,month('Amazon Royalties'!$B$2:$B999)=A36,year('Amazon Royalties'!$B$2:$B999)=B36) -> 65.541745 | E36: ='Teacher Salaries'!V37 -> 3211 | F36: =Sumproduct(Expenses!$B$2:$B999,Month(Expenses!$A$2:$A999)=A36,year(Expenses!$A$2:$A999)=B36) -> 313.6 | G36: =Sumproduct('Staff Salaries'!$B$3:$B999,month('Staff Salaries'!$A$3:$A999)=$A36,year('Staff Salaries'!$A$3:$A999)=$B36) -> 1700 | H36: =IFERROR(__xludf.DUMMYFUNCTION("sumproduct(importrange(""https://docs.google.com/spreadsheets/d/15CJ-h55pYD1KSEfDJoQc5rhrr0QtLCfpr6KnyxjMee4/edit#gid=71971023"",""Expired!E2:E""),Month(importrange(""https://docs.google.com/spreadsheets/d/15CJ-h55pYD1KSEfDJoQc5rhrr0QtLCfpr6KnyxjMee4/edit"&"#gid=71971023"",""Expired!a2:a""))=A36,year(importrange(""https://docs.google.com/spreadsheets/d/15CJ-h55pYD1KSEfDJoQc5rhrr0QtLCfpr6KnyxjMee4/edit#gid=71971023"",""Expired!a2:a""))=B36)"),0.0) -> 0 | I36: =sumproduct('Profit Distributions'!$B$2:$B999,Year('Profit Distributions'!$A$2:$A999)=B36,Month('Profit Distributions'!$A$2:$A999)=A36,'Profit Distributions'!$C$2:$C999<>"Savings") -> 0 | J36: =sumproduct('Profit Distributions'!$B$2:$B999,Year('Profit Distributions'!$A$2:$A999)=B36,Month('Profit Distributions'!$A$2:$A999)=A36,'Profit Distributions'!$C$2:$C999="Savings") -> -3000 | K36: =C36+D36-F36-G36-E36+H36 -> -1213.1683 | L36: =K36-J36 -> 1786.8317 | M36: =L36+M35-I36 -> -1114.2215
A37: 6 | B37: 2025 | C37: =Sumproduct(Sales!$F$2:$F999,month(Sales!$A$2:$A999)=A37,year(Sales!$A$2:$A999)=B37) -> 2738.89 | D37: =Sumproduct('Amazon Royalties'!$E$2:$E999,month('Amazon Royalties'!$B$2:$B999)=A37,year('Amazon Royalties'!$B$2:$B999)=B37) -> 48.84004 | E37: ='Teacher Salaries'!V38 -> 2818 | F37: =Sumproduct(Expenses!$B$2:$B999,Month(Expenses!$A$2:$A999)=A37,year(Expenses!$A$2:$A999)=B37) -> 202.18 | G37: =Sumproduct('Staff Salaries'!$B$3:$B999,month('Staff Salaries'!$A$3:$A999)=$A37,year('Staff Salaries'!$A$3:$A999)=$B37) -> 1700 | H37: =IFERROR(__xludf.DUMMYFUNCTION("sumproduct(importrange(""https://docs.google.com/spreadsheets/d/15CJ-h55pYD1KSEfDJoQc5rhrr0QtLCfpr6KnyxjMee4/edit#gid=71971023"",""Expired!E2:E""),Month(importrange(""https://docs.google.com/spreadsheets/d/15CJ-h55pYD1KSEfDJoQc5rhrr0QtLCfpr6KnyxjMee4/edit"&"#gid=71971023"",""Expired!a2:a""))=A37,year(importrange(""https://docs.google.com/spreadsheets/d/15CJ-h55pYD1KSEfDJoQc5rhrr0QtLCfpr6KnyxjMee4/edit#gid=71971023"",""Expired!a2:a""))=B37)"),0.0) -> 0 | I37: =sumproduct('Profit Distributions'!$B$2:$B999,Year('Profit Distributions'!$A$2:$A999)=B37,Month('Profit Distributions'!$A$2:$A999)=A37,'Profit Distributions'!$C$2:$C999<>"Savings") -> 0 | J37: =sumproduct('Profit Distributions'!$B$2:$B999,Year('Profit Distributions'!$A$2:$A999)=B37,Month('Profit Distributions'!$A$2:$A999)=A37,'Profit Distributions'!$C$2:$C999="Savings") -> 0 | K37: =C37+D37-F37-G37-E37+H37 -> -1932.45 | L37: =K37-J37 -> -1932.45 | M37: =L37+M36-I37 -> -3046.6715
A38: 7 | B38: 2025 | C38: =Sumproduct(Sales!$F$2:$F999,month(Sales!$A$2:$A999)=A38,year(Sales!$A$2:$A999)=B38) -> 4263.42 | D38: =Sumproduct('Amazon Royalties'!$E$2:$E999,month('Amazon Royalties'!$B$2:$B999)=A38,year('Amazon Royalties'!$B$2:$B999)=B38) -> 91.24263 | E38: ='Teacher Salaries'!V39 -> 2906 | F38: =Sumproduct(Expenses!$B$2:$B999,Month(Expenses!$A$2:$A999)=A38,year(Expenses!$A$2:$A999)=B38) -> 286.18 | G38: =Sumproduct('Staff Salaries'!$B$3:$B999,month('Staff Salaries'!$A$3:$A999)=$A38,year('Staff Salaries'!$A$3:$A999)=$B38) -> 1700 | H38: =IFERROR(__xludf.DUMMYFUNCTION("sumproduct(importrange(""https://docs.google.com/spreadsheets/d/15CJ-h55pYD1KSEfDJoQc5rhrr0QtLCfpr6KnyxjMee4/edit#gid=71971023"",""Expired!E2:E""),Month(importrange(""https://docs.google.com/spreadsheets/d/15CJ-h55pYD1KSEfDJoQc5rhrr0QtLCfpr6KnyxjMee4/edit"&"#gid=71971023"",""Expired!a2:a""))=A38,year(importrange(""https://docs.google.com/spreadsheets/d/15CJ-h55pYD1KSEfDJoQc5rhrr0QtLCfpr6KnyxjMee4/edit#gid=71971023"",""Expired!a2:a""))=B38)"),0.0) -> 0 | I38: =sumproduct('Profit Distributions'!$B$2:$B999,Year('Profit Distributions'!$A$2:$A999)=B38,Month('Profit Distributions'!$A$2:$A999)=A38,'Profit Distributions'!$C$2:$C999<>"Savings") -> 0 | J38: =sumproduct('Profit Distributions'!$B$2:$B999,Year('Profit Distributions'!$A$2:$A999)=B38,Month('Profit Distributions'!$A$2:$A999)=A38,'Profit Distributions'!$C$2:$C999="Savings") -> 0 | K38: =C38+D38-F38-G38-E38+H38 -> -537.51737 | L38: =K38-J38 -> -537.51737 | M38: =L38+M37-I38 -> -3584.1888
A39: 8 | B39: 2025 | C39: =Sumproduct(Sales!$F$2:$F999,month(Sales!$A$2:$A999)=A39,year(Sales!$A$2:$A999)=B39) -> 2948.53 | D39: =Sumproduct('Amazon Royalties'!$E$2:$E999,month('Amazon Royalties'!$B$2:$B999)=A39,year('Amazon Royalties'!$B$2:$B999)=B39) -> 71.646288 | E39: ='Teacher Salaries'!V40 -> 2895 | F39: =Sumproduct(Expenses!$B$2:$B999,Month(Expenses!$A$2:$A999)=A39,year(Expenses!$A$2:$A999)=B39) -> 302.64 | G39: =Sumproduct('Staff Salaries'!$B$3:$B999,month('Staff Salaries'!$A$3:$A999)=$A39,year('Staff Salaries'!$A$3:$A999)=$B39) -> 1700 | H39: =IFERROR(__xludf.DUMMYFUNCTION("sumproduct(importrange(""https://docs.google.com/spreadsheets/d/15CJ-h55pYD1KSEfDJoQc5rhrr0QtLCfpr6KnyxjMee4/edit#gid=71971023"",""Expired!E2:E""),Month(importrange(""https://docs.google.com/spreadsheets/d/15CJ-h55pYD1KSEfDJoQc5rhrr0QtLCfpr6KnyxjMee4/edit"&"#gid=71971023"",""Expired!a2:a""))=A39,year(importrange(""https://docs.google.com/spreadsheets/d/15CJ-h55pYD1KSEfDJoQc5rhrr0QtLCfpr6KnyxjMee4/edit#gid=71971023"",""Expired!a2:a""))=B39)"),0.0) -> 0 | I39: =sumproduct('Profit Distributions'!$B$2:$B999,Year('Profit Distributions'!$A$2:$A999)=B39,Month('Profit Distributions'!$A$2:$A999)=A39,'Profit Distributions'!$C$2:$C999<>"Savings") -> 0 | J39: =sumproduct('Profit Distributions'!$B$2:$B999,Year('Profit Distributions'!$A$2:$A999)=B39,Month('Profit Distributions'!$A$2:$A999)=A39,'Profit Distributions'!$C$2:$C999="Savings") -> -2140 | K39: =C39+D39-F39-G39-E39+H39 -> -1877.4637 | L39: =K39-J39 -> 262.53629 | M39: =L39+M38-I39 -> -3321.6525
A40: 9 | B40: 2025 | C40: =Sumproduct(Sales!$F$2:$F999,month(Sales!$A$2:$A999)=A40,year(Sales!$A$2:$A999)=B40) -> 4906.04 | D40: =Sumproduct('Amazon Royalties'!$E$2:$E999,month('Amazon Royalties'!$B$2:$B999)=A40,year('Amazon Royalties'!$B$2:$B999)=B40) -> 73.013122 | E40: ='Teacher Salaries'!V41 -> 2785 | F40: =Sumproduct(Expenses!$B$2:$B999,Month(Expenses!$A$2:$A999)=A40,year(Expenses!$A$2:$A999)=B40) -> 567.83 | G40: =Sumproduct('Staff Salaries'!$B$3:$B999,month('Staff Salaries'!$A$3:$A999)=$A40,year('Staff Salaries'!$A$3:$A999)=$B40) -> 1700 | H40: =IFERROR(__xludf.DUMMYFUNCTION("sumproduct(importrange(""https://docs.google.com/spreadsheets/d/15CJ-h55pYD1KSEfDJoQc5rhrr0QtLCfpr6KnyxjMee4/edit#gid=71971023"",""Expired!E2:E""),Month(importrange(""https://docs.google.com/spreadsheets/d/15CJ-h55pYD1KSEfDJoQc5rhrr0QtLCfpr6KnyxjMee4/edit"&"#gid=71971023"",""Expired!a2:a""))=A40,year(importrange(""https://docs.google.com/spreadsheets/d/15CJ-h55pYD1KSEfDJoQc5rhrr0QtLCfpr6KnyxjMee4/edit#gid=71971023"",""Expired!a2:a""))=B40)"),0.0) -> 0 | I40: =sumproduct('Profit Distributions'!$B$2:$B999,Year('Profit Distributions'!$A$2:$A999)=B40,Month('Profit Distributions'!$A$2:$A999)=A40,'Profit Distributions'!$C$2:$C999<>"Savings") -> 0 | J40: =sumproduct('Profit Distributions'!$B$2:$B999,Year('Profit Distributions'!$A$2:$A999)=B40,Month('Profit Distributions'!$A$2:$A999)=A40,'Profit Distributions'!$C$2:$C999="Savings") -> 0 | K40: =C40+D40-F40-G40-E40+H40 -> -73.776878 | L40: =K40-J40 -> -73.776878 | M40: =L40+M39-I40 -> -3395.4294
A41: 10 | B41: 2025 | C41: =Sumproduct(Sales!$F$2:$F999,month(Sales!$A$2:$A999)=A41,year(Sales!$A$2:$A999)=B41) -> 1694.82 | D41: =Sumproduct('Amazon Royalties'!$E$2:$E999,month('Amazon Royalties'!$B$2:$B999)=A41,year('Amazon Royalties'!$B$2:$B999)=B41) -> 70.780697 | E41: ='Teacher Salaries'!V42 -> 2807 | F41: =Sumproduct(Expenses!$B$2:$B999,Month(Expenses!$A$2:$A999)=A41,year(Expenses!$A$2:$A999)=B41) -> 790.39 | G41: =Sumproduct('Staff Salaries'!$B$3:$B999,month('Staff Salaries'!$A$3:$A999)=$A41,year('Staff Salaries'!$A$3:$A999)=$B41) -> 400 | H41: =IFERROR(__xludf.DUMMYFUNCTION("sumproduct(importrange(""https://docs.google.com/spreadsheets/d/15CJ-h55pYD1KSEfDJoQc5rhrr0QtLCfpr6KnyxjMee4/edit#gid=71971023"",""Expired!E2:E""),Month(importrange(""https://docs.google.com/spreadsheets/d/15CJ-h55pYD1KSEfDJoQc5rhrr0QtLCfpr6KnyxjMee4/edit"&"#gid=71971023"",""Expired!a2:a""))=A41,year(importrange(""https://docs.google.com/spreadsheets/d/15CJ-h55pYD1KSEfDJoQc5rhrr0QtLCfpr6KnyxjMee4/edit#gid=71971023"",""Expired!a2:a""))=B41)"),0.0) -> 0 | I41: =sumproduct('Profit Distributions'!$B$2:$B999,Year('Profit Distributions'!$A$2:$A999)=B41,Month('Profit Distributions'!$A$2:$A999)=A41,'Profit Distributions'!$C$2:$C999<>"Savings") -> 0 | J41: =sumproduct('Profit Distributions'!$B$2:$B999,Year('Profit Distributions'!$A$2:$A999)=B41,Month('Profit Distributions'!$A$2:$A999)=A41,'Profit Distributions'!$C$2:$C999="Savings") -> 0 | K41: =C41+D41-F41-G41-E41+H41 -> -2231.7893 | L41: =K41-J41 -> -2231.7893 | M41: =L41+M40-I41 -> -5627.2187
A42: 11 | B42: 2025 | C42: =Sumproduct(Sales!$F$2:$F999,month(Sales!$A$2:$A999)=A42,year(Sales!$A$2:$A999)=B42) -> 3881.32 | D42: =Sumproduct('Amazon Royalties'!$E$2:$E999,month('Amazon Royalties'!$B$2:$B999)=A42,year('Amazon Royalties'!$B$2:$B999)=B42) -> 35.220089 | E42: ='Teacher Salaries'!V43 -> 2807 | F42: =Sumproduct(Expenses!$B$2:$B999,Month(Expenses!$A$2:$A999)=A42,year(Expenses!$A$2:$A999)=B42) -> 594.01 | G42: =Sumproduct('Staff Salaries'!$B$3:$B999,month('Staff Salaries'!$A$3:$A999)=$A42,year('Staff Salaries'!$A$3:$A999)=$B42) -> 400 | H42: =IFERROR(__xludf.DUMMYFUNCTION("sumproduct(importrange(""https://docs.google.com/spreadsheets/d/15CJ-h55pYD1KSEfDJoQc5rhrr0QtLCfpr6KnyxjMee4/edit#gid=71971023"",""Expired!E2:E""),Month(importrange(""https://docs.google.com/spreadsheets/d/15CJ-h55pYD1KSEfDJoQc5rhrr0QtLCfpr6KnyxjMee4/edit"&"#gid=71971023"",""Expired!a2:a""))=A42,year(importrange(""https://docs.google.com/spreadsheets/d/15CJ-h55pYD1KSEfDJoQc5rhrr0QtLCfpr6KnyxjMee4/edit#gid=71971023"",""Expired!a2:a""))=B42)"),0.0) -> 0 | I42: =sumproduct('Profit Distributions'!$B$2:$B999,Year('Profit Distributions'!$A$2:$A999)=B42,Month('Profit Distributions'!$A$2:$A999)=A42,'Profit Distributions'!$C$2:$C999<>"Savings") -> 0 | J42: =sumproduct('Profit Distributions'!$B$2:$B999,Year('Profit Distributions'!$A$2:$A999)=B42,Month('Profit Distributions'!$A$2:$A999)=A42,'Profit Distributions'!$C$2:$C999="Savings") -> 0 | K42: =C42+D42-F42-G42-E42+H42 -> 115.53009 | L42: =K42-J42 -> 115.53009 | M42: =L42+M41-I42 -> -5511.6886
A43: 12 | B43: 2025 | C43: =Sumproduct(Sales!$F$2:$F999,month(Sales!$A$2:$A999)=A43,year(Sales!$A$2:$A999)=B43) -> 4071.05 | D43: =Sumproduct('Amazon Royalties'!$E$2:$E999,month('Amazon Royalties'!$B$2:$B999)=A43,year('Amazon Royalties'!$B$2:$B999)=B43) -> 44.581889 | E43: ='Teacher Salaries'!V44 -> 2377 | F43: =Sumproduct(Expenses!$B$2:$B999,Month(Expenses!$A$2:$A999)=A43,year(Expenses!$A$2:$A999)=B43) -> 855.08 | G43: =Sumproduct('Staff Salaries'!$B$3:$B999,month('Staff Salaries'!$A$3:$A999)=$A43,year('Staff Salaries'!$A$3:$A999)=$B43) -> 400 | H43: =IFERROR(__xludf.DUMMYFUNCTION("sumproduct(importrange(""https://docs.google.com/spreadsheets/d/15CJ-h55pYD1KSEfDJoQc5rhrr0QtLCfpr6KnyxjMee4/edit#gid=71971023"",""Expired!E2:E""),Month(importrange(""https://docs.google.com/spreadsheets/d/15CJ-h55pYD1KSEfDJoQc5rhrr0QtLCfpr6KnyxjMee4/edit"&"#gid=71971023"",""Expired!a2:a""))=A43,year(importrange(""https://docs.google.com/spreadsheets/d/15CJ-h55pYD1KSEfDJoQc5rhrr0QtLCfpr6KnyxjMee4/edit#gid=71971023"",""Expired!a2:a""))=B43)"),0.0) -> 0 | I43: =sumproduct('Profit Distributions'!$B$2:$B999,Year('Profit Distributions'!$A$2:$A999)=B43,Month('Profit Distributions'!$A$2:$A999)=A43,'Profit Distributions'!$C$2:$C999<>"Savings") -> 0 | J43: =sumproduct('Profit Distributions'!$B$2:$B999,Year('Profit Distributions'!$A$2:$A999)=B43,Month('Profit Distributions'!$A$2:$A999)=A43,'Profit Distributions'!$C$2:$C999="Savings") -> 0 | K43: =C43+D43-F43-G43-E43+H43 -> 483.55189 | L43: =K43-J43 -> 483.55189 | M43: =L43+M42-I43 -> -5028.1367

Sheet Sales
A1: Date | B1: Name | C1: Amount | D1: Currency | E1: Gateway | F1: USD amount | G1: Lesson Type | H1: Amount of lessons | I1: Package | J1: Single Lesson Minutes | K1: Salary | L1: Profit | M1: Group # | N1: Total Minutes | O1: Payment ID
A2: 44732 | B2: gertruda abi mansour | C2: 142.55 | D2: EUR | E2: Wise | F2: 149.97 | G2: Group | H2: 9 | I2: yes | J2: 75 | K2: 0 | L2: 149.97 | M2: 1 | N2: 675 | O2: 438385954
A3: 44732 | B3: julia rushchenko | C3: 129 | D3: EUR | E3: Wise | F3: 135.71 | G3: Conversational | H3: 8 | I3: yes | J3: 60 | K3: 120 | L3: 15.71 | M3: - | N3: 480 | O3: 438809844
A4: 44732 | B4: anja younes | C4: 143 | D4: EUR | E4: Paypal | F4: 150.44 | G4: Group | H4: 9 | I4: yes | J4: 75 | K4: 0 | L4: 150.44 | M4: 1 | N4: 675 | O4: 45X09692L1553483B
A5: 44735 | B5: hr drs r van wel | C5: 160 | D5: EUR | E5: Wise | F5: 168.32 | G5: Conversational | H5: 8 | I5: yes | J5: 60 | K5: 120 | L5: 48.32 | M5: - | N5: 480 | O5: 440292427
A6: 44736 | B6: farah afshar | C6: 28.44 | D6: USD | E6: Paypal | F6: 28.44 | G6: Prepared | H6: 1 | I6: no | J6: 60 | K6: 15 | L6: 13.44 | M6: - | N6: 60 | O6: 61V43119MX955022A
A7: 44743 | B7: zach bajaber | C7: 73.23 | D7: EUR | E7: Paypal | F7: 76.37 | G7: Conversational | H7: 4 | I7: no | J7: 60 | K7: 60 | L7: 16.37 | M7: - | N7: 240 | O7: 0GK08633CF767192Y
A8: 44747 | B8: farah afshar | C8: 28.44 | D8: USD | E8: Paypal | F8: 28.44 | G8: Prepared | H8: 1 | I8: no | J8: 60 | K8: 15 | L8: 13.44 | M8: - | N8: 60 | O8: 0EH8943775297013M
A9: 44749 | B9: sarah abouhamad | C9: 18.67 | D9: EUR | E9: Paypal | F9: 18.98 | G9: Conversational | H9: 1 | I9: no | J9: 60 | K9: 15 | L9: 3.98 | M9: - | N9: 60 | O9: 8VU098053M190972F
A10: 44753 | B10: anna grouzdev | C10: 28.26 | D10: EUR | E10: Paypal | F10: 28.4 | G10: Prepared | H10: 1 | I10: no | J10: 60 | K10: 15 | L10: 13.4 | M10: - | N10: 60 | O10: 9ES31142T5458205F
A11: 44760 | B11: sarah abouhamad | C11: 37.69 | D11: EUR | E11: Paypal | F11: 38.24 | G11: Conversational | H11: 2 | I11: no | J11: 60 | K11: 30 | L11: 8.24 | M11: - | N11: 120 | O11: 6P098050J4146573D
A12: 44763 | B12: frank lohÃ©ac | C12: 200 | D12: USD | E12: Wise | F12: 200 | G12: Prepared | H12: 8 | I12: yes | J12: 60 | K12: 120 | L12: 80 | M12: - | N12: 480 | O12: 458357464
A13: 44766 | B13: philip wynn jones | C13: 191.32 | D13: USD | E13: Paypal | F13: 191.32 | G13: Prepared | H13: 8 | I13: yes | J13: 60 | K13: 120 | L13: 71.32 | M13: - | N13: 480 | O13: 5XX7590587566825B
A14: 44767 | B14: katarina vasilj | C14: 190.4 | D14: EUR | E14: Paypal | F14: 194.64 | G14: Prepared | H14: 8 | I14: yes | J14: 60 | K14: 120 | L14: 74.64 | M14: - | N14: 480 | O14: 460580316
A15: 44767 | B15: federico durante | C15: 171.52 | D15: EUR | E15: Paypal | F15: 175.34 | G15: Prepared | H15: 8 | I15: yes | J15: 60 | K15: 120 | L15: 55.34 | M15: - | N15: 480 | O15: 1E864407HK994052R
A16: 44770 | B16: farah afshar | C16: 28.44 | D16: USD | E16: Paypal | F16: 28.44 | G16: Prepared | H16: 1 | I16: no | J16: 60 | K16: 15 | L16: 13.44 | M16: - | N16: 60 | O16: 1F925158B0669181C
A17: 44770 | B17: oleavanti. llc | C17: 187.85 | D17: EUR | E17: Paypal | F17: 191.46 | G17: Prepared | H17: 8 | I17: yes | J17: 60 | K17: 120 | L17: 71.46 | M17: - | N17: 480 | O17: 8F515337L44842545
A18: 44774 | B18: miriam el hilany | C18: 145 | D18: EUR | E18: Paypal | F18: 148.82 | G18: Conversational | H18: 8 | I18: yes | J18: 60 | K18: 120 | L18: 28.82 | M18: - | N18: 480 | O18: 465786012
A19: 44774 | B19: farah afshar | C19: 28.44 | D19: USD | E19: Paypal | F19: 28.44 | G19: Prepared | H19: 1 | I19: no | J19: 60 | K19: 15 | L19: 13.44 | M19: - | N19: 60 | O19: 8A364258NY629935E
A20: 44776 | B20: elena taranina | C20: 200 | D20: USD | E20: 2checkout | F20: 188.55 | G20: Prepared | H20: 8 | I20: yes | J20: 60 | K20: 120 | L20: 68.55 | M20: - | N20: 480 | O20: 188277549
A21: 44781 | B21: zach bajaber | C21: 74.91 | D21: EUR | E21: Paypal | F21: 76.39 | G21: Conversational | H21: 4 | I21: no | J21: 60 | K21: 60 | L21: 16.39 | M21: - | N21: 240 | O21: 5WE506375B487062L
A22: 44781 | B22: sarah abouhamad | C22: 40 | D22: USD | E22: 2checkout | F22: 37.35 | G22: Prepared | H22: 2 | I22: no | J22: 60 | K22: 30 | L22: 7.35 | N22: 120 | O22: 188636694
A23: 44784 | B23: sevag toujian | C23: 200 | D23: USD | E23: 2checkout | F23: 188.55 | G23: Group | H23: 12 | I23: yes | J23: 75 | K23: 225 | L23: -36.45 | M23: 2 | N23: 900 | O23: 189002401
A24: 44785 | B24: mckenna mills | C24: 200 | D24: USD | E24: 2checkout | F24: 188.55 | G24: Group | H24: 12 | I24: yes | J24: 75 | K24: 0 | L24: 188.55 | M24: 2 | N24: 900 | O24: 188840032
A25: 44785 | B25: maya abood | C25: 200 | D25: USD | E25: 2checkout | F25: 188.55 | G25: Group | H25: 12 | I25: yes | J25: 75 | K25: 0 | L25: 188.55 | M25: 2 | N25: 900 | O25: 188915011
A26: 44785 | B26: renee nassar | C26: 200 | D26: USD | E26: 2checkout | F26: 188.55 | G26: Prepared | H26: 8 | I26: yes | J26: 60 | K26: 120 | L26: 68.55 | M26: - | N26: 480 | O26: 188786366
A27: 44786 | B27: tony gualtieri | C27: 200 | D27: USD | E27: 2checkout | F27: 188.55 | G27: Prepared | H27: 8 | I27: yes | J27: 60 | K27: 120 | L27: 68.55 | M27: - | N27: 480 | O27: 188813576
A28: 44787 | B28: tanja traboulsi | C28: 140.26 | D28: EUR | E28: 2checkout | F28: 125.93 | G28: Conversational | H28: 8 | I28: yes | J28: 60 | K28: 120 | L28: 5.93 | M28: - | N28: 480 | O28: 189095677
A29: 44788 | B29: farah afshar | C29: 30 | D29: USD | E29: 2checkout | F29: 27.9 | G29: Prepared | H29: 1 | I29: no | J29: 60 | K29: 15 | L29: 12.9 | M29: - | N29: 60 | O29: 189582776
A30: 44810 | B30: jessica gerschultz | C30: 200 | D30: USD | E30: 2checkout | F30: 188.55 | G30: Prepared | H30: 8 | I30: yes | J30: 60 | K30: 120 | L30: 68.55 | M30: - | N30: 480 | O30: 190990762
A31: 44812 | B31: erika whitmore | C31: 80 | D31: USD | E31: 2checkout | F31: 75.15 | G31: Conversational | H31: 4 | I31: no | J31: 60 | K31: 60 | L31: 15.15 | M31: - | N31: 240 | O31: 190713130
A32: 44813 | B32: danny hage | C32: 200 | D32: USD | E32: 2checkout | F32: 188.55 | G32: Prepared | H32: 8 | I32: yes | J32: 60 | K32: 120 | L32: 68.55 | M32: - | N32: 480 | O32: 191033346
A33: 44813 | B33: octavia purdy | C33: 200 | D33: USD | E33: 2checkout | F33: 188.55 | G33: Prepared | H33: 8 | I33: yes | J33: 60 | K33: 120 | L33: 68.55 | M33: - | N33: 480 | O33: 190838946
A34: 44813 | B34: nina lacaprara | C34: 30 | D34: USD | E34: 2checkout | F34: 27.9 | G34: Prepared | H34: 1 | I34: no | J34: 60 | K34: 15 | L34: 12.9 | M34: - | N34: 60 | O34: 190805518
A35: 44815 | B35: ann marie sabath | C35: 200 | D35: USD | E35: 2checkout | F35: 188.55 | G35: Prepared | H35: 8 | I35: yes | J35: 60 | K35: 120 | L35: 68.55 | M35: - | N35: 480 | O35: 191243534
A36: 44816 | B36: sarah abouhamad | C36: 40 | D36: USD | E36: 2checkout | F36: 37.35 | G36: Conversational | H36: 2 | I36: no | J36: 60 | K36: 30 | L36: 7.35 | M36: - | N36: 120 | O36: 191583179
A37: 44821 | B37: nina lacaprara | C37: 30 | D37: USD | E37: 2checkout | F37: 27.9 | G37: Prepared | H37: 1 | I37: no | J37: 60 | K37: 15 | L37: 12.9 | M37: - | N37: 60 | O37: 191973369
... A46: 44849 | B46: nina lacaprara | C46: 200 | D46: USD | E46: 2checkout | F46: 188.55 | G46: Prepared | H46: 8 | I46: yes | J46: 60 | K46: 120 | L46: 68.55 | M46: - | N46: 480 | O46: 193738864
A47: 44849 | B47: jonathan donovan | C47: 200 | D47: USD | E47: 2checkout | F47: 188.55 | G47: Group | H47: 12 | I47: yes | J47: 75 | K47: 225 | L47: -36.45 | M47: 3 | N47: 900 | O47: 193793492
A48: 44853 | B48: sevag toujian | C48: 200 | D48: USD | E48: 2checkout | F48: 188.55 | G48: Group | H48: 12 | I48: yes | J48: 75 | K48: 0 | L48: 188.55 | M48: 3 | N48: 900 | O48: 194615564
A49: 44855 | B49: renee nassar | C49: 200 | D49: USD | E49: 2checkout | F49: 188.55 | G49: Prepared | H49: 8 | I49: yes | J49: 60 | K49: 120 | L49: 68.55 | M49: - | N49: 480 | O49: 194153606
A50: 44862 | B50: alessandra tadei | C50: 200 | D50: USD | E50: 2checkout | F50: 188.55 | G50: Prepared | H50: 8 | I50: yes | J50: 60 | K50: 120 | L50: 68.55 | M50: - | N50: 480 | O50: 194643653
A51: 44868 | B51: octavia purdy | C51: 200 | D51: USD | E51: 2checkout | F51: 188.55 | G51: Prepared | H51: 8 | I51: yes | J51: 60 | K51: 120 | L51: 68.55 | M51: - | N51: 480 | O51: 195171061
A52: 44879 | B52: federico durante | C52: 171.52 | D52: EUR | E52: Paypal | F52: 176.99 | G52: Prepared | H52: 8 | I52: yes | J52: 45 | K52: 90 | L52: 86.99 | N52: 360 | O52: 8D114385UT3118807
A53: 44880 | B53: tony gualtieri | C53: 400 | D53: USD | E53: 2checkout | F53: 377.55 | G53: Prepared | H53: 16 | I53: yes | J53: 60 | K53: 240 | L53: 137.55 | M53: - | N53: 960 | O53: 196568327
A54: 44882 | B54: miriam el hilany | C54: 145 | D54: USD | E54: 2checkout | F54: 136.58 | G54: Conversational | H54: 8 | I54: yes | J54: 60 | K54: 120 | L54: 16.58 | M54: - | N54: 480 | O54: 196241009
A55: 44890 | B55: mckenna mills | C55: 190 | D55: EUR | E55: Wise | F55: 197.86 | G55: Group | H55: 12 | I55: yes | J55: 75 | K55: 0 | L55: 197.86 | M55: 3 | N55: 900 | O55: 546475861
A56: 44896 | B56: anthony barakat | C56: 20 | D56: USD | E56: 2checkout | F56: 18.45 | G56: Conversational | H56: 1 | I56: no | J56: 60 | K56: 15 | L56: 3.45 | N56: 60 | O56: 197428110
A57: 44896 | B57: oliver black | C57: 200 | D57: USD | E57: 2checkout | F57: 188.55 | G57: Prepared | H57: 8 | I57: yes | J57: 60 | K57: 120 | L57: 68.55 | N57: 480 | O57: 197205760
A58: 44897 | B58: nina lacaprara | C58: 200 | D58: USD | E58: 2checkout | F58: 188.55 | G58: Prepared | H58: 8 | I58: yes | J58: 60 | K58: 120 | L58: 68.55 | N58: 480 | O58: 197997169
A59: 44900 | B59: anthony barakat | C59: 145 | D59: USD | E59: 2checkout | F59: 136.58 | G59: Conversational | H59: 8 | I59: yes | J59: 60 | K59: 120 | L59: 16.58 | N59: 480 | O59: 198044202
A60: 44906 | B60: giulio iacobelli | C60: 145 | D60: USD | E60: 2checkout | F60: 136.58 | G60: Conversational | H60: 8 | I60: yes | J60: 60 | K60: 120 | L60: 16.58 | N60: 480 | O60: 198341245
A61: 44907 | B61: zach bajaber | C61: 80 | D61: USD | E61: 2checkout | F61: 75.15 | G61: Conversational | H61: 4 | I61: no | J61: 60 | K61: 60 | L61: 15.15 | N61: 240 | O61: 198610975
A62: 44912 | B62: tony gualtieri | C62: 200 | D62: USD | E62: 2checkout | F62: 188.55 | G62: Prepared | H62: 8 | I62: yes | J62: 60 | K62: 120 | L62: 68.55 | N62: 480 | O62: 198955210
A63: 44919 | B63: agdaliya mikhalkova | C63: 165.98 | D63: GBP | E63: 2checkout | F63: 175.57 | G63: Group | H63: 12 | I63: yes | J63: 75 | K63: 225 | L63: -49.43 | M63: 4 | N63: 900 | O63: 199195804
A64: 44922 | B64: julia rushchenko | C64: 145 | D64: USD | E64: 2checkout | F64: 136.58 | G64: Conversational | H64: 8 | I64: yes | J64: 60 | K64: 120 | L64: 16.58 | N64: 480 | O64: 199724800
A65: 44923 | B65: chelsea el-azzi | C65: 200 | D65: USD | E65: 2checkout | F65: 188.55 | G65: Prepared | H65: 8 | I65: yes | J65: 60 | K65: 120 | L65: 68.55 | N65: 480 | O65: 200044299
A66: 44928 | B66: natalie hammoud | C66: 200 | D66: USD | E66: 2checkout | F66: 188.55 | G66: Group | H66: 12 | I66: yes | J66: 75 | K66: 0 | L66: 188.55 | M66: 4 | N66: 900 | O66: 200623078
A67: 44928 | B67: alida | C67: 145 | D67: EUR | E67: Wise | F67: 154.82 | G67: Conversational | H67: 8 | I67: yes | J67: 60 | K67: 120 | L67: 34.82 | N67: 480 | O67: 575395007
A68: 44930 | B68: ghadi tayeh | C68: 20 | D68: USD | E68: 2checkout | F68: 18.45 | G68: Conversational | H68: 1 | I68: no | J68: 60 | K68: 15 | L68: 3.45 | N68: 60 | O68: 200240276
A69: 44930 | B69: sophie kenos | C69: 200 | D69: USD | E69: 2checkout | F69: 188.55 | G69: Prepared | H69: 8 | I69: yes | J69: 60 | K69: 120 | L69: 68.55 | N69: 480 | O69: 200424744
A70: 44931 | B70: jason corey | C70: 200 | D70: USD | E70: 2checkout | F70: 188.55 | G70: Group | H70: 12 | I70: yes | J70: 75 | K70: 0 | L70: 188.55 | M70: 4 | N70: 900 | O70: 200215214
A71: 44932 | B71: anthony wubbena | C71: 200 | D71: USD | E71: 2checkout | F71: 188.55 | G71: Group | H71: 12 | I71: yes | J71: 75 | K71: 0 | L71: 188.55 | M71: 4 | N71: 900 | O71: 200213560
A72: 44932 | B72: somaya jalal | C72: 200 | D72: USD | E72: 2checkout | F72: 188.55 | G72: Group | H72: 12 | I72: yes | J72: 75 | K72: 225 | L72: -36.45 | M72: 5 | N72: 900 | O72: 200656844
A73: 44932 | B73: leah halcomb | C73: 200 | D73: USD | E73: 2checkout | F73: 188.55 | G73: Prepared | H73: 8 | I73: yes | J73: 60 | K73: 120 | L73: 68.55 | M73: - | N73: 480 | O73: 200770333
A74: 44933 | B74: mike calvin | C74: 200 | D74: USD | E74: 2checkout | F74: 188.55 | G74: Group | H74: 12 | I74: yes | J74: 75 | K74: 0 | L74: 188.55 | M74: 4 | N74: 900 | O74: 201013561
A75: 44934 | B75: ramzi sleiman | C75: 40 | D75: USD | E75: 2checkout | F75: 37.35 | G75: Conversational | H75: 2 | I75: no | J75: 60 | K75: 30 | L75: 7.35 | N75: 120 | O75: 200944513
A76: 44935 | B76: noura kiridly | C76: 200 | D76: USD | E76: 2checkout | F76: 188.55 | G76: Group | H76: 12 | I76: yes | J76: 75 | K76: 0 | L76: 188.55 | M76: 5 | N76: 900 | O76: 200699437
A77: 44936 | B77: jeremiah carter | C77: 200 | D77: USD | E77: 2checkout | F77: 188.55 | G77: Prepared | H77: 8 | I77: yes | J77: 60 | K77: 120 | L77: 68.55 | N77: 480 | O77: 200831424
A78: 44938 | B78: jonathan donovan | C78: 165.02 | D78: GBP | E78: 2checkout | F78: 175.57 | G78: Group | H78: 12 | I78: yes | J78: 75 | K78: 225 | L78: -49.43 | M78: 3 | N78: 900 | O78: 201511886
A79: 44939 | B79: sevag toujian | C79: 200 | D79: USD | E79: 2checkout | F79: 188.55 | G79: Group | H79: 12 | I79: yes | J79: 75 | K79: 0 | L79: 188.55 | M79: 3 | N79: 900 | O79: 201192935
A80: 44940 | B80: emil naamani | C80: 200 | D80: USD | E80: 2checkout | F80: 188.55 | G80: Prepared | H80: 8 | I80: yes | J80: 60 | K80: 120 | L80: 68.55 | N80: 480 | O80: 201272238
A81: 44942 | B81: sophie stansfield | C81: 200 | D81: USD | E81: 2checkout | F81: 188.55 | G81: Group | H81: 12 | I81: yes | J81: 75 | K81: 225 | L81: -36.45 | M81: 6 | N81: 900 | O81: 201514663
A82: 44943 | B82: zach bajaber | C82: 80 | D82: USD | E82: 2checkout | F82: 75.15 | G82: Conversational | H82: 4 | I82: no | J82: 60 | K82: 60 | L82: 15.15 | N82: 240 | O82: 201627806
A83: 44943 | B83: helena nelson | C83: 30 | D83: USD | E83: 2checkout | F83: 27.9 | G83: Prepared | H83: 1 | I83: no | J83: 60 | K83: 15 | L83: 12.9 | N83: 60 | O83: 201540651
A84: 44943 | B84: kelly sciandra | C84: 200 | D84: USD | E84: 2checkout | F84: 188.55 | G84: Group | H84: 12 | I84: yes | J84: 75 | K84: 0 | L84: 188.55 | M84: 6 | N84: 900 | O84: 201907068
A85: 44944 | B85: renee nassar | C85: 200 | D85: USD | E85: 2checkout | F85: 188.55 | G85: Prepared | H85: 8 | I85: yes | J85: 60 | K85: 120 | L85: 68.55 | N85: 480 | O85: 201727220
A86: 44945 | B86: ghadi tayeh | C86: 20 | D86: USD | E86: 2checkout | F86: 18.45 | G86: Conversational | H86: 1 | I86: no | J86: 60 | K86: 15 | L86: 3.45 | N86: 60 | O86: 201998064
A87: 44946 | B87: helena nelson | C87: 184.93 | D87: EUR | E87: 2checkout | F87: 175.57 | G87: Group | H87: 12 | I87: yes | J87: 75 | K87: 0 | L87: 175.57 | M87: 6 | N87: 900 | O87: 201871295
A88: 44947 | B88: nina lacaprara | C88: 200 | D88: USD | E88: 2checkout | F88: 188.55 | G88: Prepared | H88: 8 | I88: yes | J88: 60 | K88: 120 | L88: 68.55 | N88: 480 | O88: 201787760
A89: 44947 | B89: tony gualtieri | C89: 200 | D89: USD | E89: 2checkout | F89: 188.55 | G89: Prepared | H89: 8 | I89: yes | J89: 60 | K89: 120 | L89: 68.55 | N89: 480 | O89: 201842985
A90: 44947 | B90: polina tsapko | C90: 30 | D90: USD | E90: 2checkout | F90: 27.9 | G90: Prepared | H90: 1 | I90: no | J90: 60 | K90: 15 | L90: 12.9 | N90: 60 | O90: 201910007
A91: 44949 | B91: gertruda abi mansour | C91: 184.25 | D91: EUR | E91: Wise | F91: 200.32 | G91: Group | H91: 12 | I91: yes | J91: 75 | K91: 0 | L91: 200.32 | M91: 5 | N91: 900 | O91: 590830785
A92: 44949 | B92: chris wehbe | C92: 30 | D92: USD | E92: 2checkout | F92: 27.9 | G92: Prepared | H92: 1 | I92: no | J92: 60 | K92: 15 | L92: 12.9 | N92: 60 | O92: 201954239
A93: 44951 | B93: lauren blackwell | C93: 162.77 | D93: EUR | E93: Wise | F93: 177.78 | G93: Group | H93: 12 | I93: yes | J93: 75 | K93: 0 | L93: 177.78 | M93: 6 | N93: 900 | O93: 592848975
A94: 44951 | B94: mohamad majzoub | C94: 200 | D94: USD | E94: 2checkout | F94: 188.55 | G94: Prepared | H94: 8 | I94: yes | J94: 60 | K94: 120 | L94: 68.55 | N94: 480 | O94: 202252937
A95: 44954 | B95: florence hajj assaf | C95: 40.12 | D95: CAD | E95: 2checkout | F95: 22.15 | G95: Prepared | H95: 1 | I95: no | J95: 60 | K95: 15 | L95: 7.15 | N95: 60 | O95: 202621339
A96: 44955 | B96: chelsea el-azzi | C96: 200 | D96: USD | E96: 2checkout | F96: 188.55 | G96: Prepared | H96: 8 | I96: yes | J96: 60 | K96: 120 | L96: 68.55 | N96: 480 | O96: 202228235
A97: 44956 | B97: elissar saleh | C97: 145 | D97: USD | E97: 2checkout | F97: 136.58 | G97: Conversational | H97: 8 | I97: yes | J97: 60 | K97: 120 | L97: 16.58 | N97: 480 | O97: 202991148
A98: 44956 | B98: chris wehbe | C98: 200 | D98: USD | E98: 2checkout | F98: 188.55 | G98: Prepared | H98: 8 | I98: yes | J98: 60 | K98: 120 | L98: 68.55 | N98: 480 | O98: 202657730
A99: 44956 | B99: miriam el hilany | C99: 145 | D99: USD | E99: 2checkout | F99: 136.58 | G99: Conversational | H99: 8 | I99: yes | J99: 60 | K99: 120 | L99: 16.58 | N99: 480 | O99: 203000841
A100: 44958 | B100: mckenna mills | C100: 170 | D100: EUR | E100: Wise | F100: 187.16 | G100: Group | H100: 12 | I100: yes | J100: 75 | K100: 0 | L100: 187.16 | M100: 3 | N100: 900 | O100: 598379310
A101: 44959 | B101: ghadi tayeh | C101: 20 | D101: USD | E101: 2checkout | F101: 18.45 | G101: Conversational | H101: 1 | I101: no | J101: 60 | K101: 15 | L101: 3.45 | N101: 60 | O101: 202828670
A102: 44960 | B102: ghadi tayeh | C102: 20 | D102: USD | E102: 2checkout | F102: 18.45 | G102: Conversational | H102: 1 | I102: no | J102: 60 | K102: 15 | L102: 3.45 | N102: 60 | O102: 202752042
A103: 44960 | B103: florence hajj assaf | C103: 265.79 | D103: CAD | E103: 2checkout | F103: 175.57 | G103: Prepared | H103: 8 | I103: yes | J103: 60 | K103: 120 | L103: 55.57 | N103: 480 | O103: 202960183
A104: 44962 | B104: rose wyatt | C104: 20 | D104: USD | E104: 2checkout | F104: 18.45 | G104: Conversational | H104: 1 | I104: no | J104: 60 | K104: 15 | L104: 3.45 | N104: 60 | O104: 203440863
A105: 44963 | B105: polina tsapko | C105: 30 | D105: USD | E105: 2checkout | F105: 27.9 | G105: Prepared | H105: 1 | I105: no | J105: 60 | K105: 15 | L105: 12.9 | N105: 60 | O105: 203264064
A106: 44965 | B106: janice chaoul | C106: 200 | D106: USD | E106: 2checkout | F106: 188.55 | G106: Prepared | H106: 8 | I106: yes | J106: 60 | K106: 120 | L106: 68.55 | N106: 480 | O106: 203303009
A107: 44965 | B107: jared ferrell | C107: 200 | D107: USD | E107: 2checkout | F107: 188.55 | G107: Prepared | H107: 8 | I107: yes | J107: 60 | K107: 120 | L107: 68.55 | N107: 480 | O107: 203405828
A108: 44966 | B108: ghadi tayeh | C108: 20 | D108: USD | E108: 2checkout | F108: 18.45 | G108: Conversational | H108: 1 | I108: no | J108: 60 | K108: 15 | L108: 3.45 | N108: 60 | O108: 203310532
...

Sheet Student Pivot

Sheet Sales Pivot
H24: 0

Sheet Expenses
A1: Payment Date | B1: Payment Amount | C1: Receiver | D1: Reason
A2: 44736 | B2: 6.46 | C2: Facebook | D2: Ads
A3: 44744 | B3: 15.99 | C3: Rapidgator | D3: Subscription
A4: 44746 | B4: 32.54 | C4: Shopify | D4: Subscription
A5: 44747 | B5: 10.78 | C5: Saleshandy | D5: Subscription
A6: 44776 | B6: 29 | C6: Shopify | D6: Subscription
A7: 44781 | B7: 100 | C7: SGBL | D7: World Debit Card
A8: 44782 | B8: 26.26 | C8: Bank | D8: Transfer fee
A9: 44783 | B9: 1.95 | C9: Facebook | D9: Ads
A10: 44784 | B10: 18.9 | C10: NitroPack | D10: Subscription
A11: 44791 | B11: 47.41 | C11: Bank | D11: Transfer fee
A12: 44800 | B12: 75 | C12: Facebook | D12: Ads
A13: 44806 | B13: 57.3 | C13: Shopify | D13: Subscription
... A141: 45148 | B141: 3 | C141: 2checkout | D141: Transfer fee
A142: 45148 | B142: 39..84 | C142: Payoneer | D142: Transfer fee
A143: 45149 | B143: 21 | C143: Nitropack | D143: Subscription
A144: 45149 | B144: 14.39 | C144: Wise | D144: Transfer fee
A145: 45152 | B145: 20 | C145: ChatGPT | D145: Subscription
A146: 45153 | B146: 59 | C146: Howuku | D146: Subscription
A147: 45153 | B147: 5 | C147: Cloudflare | D147: Subscription
A148: 45154 | B148: 4.84 | C148: Cloudflare | D148: Subscription
A149: 45155 | B149: 10 | C149: SGBL | D149: Transfer fee
A150: 45157 | B150: 29 | C150: Cockatoo | D150: Subscription
A151: 45162 | B151: 3 | C151: 2checkout | D151: Transfer fee
A152: 45163 | B152: 18.56 | C152: Payoneer | D152: Transfer fee
A153: 45164 | B153: 14.99 | C153: Zoom | D153: Subscription
A154: 45166 | B154: 77.2 | C154: Shopify | D154: Subscription
... A475: 46023 | B475: 117.6 | C475: Google Gsuite | D475: Subscription

Sheet Pivot Table 6

Sheet Amazon Royalties
A1: Marketplace | B1: Date | C1: Currency | D1: Payout Amount | E1: USD Amount
A2: Amazon.com.au | B2: 42063 | C2: USD | D2: 4.54 | E2: =IFERROR(__xludf.DUMMYFUNCTION("IF(C2=""USD"", D2, IFERROR( D2 * INDEX(GOOGLEFINANCE(CONCATENATE(""CURRENCY:"", C2, ""USD""), ""close"", B2), 2, 2), IFERROR( D2 * INDEX(GOOGLEFINANCE(CONCATENATE(""CURRENCY:"", C2, ""USD""), ""close"", B2 - 1), 2, 2), D2 * INDEX(GO"&"OGLEFINANCE(CONCATENATE(""CURRENCY:"", C2, ""USD""), ""close"", B2 + 1), 2, 2) ) ) )"),4.54) -> 4.54
A3: CreateSpace UK | B3: 42153 | C3: USD | D3: 158.2 | E3: =IFERROR(__xludf.DUMMYFUNCTION("IF(C3=""USD"", D3, IFERROR( D3 * INDEX(GOOGLEFINANCE(CONCATENATE(""CURRENCY:"", C3, ""USD""), ""close"", B3), 2, 2), IFERROR( D3 * INDEX(GOOGLEFINANCE(CONCATENATE(""CURRENCY:"", C3, ""USD""), ""close"", B3 - 1), 2, 2), D3 * INDEX(GO"&"OGLEFINANCE(CONCATENATE(""CURRENCY:"", C3, ""USD""), ""close"", B3 + 1), 2, 2) ) ) )"),158.2) -> 158.2
A4: Amazon.it | B4: 42153 | C4: USD | D4: 10.08 | E4: =IFERROR(__xludf.DUMMYFUNCTION("IF(C4=""USD"", D4, IFERROR( D4 * INDEX(GOOGLEFINANCE(CONCATENATE(""CURRENCY:"", C4, ""USD""), ""close"", B4), 2, 2), IFERROR( D4 * INDEX(GOOGLEFINANCE(CONCATENATE(""CURRENCY:"", C4, ""USD""), ""close"", B4 - 1), 2, 2), D4 * INDEX(GO"&"OGLEFINANCE(CONCATENATE(""CURRENCY:"", C4, ""USD""), ""close"", B4 + 1), 2, 2) ) ) )"),10.08) -> 10.08
A5: Amazon.co.uk | B5: 42153 | C5: USD | D5: 85.67 | E5: =IFERROR(__xludf.DUMMYFUNCTION("IF(C5=""USD"", D5, IFERROR( D5 * INDEX(GOOGLEFINANCE(CONCATENATE(""CURRENCY:"", C5, ""USD""), ""close"", B5), 2, 2), IFERROR( D5 * INDEX(GOOGLEFINANCE(CONCATENATE(""CURRENCY:"", C5, ""USD""), ""close"", B5 - 1), 2, 2), D5 * INDEX(GO"&"OGLEFINANCE(CONCATENATE(""CURRENCY:"", C5, ""USD""), ""close"", B5 + 1), 2, 2) ) ) )"),85.67) -> 85.67
A6: CreateSpace US | B6: 42153 | C6: USD | D6: 745.46 | E6: =IFERROR(__xludf.DUMMYFUNCTION("IF(C6=""USD"", D6, IFERROR( D6 * INDEX(GOOGLEFINANCE(CONCATENATE(""CURRENCY:"", C6, ""USD""), ""close"", B6), 2, 2), IFERROR( D6 * INDEX(GOOGLEFINANCE(CONCATENATE(""CURRENCY:"", C6, ""USD""), ""close"", B6 - 1), 2, 2), D6 * INDEX(GO"&"OGLEFINANCE(CONCATENATE(""CURRENCY:"", C6, ""USD""), ""close"", B6 + 1), 2, 2) ) ) )"),745.46) -> 745.46
A7: CreateSpace DE | B7: 42153 | C7: USD | D7: 33.58 | E7: =IFERROR(__xludf.DUMMYFUNCTION("IF(C7=""USD"", D7, IFERROR( D7 * INDEX(GOOGLEFINANCE(CONCATENATE(""CURRENCY:"", C7, ""USD""), ""close"", B7), 2, 2), IFERROR( D7 * INDEX(GOOGLEFINANCE(CONCATENATE(""CURRENCY:"", C7, ""USD""), ""close"", B7 - 1), 2, 2), D7 * INDEX(GO"&"OGLEFINANCE(CONCATENATE(""CURRENCY:"", C7, ""USD""), ""close"", B7 + 1), 2, 2) ) ) )"),33.58) -> 33.58
A8: Amazon.ca | B8: 42153 | C8: USD | D8: 14.28 | E8: =IFERROR(__xludf.DUMMYFUNCTION("IF(C8=""USD"", D8, IFERROR( D8 * INDEX(GOOGLEFINANCE(CONCATENATE(""CURRENCY:"", C8, ""USD""), ""close"", B8), 2, 2), IFERROR( D8 * INDEX(GOOGLEFINANCE(CONCATENATE(""CURRENCY:"", C8, ""USD""), ""close"", B8 - 1), 2, 2), D8 * INDEX(GO"&"OGLEFINANCE(CONCATENATE(""CURRENCY:"", C8, ""USD""), ""close"", B8 + 1), 2, 2) ) ) )"),14.28) -> 14.28
A9: Amazon.es | B9: 42153 | C9: USD | D9: 5.98 | E9: =IFERROR(__xludf.DUMMYFUNCTION("IF(C9=""USD"", D9, IFERROR( D9 * INDEX(GOOGLEFINANCE(CONCATENATE(""CURRENCY:"", C9, ""USD""), ""close"", B9), 2, 2), IFERROR( D9 * INDEX(GOOGLEFINANCE(CONCATENATE(""CURRENCY:"", C9, ""USD""), ""close"", B9 - 1), 2, 2), D9 * INDEX(GO"&"OGLEFINANCE(CONCATENATE(""CURRENCY:"", C9, ""USD""), ""close"", B9 + 1), 2, 2) ) ) )"),5.98) -> 5.98
A10: Amazon.com | B10: 42153 | C10: USD | D10: 322.74 | E10: =IFERROR(__xludf.DUMMYFUNCTION("IF(C10=""USD"", D10, IFERROR( D10 * INDEX(GOOGLEFINANCE(CONCATENATE(""CURRENCY:"", C10, ""USD""), ""close"", B10), 2, 2), IFERROR( D10 * INDEX(GOOGLEFINANCE(CONCATENATE(""CURRENCY:"", C10, ""USD""), ""close"", B10 - 1), 2, 2), D10 *"&" INDEX(GOOGLEFINANCE(CONCATENATE(""CURRENCY:"", C10, ""USD""), ""close"", B10 + 1), 2, 2) ) ) )"),322.74) -> 322.74
A11: Amazon.de | B11: 42153 | C11: USD | D11: 33.63 | E11: =IFERROR(__xludf.DUMMYFUNCTION("IF(C11=""USD"", D11, IFERROR( D11 * INDEX(GOOGLEFINANCE(CONCATENATE(""CURRENCY:"", C11, ""USD""), ""close"", B11), 2, 2), IFERROR( D11 * INDEX(GOOGLEFINANCE(CONCATENATE(""CURRENCY:"", C11, ""USD""), ""close"", B11 - 1), 2, 2), D11 *"&" INDEX(GOOGLEFINANCE(CONCATENATE(""CURRENCY:"", C11, ""USD""), ""close"", B11 + 1), 2, 2) ) ) )"),33.63) -> 33.63
A12: Amazon.fr | B12: 42153 | C12: USD | D12: 19.11 | E12: =IFERROR(__xludf.DUMMYFUNCTION("IF(C12=""USD"", D12, IFERROR( D12 * INDEX(GOOGLEFINANCE(CONCATENATE(""CURRENCY:"", C12, ""USD""), ""close"", B12), 2, 2), IFERROR( D12 * INDEX(GOOGLEFINANCE(CONCATENATE(""CURRENCY:"", C12, ""USD""), ""close"", B12 - 1), 2, 2), D12 *"&" INDEX(GOOGLEFINANCE(CONCATENATE(""CURRENCY:"", C12, ""USD""), ""close"", B12 + 1), 2, 2) ) ) )"),19.11) -> 19.11
A13: Amazon.com.au | B13: 42169 | C13: USD | D13: 4.5 | E13: =IFERROR(__xludf.DUMMYFUNCTION("IF(C13=""USD"", D13, IFERROR( D13 * INDEX(GOOGLEFINANCE(CONCATENATE(""CURRENCY:"", C13, ""USD""), ""close"", B13), 2, 2), IFERROR( D13 * INDEX(GOOGLEFINANCE(CONCATENATE(""CURRENCY:"", C13, ""USD""), ""close"", B13 - 1), 2, 2), D13 *"&" INDEX(GOOGLEFINANCE(CONCATENATE(""CURRENCY:"", C13, ""USD""), ""close"", B13 + 1), 2, 2) ) ) )"),4.5) -> 4.5
A14: Amazon.com | B14: 42184 | C14: USD | D14: 32.55 | E14: =IFERROR(__xludf.DUMMYFUNCTION("IF(C14=""USD"", D14, IFERROR( D14 * INDEX(GOOGLEFINANCE(CONCATENATE(""CURRENCY:"", C14, ""USD""), ""close"", B14), 2, 2), IFERROR( D14 * INDEX(GOOGLEFINANCE(CONCATENATE(""CURRENCY:"", C14, ""USD""), ""close"", B14 - 1), 2, 2), D14 *"&" INDEX(GOOGLEFINANCE(CONCATENATE(""CURRENCY:"", C14, ""USD""), ""close"", B14 + 1), 2, 2) ) ) )"),32.55) -> 32.55
A15: Amazon.ca | B15: 42184 | C15: USD | D15: 4.8 | E15: =IFERROR(__xludf.DUMMYFUNCTION("IF(C15=""USD"", D15, IFERROR( D15 * INDEX(GOOGLEFINANCE(CONCATENATE(""CURRENCY:"", C15, ""USD""), ""close"", B15), 2, 2), IFERROR( D15 * INDEX(GOOGLEFINANCE(CONCATENATE(""CURRENCY:"", C15, ""USD""), ""close"", B15 - 1), 2, 2), D15 *"&" INDEX(GOOGLEFINANCE(CONCATENATE(""CURRENCY:"", C15, ""USD""), ""close"", B15 + 1), 2, 2) ) ) )"),4.8) -> 4.8
A16: Amazon.fr | B16: 42184 | C16: USD | D16: 1.33 | E16: =IFERROR(__xludf.DUMMYFUNCTION("IF(C16=""USD"", D16, IFERROR( D16 * INDEX(GOOGLEFINANCE(CONCATENATE(""CURRENCY:"", C16, ""USD""), ""close"", B16), 2, 2), IFERROR( D16 * INDEX(GOOGLEFINANCE(CONCATENATE(""CURRENCY:"", C16, ""USD""), ""close"", B16 - 1), 2, 2), D16 *"&" INDEX(GOOGLEFINANCE(CONCATENATE(""CURRENCY:"", C16, ""USD""), ""close"", B16 + 1), 2, 2) ) ) )"),1.33) -> 1.33
A17: Amazon.co.uk | B17: 42184 | C17: USD | D17: 5.11 | E17: =IFERROR(__xludf.DUMMYFUNCTION("IF(C17=""USD"", D17, IFERROR( D17 * INDEX(GOOGLEFINANCE(CONCATENATE(""CURRENCY:"", C17, ""USD""), ""close"", B17), 2, 2), IFERROR( D17 * INDEX(GOOGLEFINANCE(CONCATENATE(""CURRENCY:"", C17, ""USD""), ""close"", B17 - 1), 2, 2), D17 *"&" INDEX(GOOGLEFINANCE(CONCATENATE(""CURRENCY:"", C17, ""USD""), ""close"", B17 + 1), 2, 2) ) ) )"),5.11) -> 5.11
A18: CreateSpace US | B18: 42184 | C18: USD | D18: 104.66 | E18: =IFERROR(__xludf.DUMMYFUNCTION("IF(C18=""USD"", D18, IFERROR( D18 * INDEX(GOOGLEFINANCE(CONCATENATE(""CURRENCY:"", C18, ""USD""), ""close"", B18), 2, 2), IFERROR( D18 * INDEX(GOOGLEFINANCE(CONCATENATE(""CURRENCY:"", C18, ""USD""), ""close"", B18 - 1), 2, 2), D18 *"&" INDEX(GOOGLEFINANCE(CONCATENATE(""CURRENCY:"", C18, ""USD""), ""close"", B18 + 1), 2, 2) ) ) )"),104.66) -> 104.66
A19: CreateSpace UK | B19: 42184 | C19: USD | D19: 37.6 | E19: =IFERROR(__xludf.DUMMYFUNCTION("IF(C19=""USD"", D19, IFERROR( D19 * INDEX(GOOGLEFINANCE(CONCATENATE(""CURRENCY:"", C19, ""USD""), ""close"", B19), 2, 2), IFERROR( D19 * INDEX(GOOGLEFINANCE(CONCATENATE(""CURRENCY:"", C19, ""USD""), ""close"", B19 - 1), 2, 2), D19 *"&" INDEX(GOOGLEFINANCE(CONCATENATE(""CURRENCY:"", C19, ""USD""), ""close"", B19 + 1), 2, 2) ) ) )"),37.6) -> 37.6
A20: Amazon.com.br | B20: 42184 | C20: USD | D20: 2 | E20: =IFERROR(__xludf.DUMMYFUNCTION("IF(C20=""USD"", D20, IFERROR( D20 * INDEX(GOOGLEFINANCE(CONCATENATE(""CURRENCY:"", C20, ""USD""), ""close"", B20), 2, 2), IFERROR( D20 * INDEX(GOOGLEFINANCE(CONCATENATE(""CURRENCY:"", C20, ""USD""), ""close"", B20 - 1), 2, 2), D20 *"&" INDEX(GOOGLEFINANCE(CONCATENATE(""CURRENCY:"", C20, ""USD""), ""close"", B20 + 1), 2, 2) ) ) )"),2.0) -> 2
A21: Amazon.co.jp | B21: 42214 | C21: USD | D21: 4.62 | E21: =IFERROR(__xludf.DUMMYFUNCTION("IF(C21=""USD"", D21, IFERROR( D21 * INDEX(GOOGLEFINANCE(CONCATENATE(""CURRENCY:"", C21, ""USD""), ""close"", B21), 2, 2), IFERROR( D21 * INDEX(GOOGLEFINANCE(CONCATENATE(""CURRENCY:"", C21, ""USD""), ""close"", B21 - 1), 2, 2), D21 *"&" INDEX(GOOGLEFINANCE(CONCATENATE(""CURRENCY:"", C21, ""USD""), ""close"", B21 + 1), 2, 2) ) ) )"),4.62) -> 4.62
A22: CreateSpace US | B22: 42214 | C22: USD | D22: 129.44 | E22: =IFERROR(__xludf.DUMMYFUNCTION("IF(C22=""USD"", D22, IFERROR( D22 * INDEX(GOOGLEFINANCE(CONCATENATE(""CURRENCY:"", C22, ""USD""), ""close"", B22), 2, 2), IFERROR( D22 * INDEX(GOOGLEFINANCE(CONCATENATE(""CURRENCY:"", C22, ""USD""), ""close"", B22 - 1), 2, 2), D22 *"&" INDEX(GOOGLEFINANCE(CONCATENATE(""CURRENCY:"", C22, ""USD""), ""close"", B22 + 1), 2, 2) ) ) )"),129.44) -> 129.44
A23: CreateSpace UK | B23: 42214 | C23: USD | D23: 20.8 | E23: =IFERROR(__xludf.DUMMYFUNCTION("IF(C23=""USD"", D23, IFERROR( D23 * INDEX(GOOGLEFINANCE(CONCATENATE(""CURRENCY:"", C23, ""USD""), ""close"", B23), 2, 2), IFERROR( D23 * INDEX(GOOGLEFINANCE(CONCATENATE(""CURRENCY:"", C23, ""USD""), ""close"", B23 - 1), 2, 2), D23 *"&" INDEX(GOOGLEFINANCE(CONCATENATE(""CURRENCY:"", C23, ""USD""), ""close"", B23 + 1), 2, 2) ) ) )"),20.8) -> 20.8
A24: CreateSpace DE | B24: 42214 | C24: USD | D24: 9.91 | E24: =IFERROR(__xludf.DUMMYFUNCTION("IF(C24=""USD"", D24, IFERROR( D24 * INDEX(GOOGLEFINANCE(CONCATENATE(""CURRENCY:"", C24, ""USD""), ""close"", B24), 2, 2), IFERROR( D24 * INDEX(GOOGLEFINANCE(CONCATENATE(""CURRENCY:"", C24, ""USD""), ""close"", B24 - 1), 2, 2), D24 *"&" INDEX(GOOGLEFINANCE(CONCATENATE(""CURRENCY:"", C24, ""USD""), ""close"", B24 + 1), 2, 2) ) ) )"),9.91) -> 9.91
A25: Amazon.ca | B25: 42214 | C25: USD | D25: 4.55 | E25: =IFERROR(__xludf.DUMMYFUNCTION("IF(C25=""USD"", D25, IFERROR( D25 * INDEX(GOOGLEFINANCE(CONCATENATE(""CURRENCY:"", C25, ""USD""), ""close"", B25), 2, 2), IFERROR( D25 * INDEX(GOOGLEFINANCE(CONCATENATE(""CURRENCY:"", C25, ""USD""), ""close"", B25 - 1), 2, 2), D25 *"&" INDEX(GOOGLEFINANCE(CONCATENATE(""CURRENCY:"", C25, ""USD""), ""close"", B25 + 1), 2, 2) ) ) )"),4.55) -> 4.55
A26: Amazon.co.uk | B26: 42214 | C26: USD | D26: 5.07 | E26: =IFERROR(__xludf.DUMMYFUNCTION("IF(C26=""USD"", D26, IFERROR( D26 * INDEX(GOOGLEFINANCE(CONCATENATE(""CURRENCY:"", C26, ""USD""), ""close"", B26), 2, 2), IFERROR( D26 * INDEX(GOOGLEFINANCE(CONCATENATE(""CURRENCY:"", C26, ""USD""), ""close"", B26 - 1), 2, 2), D26 *"&" INDEX(GOOGLEFINANCE(CONCATENATE(""CURRENCY:"", C26, ""USD""), ""close"", B26 + 1), 2, 2) ) ) )"),5.07) -> 5.07
A27: Amazon.com | B27: 42214 | C27: USD | D27: 37.21 | E27: =IFERROR(__xludf.DUMMYFUNCTION("IF(C27=""USD"", D27, IFERROR( D27 * INDEX(GOOGLEFINANCE(CONCATENATE(""CURRENCY:"", C27, ""USD""), ""close"", B27), 2, 2), IFERROR( D27 * INDEX(GOOGLEFINANCE(CONCATENATE(""CURRENCY:"", C27, ""USD""), ""close"", B27 - 1), 2, 2), D27 *"&" INDEX(GOOGLEFINANCE(CONCATENATE(""CURRENCY:"", C27, ""USD""), ""close"", B27 + 1), 2, 2) ) ) )"),37.21) -> 37.21
A28: CreateSpace DE | B28: 42245 | C28: USD | D28: 20.22 | E28: =IFERROR(__xludf.DUMMYFUNCTION("IF(C28=""USD"", D28, IFERROR( D28 * INDEX(GOOGLEFINANCE(CONCATENATE(""CURRENCY:"", C28, ""USD""), ""close"", B28), 2, 2), IFERROR( D28 * INDEX(GOOGLEFINANCE(CONCATENATE(""CURRENCY:"", C28, ""USD""), ""close"", B28 - 1), 2, 2), D28 *"&" INDEX(GOOGLEFINANCE(CONCATENATE(""CURRENCY:"", C28, ""USD""), ""close"", B28 + 1), 2, 2) ) ) )"),20.22) -> 20.22
A29: Amazon.co.uk | B29: 42245 | C29: USD | D29: 5 | E29: =IFERROR(__xludf.DUMMYFUNCTION("IF(C29=""USD"", D29, IFERROR( D29 * INDEX(GOOGLEFINANCE(CONCATENATE(""CURRENCY:"", C29, ""USD""), ""close"", B29), 2, 2), IFERROR( D29 * INDEX(GOOGLEFINANCE(CONCATENATE(""CURRENCY:"", C29, ""USD""), ""close"", B29 - 1), 2, 2), D29 *"&" INDEX(GOOGLEFINANCE(CONCATENATE(""CURRENCY:"", C29, ""USD""), ""close"", B29 + 1), 2, 2) ) ) )"),5.0) -> 5
A30: Amazon.com | B30: 42245 | C30: USD | D30: 18.04 | E30: =IFERROR(__xludf.DUMMYFUNCTION("IF(C30=""USD"", D30, IFERROR( D30 * INDEX(GOOGLEFINANCE(CONCATENATE(""CURRENCY:"", C30, ""USD""), ""close"", B30), 2, 2), IFERROR( D30 * INDEX(GOOGLEFINANCE(CONCATENATE(""CURRENCY:"", C30, ""USD""), ""close"", B30 - 1), 2, 2), D30 *"&" INDEX(GOOGLEFINANCE(CONCATENATE(""CURRENCY:"", C30, ""USD""), ""close"", B30 + 1), 2, 2) ) ) )"),18.04) -> 18.04
A31: Amazon.co.jp | B31: 42245 | C31: USD | D31: 2.05 | E31: =IFERROR(__xludf.DUMMYFUNCTION("IF(C31=""USD"", D31, IFERROR( D31 * INDEX(GOOGLEFINANCE(CONCATENATE(""CURRENCY:"", C31, ""USD""), ""close"", B31), 2, 2), IFERROR( D31 * INDEX(GOOGLEFINANCE(CONCATENATE(""CURRENCY:"", C31, ""USD""), ""close"", B31 - 1), 2, 2), D31 *"&" INDEX(GOOGLEFINANCE(CONCATENATE(""CURRENCY:"", C31, ""USD""), ""close"", B31 + 1), 2, 2) ) ) )"),2.05) -> 2.05
A32: CreateSpace UK | B32: 42245 | C32: USD | D32: 10.25 | E32: =IFERROR(__xludf.DUMMYFUNCTION("IF(C32=""USD"", D32, IFERROR( D32 * INDEX(GOOGLEFINANCE(CONCATENATE(""CURRENCY:"", C32, ""USD""), ""close"", B32), 2, 2), IFERROR( D32 * INDEX(GOOGLEFINANCE(CONCATENATE(""CURRENCY:"", C32, ""USD""), ""close"", B32 - 1), 2, 2), D32 *"&" INDEX(GOOGLEFINANCE(CONCATENATE(""CURRENCY:"", C32, ""USD""), ""close"", B32 + 1), 2, 2) ) ) )"),10.25) -> 10.25
A33: CreateSpace US | B33: 42245 | C33: USD | D33: 132.92 | E33: =IFERROR(__xludf.DUMMYFUNCTION("IF(C33=""USD"", D33, IFERROR( D33 * INDEX(GOOGLEFINANCE(CONCATENATE(""CURRENCY:"", C33, ""USD""), ""close"", B33), 2, 2), IFERROR( D33 * INDEX(GOOGLEFINANCE(CONCATENATE(""CURRENCY:"", C33, ""USD""), ""close"", B33 - 1), 2, 2), D33 *"&" INDEX(GOOGLEFINANCE(CONCATENATE(""CURRENCY:"", C33, ""USD""), ""close"", B33 + 1), 2, 2) ) ) )"),132.92) -> 132.92
A34: CreateSpace US | B34: 42276 | C34: USD | D34: 86.61 | E34: =IFERROR(__xludf.DUMMYFUNCTION("IF(C34=""USD"", D34, IFERROR( D34 * INDEX(GOOGLEFINANCE(CONCATENATE(""CURRENCY:"", C34, ""USD""), ""close"", B34), 2, 2), IFERROR( D34 * INDEX(GOOGLEFINANCE(CONCATENATE(""CURRENCY:"", C34, ""USD""), ""close"", B34 - 1), 2, 2), D34 *"&" INDEX(GOOGLEFINANCE(CONCATENATE(""CURRENCY:"", C34, ""USD""), ""close"", B34 + 1), 2, 2) ) ) )"),86.61) -> 86.61
A35: CreateSpace DE | B35: 42276 | C35: USD | D35: 20.05 | E35: =IFERROR(__xludf.DUMMYFUNCTION("IF(C35=""USD"", D35, IFERROR( D35 * INDEX(GOOGLEFINANCE(CONCATENATE(""CURRENCY:"", C35, ""USD""), ""close"", B35), 2, 2), IFERROR( D35 * INDEX(GOOGLEFINANCE(CONCATENATE(""CURRENCY:"", C35, ""USD""), ""close"", B35 - 1), 2, 2), D35 *"&" INDEX(GOOGLEFINANCE(CONCATENATE(""CURRENCY:"", C35, ""USD""), ""close"", B35 + 1), 2, 2) ) ) )"),20.05) -> 20.05
A36: Amazon.de | B36: 42276 | C36: USD | D36: 0.27 | E36: =IFERROR(__xludf.DUMMYFUNCTION("IF(C36=""USD"", D36, IFERROR( D36 * INDEX(GOOGLEFINANCE(CONCATENATE(""CURRENCY:"", C36, ""USD""), ""close"", B36), 2, 2), IFERROR( D36 * INDEX(GOOGLEFINANCE(CONCATENATE(""CURRENCY:"", C36, ""USD""), ""close"", B36 - 1), 2, 2), D36 *"&" INDEX(GOOGLEFINANCE(CONCATENATE(""CURRENCY:"", C36, ""USD""), ""close"", B36 + 1), 2, 2) ) ) )"),0.27) -> 0.27
A37: Amazon.com | B37: 42276 | C37: USD | D37: 27.04 | E37: =IFERROR(__xludf.DUMMYFUNCTION("IF(C37=""USD"", D37, IFERROR( D37 * INDEX(GOOGLEFINANCE(CONCATENATE(""CURRENCY:"", C37, ""USD""), ""close"", B37), 2, 2), IFERROR( D37 * INDEX(GOOGLEFINANCE(CONCATENATE(""CURRENCY:"", C37, ""USD""), ""close"", B37 - 1), 2, 2), D37 *"&" INDEX(GOOGLEFINANCE(CONCATENATE(""CURRENCY:"", C37, ""USD""), ""close"", B37 + 1), 2, 2) ) ) )"),27.04) -> 27.04
A38: CreateSpace UK | B38: 42276 | C38: USD | D38: 30.43 | E38: =IFERROR(__xludf.DUMMYFUNCTION("IF(C38=""USD"", D38, IFERROR( D38 * INDEX(GOOGLEFINANCE(CONCATENATE(""CURRENCY:"", C38, ""USD""), ""close"", B38), 2, 2), IFERROR( D38 * INDEX(GOOGLEFINANCE(CONCATENATE(""CURRENCY:"", C38, ""USD""), ""close"", B38 - 1), 2, 2), D38 *"&" INDEX(GOOGLEFINANCE(CONCATENATE(""CURRENCY:"", C38, ""USD""), ""close"", B38 + 1), 2, 2) ) ) )"),30.43) -> 30.43
A39: Amazon.fr | B39: 42306 | C39: USD | D39: 4.48 | E39: =IFERROR(__xludf.DUMMYFUNCTION("IF(C39=""USD"", D39, IFERROR( D39 * INDEX(GOOGLEFINANCE(CONCATENATE(""CURRENCY:"", C39, ""USD""), ""close"", B39), 2, 2), IFERROR( D39 * INDEX(GOOGLEFINANCE(CONCATENATE(""CURRENCY:"", C39, ""USD""), ""close"", B39 - 1), 2, 2), D39 *"&" INDEX(GOOGLEFINANCE(CONCATENATE(""CURRENCY:"", C39, ""USD""), ""close"", B39 + 1), 2, 2) ) ) )"),4.48) -> 4.48
A40: CreateSpace DE | B40: 42306 | C40: USD | D40: 9.91 | E40: =IFERROR(__xludf.DUMMYFUNCTION("IF(C40=""USD"", D40, IFERROR( D40 * INDEX(GOOGLEFINANCE(CONCATENATE(""CURRENCY:"", C40, ""USD""), ""close"", B40), 2, 2), IFERROR( D40 * INDEX(GOOGLEFINANCE(CONCATENATE(""CURRENCY:"", C40, ""USD""), ""close"", B40 - 1), 2, 2), D40 *"&" INDEX(GOOGLEFINANCE(CONCATENATE(""CURRENCY:"", C40, ""USD""), ""close"", B40 + 1), 2, 2) ) ) )"),9.91) -> 9.91
A41: CreateSpace US | B41: 42306 | C41: USD | D41: 292.13 | E41: =IFERROR(__xludf.DUMMYFUNCTION("IF(C41=""USD"", D41, IFERROR( D41 * INDEX(GOOGLEFINANCE(CONCATENATE(""CURRENCY:"", C41, ""USD""), ""close"", B41), 2, 2), IFERROR( D41 * INDEX(GOOGLEFINANCE(CONCATENATE(""CURRENCY:"", C41, ""USD""), ""close"", B41 - 1), 2, 2), D41 *"&" INDEX(GOOGLEFINANCE(CONCATENATE(""CURRENCY:"", C41, ""USD""), ""close"", B41 + 1), 2, 2) ) ) )"),292.13) -> 292.13
A42: Amazon.com | B42: 42306 | C42: USD | D42: 25.85 | E42: =IFERROR(__xludf.DUMMYFUNCTION("IF(C42=""USD"", D42, IFERROR( D42 * INDEX(GOOGLEFINANCE(CONCATENATE(""CURRENCY:"", C42, ""USD""), ""close"", B42), 2, 2), IFERROR( D42 * INDEX(GOOGLEFINANCE(CONCATENATE(""CURRENCY:"", C42, ""USD""), ""close"", B42 - 1), 2, 2), D42 *"&" INDEX(GOOGLEFINANCE(CONCATENATE(""CURRENCY:"", C42, ""USD""), ""close"", B42 + 1), 2, 2) ) ) )"),25.85) -> 25.85
A43: Amazon.de | B43: 42306 | C43: USD | D43: 0.22 | E43: =IFERROR(__xludf.DUMMYFUNCTION("IF(C43=""USD"", D43, IFERROR( D43 * INDEX(GOOGLEFINANCE(CONCATENATE(""CURRENCY:"", C43, ""USD""), ""close"", B43), 2, 2), IFERROR( D43 * INDEX(GOOGLEFINANCE(CONCATENATE(""CURRENCY:"", C43, ""USD""), ""close"", B43 - 1), 2, 2), D43 *"&" INDEX(GOOGLEFINANCE(CONCATENATE(""CURRENCY:"", C43, ""USD""), ""close"", B43 + 1), 2, 2) ) ) )"),0.22) -> 0.22
A44: Amazon.co.uk | B44: 42306 | C44: USD | D44: 15.39 | E44: =IFERROR(__xludf.DUMMYFUNCTION("IF(C44=""USD"", D44, IFERROR( D44 * INDEX(GOOGLEFINANCE(CONCATENATE(""CURRENCY:"", C44, ""USD""), ""close"", B44), 2, 2), IFERROR( D44 * INDEX(GOOGLEFINANCE(CONCATENATE(""CURRENCY:"", C44, ""USD""), ""close"", B44 - 1), 2, 2), D44 *"&" INDEX(GOOGLEFINANCE(CONCATENATE(""CURRENCY:"", C44, ""USD""), ""close"", B44 + 1), 2, 2) ) ) )"),15.39) -> 15.39
A45: CreateSpace DE | B45: 42306 | C45: USD | D45: 9.91 | E45: =IFERROR(__xludf.DUMMYFUNCTION("IF(C45=""USD"", D45, IFERROR( D45 * INDEX(GOOGLEFINANCE(CONCATENATE(""CURRENCY:"", C45, ""USD""), ""close"", B45), 2, 2), IFERROR( D45 * INDEX(GOOGLEFINANCE(CONCATENATE(""CURRENCY:"", C45, ""USD""), ""close"", B45 - 1), 2, 2), D45 *"&" INDEX(GOOGLEFINANCE(CONCATENATE(""CURRENCY:"", C45, ""USD""), ""close"", B45 + 1), 2, 2) ) ) )"),9.91) -> 9.91
A46: CreateSpace UK | B46: 42306 | C46: USD | D46: 40.75 | E46: =IFERROR(__xludf.DUMMYFUNCTION("IF(C46=""USD"", D46, IFERROR( D46 * INDEX(GOOGLEFINANCE(CONCATENATE(""CURRENCY:"", C46, ""USD""), ""close"", B46), 2, 2), IFERROR( D46 * INDEX(GOOGLEFINANCE(CONCATENATE(""CURRENCY:"", C46, ""USD""), ""close"", B46 - 1), 2, 2), D46 *"&" INDEX(GOOGLEFINANCE(CONCATENATE(""CURRENCY:"", C46, ""USD""), ""close"", B46 + 1), 2, 2) ) ) )"),40.75) -> 40.75
A47: Amazon.com.au | B47: 42322 | C47: USD | D47: 15.92 | E47: =IFERROR(__xludf.DUMMYFUNCTION("IF(C47=""USD"", D47, IFERROR( D47 * INDEX(GOOGLEFINANCE(CONCATENATE(""CURRENCY:"", C47, ""USD""), ""close"", B47), 2, 2), IFERROR( D47 * INDEX(GOOGLEFINANCE(CONCATENATE(""CURRENCY:"", C47, ""USD""), ""close"", B47 - 1), 2, 2), D47 *"&" INDEX(GOOGLEFINANCE(CONCATENATE(""CURRENCY:"", C47, ""USD""), ""close"", B47 + 1), 2, 2) ) ) )"),15.92) -> 15.92
A48: Amazon.com.br | B48: 42338 | C48: USD | D48: 2.34 | E48: =IFERROR(__xludf.DUMMYFUNCTION("IF(C48=""USD"", D48, IFERROR( D48 * INDEX(GOOGLEFINANCE(CONCATENATE(""CURRENCY:"", C48, ""USD""), ""close"", B48), 2, 2), IFERROR( D48 * INDEX(GOOGLEFINANCE(CONCATENATE(""CURRENCY:"", C48, ""USD""), ""close"", B48 - 1), 2, 2), D48 *"&" INDEX(GOOGLEFINANCE(CONCATENATE(""CURRENCY:"", C48, ""USD""), ""close"", B48 + 1), 2, 2) ) ) )"),2.34) -> 2.34
A49: CreateSpace DE | B49: 42338 | C49: USD | D49: 18.98 | E49: =IFERROR(__xludf.DUMMYFUNCTION("IF(C49=""USD"", D49, IFERROR( D49 * INDEX(GOOGLEFINANCE(CONCATENATE(""CURRENCY:"", C49, ""USD""), ""close"", B49), 2, 2), IFERROR( D49 * INDEX(GOOGLEFINANCE(CONCATENATE(""CURRENCY:"", C49, ""USD""), ""close"", B49 - 1), 2, 2), D49 *"&" INDEX(GOOGLEFINANCE(CONCATENATE(""CURRENCY:"", C49, ""USD""), ""close"", B49 + 1), 2, 2) ) ) )"),18.98) -> 18.98
A50: Amazon.ca | B50: 42338 | C50: USD | D50: 0.15 | E50: =IFERROR(__xludf.DUMMYFUNCTION("IF(C50=""USD"", D50, IFERROR( D50 * INDEX(GOOGLEFINANCE(CONCATENATE(""CURRENCY:"", C50, ""USD""), ""close"", B50), 2, 2), IFERROR( D50 * INDEX(GOOGLEFINANCE(CONCATENATE(""CURRENCY:"", C50, ""USD""), ""close"", B50 - 1), 2, 2), D50 *"&" INDEX(GOOGLEFINANCE(CONCATENATE(""CURRENCY:"", C50, ""USD""), ""close"", B50 + 1), 2, 2) ) ) )"),0.15) -> 0.15
A51: Amazon.com | B51: 42338 | C51: USD | D51: 19.79 | E51: =IFERROR(__xludf.DUMMYFUNCTION("IF(C51=""USD"", D51, IFERROR( D51 * INDEX(GOOGLEFINANCE(CONCATENATE(""CURRENCY:"", C51, ""USD""), ""close"", B51), 2, 2), IFERROR( D51 * INDEX(GOOGLEFINANCE(CONCATENATE(""CURRENCY:"", C51, ""USD""), ""close"", B51 - 1), 2, 2), D51 *"&" INDEX(GOOGLEFINANCE(CONCATENATE(""CURRENCY:"", C51, ""USD""), ""close"", B51 + 1), 2, 2) ) ) )"),19.79) -> 19.79
A52: CreateSpace UK | B52: 42338 | C52: USD | D52: 10.02 | E52: =IFERROR(__xludf.DUMMYFUNCTION("IF(C52=""USD"", D52, IFERROR( D52 * INDEX(GOOGLEFINANCE(CONCATENATE(""CURRENCY:"", C52, ""USD""), ""close"", B52), 2, 2), IFERROR( D52 * INDEX(GOOGLEFINANCE(CONCATENATE(""CURRENCY:"", C52, ""USD""), ""close"", B52 - 1), 2, 2), D52 *"&" INDEX(GOOGLEFINANCE(CONCATENATE(""CURRENCY:"", C52, ""USD""), ""close"", B52 + 1), 2, 2) ) ) )"),10.02) -> 10.02
A53: Amazon.co.uk | B53: 42338 | C53: USD | D53: 9.77 | E53: =IFERROR(__xludf.DUMMYFUNCTION("IF(C53=""USD"", D53, IFERROR( D53 * INDEX(GOOGLEFINANCE(CONCATENATE(""CURRENCY:"", C53, ""USD""), ""close"", B53), 2, 2), IFERROR( D53 * INDEX(GOOGLEFINANCE(CONCATENATE(""CURRENCY:"", C53, ""USD""), ""close"", B53 - 1), 2, 2), D53 *"&" INDEX(GOOGLEFINANCE(CONCATENATE(""CURRENCY:"", C53, ""USD""), ""close"", B53 + 1), 2, 2) ) ) )"),9.77) -> 9.77
A54: CreateSpace US | B54: 42338 | C54: USD | D54: 123.86 | E54: =IFERROR(__xludf.DUMMYFUNCTION("IF(C54=""USD"", D54, IFERROR( D54 * INDEX(GOOGLEFINANCE(CONCATENATE(""CURRENCY:"", C54, ""USD""), ""close"", B54), 2, 2), IFERROR( D54 * INDEX(GOOGLEFINANCE(CONCATENATE(""CURRENCY:"", C54, ""USD""), ""close"", B54 - 1), 2, 2), D54 *"&" INDEX(GOOGLEFINANCE(CONCATENATE(""CURRENCY:"", C54, ""USD""), ""close"", B54 + 1), 2, 2) ) ) )"),123.86) -> 123.86
A55: CreateSpace DE | B55: 42367 | C55: USD | D55: 19.64 | E55: =IFERROR(__xludf.DUMMYFUNCTION("IF(C55=""USD"", D55, IFERROR( D55 * INDEX(GOOGLEFINANCE(CONCATENATE(""CURRENCY:"", C55, ""USD""), ""close"", B55), 2, 2), IFERROR( D55 * INDEX(GOOGLEFINANCE(CONCATENATE(""CURRENCY:"", C55, ""USD""), ""close"", B55 - 1), 2, 2), D55 *"&" INDEX(GOOGLEFINANCE(CONCATENATE(""CURRENCY:"", C55, ""USD""), ""close"", B55 + 1), 2, 2) ) ) )"),19.64) -> 19.64
A56: Amazon.it | B56: 42367 | C56: USD | D56: 0.34 | E56: =IFERROR(__xludf.DUMMYFUNCTION("IF(C56=""USD"", D56, IFERROR( D56 * INDEX(GOOGLEFINANCE(CONCATENATE(""CURRENCY:"", C56, ""USD""), ""close"", B56), 2, 2), IFERROR( D56 * INDEX(GOOGLEFINANCE(CONCATENATE(""CURRENCY:"", C56, ""USD""), ""close"", B56 - 1), 2, 2), D56 *"&" INDEX(GOOGLEFINANCE(CONCATENATE(""CURRENCY:"", C56, ""USD""), ""close"", B56 + 1), 2, 2) ) ) )"),0.34) -> 0.34
A57: Amazon.co.uk | B57: 42367 | C57: USD | D57: 9.69 | E57: =IFERROR(__xludf.DUMMYFUNCTION("IF(C57=""USD"", D57, IFERROR( D57 * INDEX(GOOGLEFINANCE(CONCATENATE(""CURRENCY:"", C57, ""USD""), ""close"", B57), 2, 2), IFERROR( D57 * INDEX(GOOGLEFINANCE(CONCATENATE(""CURRENCY:"", C57, ""USD""), ""close"", B57 - 1), 2, 2), D57 *"&" INDEX(GOOGLEFINANCE(CONCATENATE(""CURRENCY:"", C57, ""USD""), ""close"", B57 + 1), 2, 2) ) ) )"),9.69) -> 9.69
A58: Amazon.fr | B58: 42367 | C58: USD | D58: 4.43 | E58: =IFERROR(__xludf.DUMMYFUNCTION("IF(C58=""USD"", D58, IFERROR( D58 * INDEX(GOOGLEFINANCE(CONCATENATE(""CURRENCY:"", C58, ""USD""), ""close"", B58), 2, 2), IFERROR( D58 * INDEX(GOOGLEFINANCE(CONCATENATE(""CURRENCY:"", C58, ""USD""), ""close"", B58 - 1), 2, 2), D58 *"&" INDEX(GOOGLEFINANCE(CONCATENATE(""CURRENCY:"", C58, ""USD""), ""close"", B58 + 1), 2, 2) ) ) )"),4.43) -> 4.43
A59: CreateSpace US | B59: 42367 | C59: USD | D59: 122.56 | E59: =IFERROR(__xludf.DUMMYFUNCTION("IF(C59=""USD"", D59, IFERROR( D59 * INDEX(GOOGLEFINANCE(CONCATENATE(""CURRENCY:"", C59, ""USD""), ""close"", B59), 2, 2), IFERROR( D59 * INDEX(GOOGLEFINANCE(CONCATENATE(""CURRENCY:"", C59, ""USD""), ""close"", B59 - 1), 2, 2), D59 *"&" INDEX(GOOGLEFINANCE(CONCATENATE(""CURRENCY:"", C59, ""USD""), ""close"", B59 + 1), 2, 2) ) ) )"),122.56) -> 122.56
A60: Amazon.com | B60: 42367 | C60: USD | D60: 39.77 | E60: =IFERROR(__xludf.DUMMYFUNCTION("IF(C60=""USD"", D60, IFERROR( D60 * INDEX(GOOGLEFINANCE(CONCATENATE(""CURRENCY:"", C60, ""USD""), ""close"", B60), 2, 2), IFERROR( D60 * INDEX(GOOGLEFINANCE(CONCATENATE(""CURRENCY:"", C60, ""USD""), ""close"", B60 - 1), 2, 2), D60 *"&" INDEX(GOOGLEFINANCE(CONCATENATE(""CURRENCY:"", C60, ""USD""), ""close"", B60 + 1), 2, 2) ) ) )"),39.77) -> 39.77
A61: CreateSpace UK | B61: 42367 | C61: USD | D61: 19.88 | E61: =IFERROR(__xludf.DUMMYFUNCTION("IF(C61=""USD"", D61, IFERROR( D61 * INDEX(GOOGLEFINANCE(CONCATENATE(""CURRENCY:"", C61, ""USD""), ""close"", B61), 2, 2), IFERROR( D61 * INDEX(GOOGLEFINANCE(CONCATENATE(""CURRENCY:"", C61, ""USD""), ""close"", B61 - 1), 2, 2), D61 *"&" INDEX(GOOGLEFINANCE(CONCATENATE(""CURRENCY:"", C61, ""USD""), ""close"", B61 + 1), 2, 2) ) ) )"),19.88) -> 19.88
A62: CreateSpace UK | B62: 42398 | C62: USD | D62: 47.74 | E62: =IFERROR(__xludf.DUMMYFUNCTION("IF(C62=""USD"", D62, IFERROR( D62 * INDEX(GOOGLEFINANCE(CONCATENATE(""CURRENCY:"", C62, ""USD""), ""close"", B62), 2, 2), IFERROR( D62 * INDEX(GOOGLEFINANCE(CONCATENATE(""CURRENCY:"", C62, ""USD""), ""close"", B62 - 1), 2, 2), D62 *"&" INDEX(GOOGLEFINANCE(CONCATENATE(""CURRENCY:"", C62, ""USD""), ""close"", B62 + 1), 2, 2) ) ) )"),47.74) -> 47.74
A63: Amazon.com | B63: 42398 | C63: USD | D63: 26.56 | E63: =IFERROR(__xludf.DUMMYFUNCTION("IF(C63=""USD"", D63, IFERROR( D63 * INDEX(GOOGLEFINANCE(CONCATENATE(""CURRENCY:"", C63, ""USD""), ""close"", B63), 2, 2), IFERROR( D63 * INDEX(GOOGLEFINANCE(CONCATENATE(""CURRENCY:"", C63, ""USD""), ""close"", B63 - 1), 2, 2), D63 *"&" INDEX(GOOGLEFINANCE(CONCATENATE(""CURRENCY:"", C63, ""USD""), ""close"", B63 + 1), 2, 2) ) ) )"),26.56) -> 26.56
A64: Amazon.de | B64: 42398 | C64: USD | D64: 4.37 | E64: =IFERROR(__xludf.DUMMYFUNCTION("IF(C64=""USD"", D64, IFERROR( D64 * INDEX(GOOGLEFINANCE(CONCATENATE(""CURRENCY:"", C64, ""USD""), ""close"", B64), 2, 2), IFERROR( D64 * INDEX(GOOGLEFINANCE(CONCATENATE(""CURRENCY:"", C64, ""USD""), ""close"", B64 - 1), 2, 2), D64 *"&" INDEX(GOOGLEFINANCE(CONCATENATE(""CURRENCY:"", C64, ""USD""), ""close"", B64 + 1), 2, 2) ) ) )"),4.37) -> 4.37
A65: CreateSpace US | B65: 42398 | C65: USD | D65: 108.77 | E65: =IFERROR(__xludf.DUMMYFUNCTION("IF(C65=""USD"", D65, IFERROR( D65 * INDEX(GOOGLEFINANCE(CONCATENATE(""CURRENCY:"", C65, ""USD""), ""close"", B65), 2, 2), IFERROR( D65 * INDEX(GOOGLEFINANCE(CONCATENATE(""CURRENCY:"", C65, ""USD""), ""close"", B65 - 1), 2, 2), D65 *"&" INDEX(GOOGLEFINANCE(CONCATENATE(""CURRENCY:"", C65, ""USD""), ""close"", B65 + 1), 2, 2) ) ) )"),108.77) -> 108.77
A66: Amazon.de | B66: 42429 | C66: USD | D66: 4.35 | E66: =IFERROR(__xludf.DUMMYFUNCTION("IF(C66=""USD"", D66, IFERROR( D66 * INDEX(GOOGLEFINANCE(CONCATENATE(""CURRENCY:"", C66, ""USD""), ""close"", B66), 2, 2), IFERROR( D66 * INDEX(GOOGLEFINANCE(CONCATENATE(""CURRENCY:"", C66, ""USD""), ""close"", B66 - 1), 2, 2), D66 *"&" INDEX(GOOGLEFINANCE(CONCATENATE(""CURRENCY:"", C66, ""USD""), ""close"", B66 + 1), 2, 2) ) ) )"),4.35) -> 4.35
A67: Amazon.ca | B67: 42429 | C67: USD | D67: 0.13 | E67: =IFERROR(__xludf.DUMMYFUNCTION("IF(C67=""USD"", D67, IFERROR( D67 * INDEX(GOOGLEFINANCE(CONCATENATE(""CURRENCY:"", C67, ""USD""), ""close"", B67), 2, 2), IFERROR( D67 * INDEX(GOOGLEFINANCE(CONCATENATE(""CURRENCY:"", C67, ""USD""), ""close"", B67 - 1), 2, 2), D67 *"&" INDEX(GOOGLEFINANCE(CONCATENATE(""CURRENCY:"", C67, ""USD""), ""close"", B67 + 1), 2, 2) ) ) )"),0.13) -> 0.13
A68: Amazon.com | B68: 42429 | C68: USD | D68: 32.6 | E68: =IFERROR(__xludf.DUMMYFUNCTION("IF(C68=""USD"", D68, IFERROR( D68 * INDEX(GOOGLEFINANCE(CONCATENATE(""CURRENCY:"", C68, ""USD""), ""close"", B68), 2, 2), IFERROR( D68 * INDEX(GOOGLEFINANCE(CONCATENATE(""CURRENCY:"", C68, ""USD""), ""close"", B68 - 1), 2, 2), D68 *"&" INDEX(GOOGLEFINANCE(CONCATENATE(""CURRENCY:"", C68, ""USD""), ""close"", B68 + 1), 2, 2) ) ) )"),32.6) -> 32.6
A69: Amazon.fr | B69: 42429 | C69: USD | D69: 4.58 | E69: =IFERROR(__xludf.DUMMYFUNCTION("IF(C69=""USD"", D69, IFERROR( D69 * INDEX(GOOGLEFINANCE(CONCATENATE(""CURRENCY:"", C69, ""USD""), ""close"", B69), 2, 2), IFERROR( D69 * INDEX(GOOGLEFINANCE(CONCATENATE(""CURRENCY:"", C69, ""USD""), ""close"", B69 - 1), 2, 2), D69 *"&" INDEX(GOOGLEFINANCE(CONCATENATE(""CURRENCY:"", C69, ""USD""), ""close"", B69 + 1), 2, 2) ) ) )"),4.58) -> 4.58
A70: CreateSpace US | B70: 42429 | C70: USD | D70: 155.31 | E70: =IFERROR(__xludf.DUMMYFUNCTION("IF(C70=""USD"", D70, IFERROR( D70 * INDEX(GOOGLEFINANCE(CONCATENATE(""CURRENCY:"", C70, ""USD""), ""close"", B70), 2, 2), IFERROR( D70 * INDEX(GOOGLEFINANCE(CONCATENATE(""CURRENCY:"", C70, ""USD""), ""close"", B70 - 1), 2, 2), D70 *"&" INDEX(GOOGLEFINANCE(CONCATENATE(""CURRENCY:"", C70, ""USD""), ""close"", B70 + 1), 2, 2) ) ) )"),155.31) -> 155.31
A71: Amazon.co.uk | B71: 42429 | C71: USD | D71: 5.95 | E71: =IFERROR(__xludf.DUMMYFUNCTION("IF(C71=""USD"", D71, IFERROR( D71 * INDEX(GOOGLEFINANCE(CONCATENATE(""CURRENCY:"", C71, ""USD""), ""close"", B71), 2, 2), IFERROR( D71 * INDEX(GOOGLEFINANCE(CONCATENATE(""CURRENCY:"", C71, ""USD""), ""close"", B71 - 1), 2, 2), D71 *"&" INDEX(GOOGLEFINANCE(CONCATENATE(""CURRENCY:"", C71, ""USD""), ""close"", B71 + 1), 2, 2) ) ) )"),5.95) -> 5.95
A72: CreateSpace DE | B72: 42429 | C72: USD | D72: 19.75 | E72: =IFERROR(__xludf.DUMMYFUNCTION("IF(C72=""USD"", D72, IFERROR( D72 * INDEX(GOOGLEFINANCE(CONCATENATE(""CURRENCY:"", C72, ""USD""), ""close"", B72), 2, 2), IFERROR( D72 * INDEX(GOOGLEFINANCE(CONCATENATE(""CURRENCY:"", C72, ""USD""), ""close"", B72 - 1), 2, 2), D72 *"&" INDEX(GOOGLEFINANCE(CONCATENATE(""CURRENCY:"", C72, ""USD""), ""close"", B72 + 1), 2, 2) ) ) )"),19.75) -> 19.75
A73: CreateSpace UK | B73: 42429 | C73: USD | D73: 18.65 | E73: =IFERROR(__xludf.DUMMYFUNCTION("IF(C73=""USD"", D73, IFERROR( D73 * INDEX(GOOGLEFINANCE(CONCATENATE(""CURRENCY:"", C73, ""USD""), ""close"", B73), 2, 2), IFERROR( D73 * INDEX(GOOGLEFINANCE(CONCATENATE(""CURRENCY:"", C73, ""USD""), ""close"", B73 - 1), 2, 2), D73 *"&" INDEX(GOOGLEFINANCE(CONCATENATE(""CURRENCY:"", C73, ""USD""), ""close"", B73 + 1), 2, 2) ) ) )"),18.65) -> 18.65
A74: Amazon.it | B74: 42429 | C74: USD | D74: 4.59 | E74: =IFERROR(__xludf.DUMMYFUNCTION("IF(C74=""USD"", D74, IFERROR( D74 * INDEX(GOOGLEFINANCE(CONCATENATE(""CURRENCY:"", C74, ""USD""), ""close"", B74), 2, 2), IFERROR( D74 * INDEX(GOOGLEFINANCE(CONCATENATE(""CURRENCY:"", C74, ""USD""), ""close"", B74 - 1), 2, 2), D74 *"&" INDEX(GOOGLEFINANCE(CONCATENATE(""CURRENCY:"", C74, ""USD""), ""close"", B74 + 1), 2, 2) ) ) )"),4.59) -> 4.59
A75: Amazon.ca | B75: 42458 | C75: USD | D75: 0.06 | E75: =IFERROR(__xludf.DUMMYFUNCTION("IF(C75=""USD"", D75, IFERROR( D75 * INDEX(GOOGLEFINANCE(CONCATENATE(""CURRENCY:"", C75, ""USD""), ""close"", B75), 2, 2), IFERROR( D75 * INDEX(GOOGLEFINANCE(CONCATENATE(""CURRENCY:"", C75, ""USD""), ""close"", B75 - 1), 2, 2), D75 *"&" INDEX(GOOGLEFINANCE(CONCATENATE(""CURRENCY:"", C75, ""USD""), ""close"", B75 + 1), 2, 2) ) ) )"),0.06) -> 0.06
A76: CreateSpace US | B76: 42458 | C76: USD | D76: 74.31 | E76: =IFERROR(__xludf.DUMMYFUNCTION("IF(C76=""USD"", D76, IFERROR( D76 * INDEX(GOOGLEFINANCE(CONCATENATE(""CURRENCY:"", C76, ""USD""), ""close"", B76), 2, 2), IFERROR( D76 * INDEX(GOOGLEFINANCE(CONCATENATE(""CURRENCY:"", C76, ""USD""), ""close"", B76 - 1), 2, 2), D76 *"&" INDEX(GOOGLEFINANCE(CONCATENATE(""CURRENCY:"", C76, ""USD""), ""close"", B76 + 1), 2, 2) ) ) )"),74.31) -> 74.31
A77: Amazon.co.uk | B77: 42458 | C77: USD | D77: 4.59 | E77: =IFERROR(__xludf.DUMMYFUNCTION("IF(C77=""USD"", D77, IFERROR( D77 * INDEX(GOOGLEFINANCE(CONCATENATE(""CURRENCY:"", C77, ""USD""), ""close"", B77), 2, 2), IFERROR( D77 * INDEX(GOOGLEFINANCE(CONCATENATE(""CURRENCY:"", C77, ""USD""), ""close"", B77 - 1), 2, 2), D77 *"&" INDEX(GOOGLEFINANCE(CONCATENATE(""CURRENCY:"", C77, ""USD""), ""close"", B77 + 1), 2, 2) ) ) )"),4.59) -> 4.59
A78: Amazon.com | B78: 42458 | C78: USD | D78: 22.24 | E78: =IFERROR(__xludf.DUMMYFUNCTION("IF(C78=""USD"", D78, IFERROR( D78 * INDEX(GOOGLEFINANCE(CONCATENATE(""CURRENCY:"", C78, ""USD""), ""close"", B78), 2, 2), IFERROR( D78 * INDEX(GOOGLEFINANCE(CONCATENATE(""CURRENCY:"", C78, ""USD""), ""close"", B78 - 1), 2, 2), D78 *"&" INDEX(GOOGLEFINANCE(CONCATENATE(""CURRENCY:"", C78, ""USD""), ""close"", B78 + 1), 2, 2) ) ) )"),22.24) -> 22.24
A79: CreateSpace DE | B79: 42458 | C79: USD | D79: 15.99 | E79: =IFERROR(__xludf.DUMMYFUNCTION("IF(C79=""USD"", D79, IFERROR( D79 * INDEX(GOOGLEFINANCE(CONCATENATE(""CURRENCY:"", C79, ""USD""), ""close"", B79), 2, 2), IFERROR( D79 * INDEX(GOOGLEFINANCE(CONCATENATE(""CURRENCY:"", C79, ""USD""), ""close"", B79 - 1), 2, 2), D79 *"&" INDEX(GOOGLEFINANCE(CONCATENATE(""CURRENCY:"", C79, ""USD""), ""close"", B79 + 1), 2, 2) ) ) )"),15.99) -> 15.99
A80: CreateSpace DE | B80: 42489 | C80: USD | D80: 8.13 | E80: =IFERROR(__xludf.DUMMYFUNCTION("IF(C80=""USD"", D80, IFERROR( D80 * INDEX(GOOGLEFINANCE(CONCATENATE(""CURRENCY:"", C80, ""USD""), ""close"", B80), 2, 2), IFERROR( D80 * INDEX(GOOGLEFINANCE(CONCATENATE(""CURRENCY:"", C80, ""USD""), ""close"", B80 - 1), 2, 2), D80 *"&" INDEX(GOOGLEFINANCE(CONCATENATE(""CURRENCY:"", C80, ""USD""), ""close"", B80 + 1), 2, 2) ) ) )"),8.13) -> 8.13
A81: Amazon.co.uk | B81: 42489 | C81: USD | D81: 9.42 | E81: =IFERROR(__xludf.DUMMYFUNCTION("IF(C81=""USD"", D81, IFERROR( D81 * INDEX(GOOGLEFINANCE(CONCATENATE(""CURRENCY:"", C81, ""USD""), ""close"", B81), 2, 2), IFERROR( D81 * INDEX(GOOGLEFINANCE(CONCATENATE(""CURRENCY:"", C81, ""USD""), ""close"", B81 - 1), 2, 2), D81 *"&" INDEX(GOOGLEFINANCE(CONCATENATE(""CURRENCY:"", C81, ""USD""), ""close"", B81 + 1), 2, 2) ) ) )"),9.42) -> 9.42
A82: Amazon.com | B82: 42489 | C82: USD | D82: 22.83 | E82: =IFERROR(__xludf.DUMMYFUNCTION("IF(C82=""USD"", D82, IFERROR( D82 * INDEX(GOOGLEFINANCE(CONCATENATE(""CURRENCY:"", C82, ""USD""), ""close"", B82), 2, 2), IFERROR( D82 * INDEX(GOOGLEFINANCE(CONCATENATE(""CURRENCY:"", C82, ""USD""), ""close"", B82 - 1), 2, 2), D82 *"&" INDEX(GOOGLEFINANCE(CONCATENATE(""CURRENCY:"", C82, ""USD""), ""close"", B82 + 1), 2, 2) ) ) )"),22.83) -> 22.83
A83: CreateSpace US | B83: 42489 | C83: USD | D83: 110.07 | E83: =IFERROR(__xludf.DUMMYFUNCTION("IF(C83=""USD"", D83, IFERROR( D83 * INDEX(GOOGLEFINANCE(CONCATENATE(""CURRENCY:"", C83, ""USD""), ""close"", B83), 2, 2), IFERROR( D83 * INDEX(GOOGLEFINANCE(CONCATENATE(""CURRENCY:"", C83, ""USD""), ""close"", B83 - 1), 2, 2), D83 *"&" INDEX(GOOGLEFINANCE(CONCATENATE(""CURRENCY:"", C83, ""USD""), ""close"", B83 + 1), 2, 2) ) ) )"),110.07) -> 110.07
A84: CreateSpace US | B84: 42519 | C84: USD | D84: 60.51 | E84: =IFERROR(__xludf.DUMMYFUNCTION("IF(C84=""USD"", D84, IFERROR( D84 * INDEX(GOOGLEFINANCE(CONCATENATE(""CURRENCY:"", C84, ""USD""), ""close"", B84), 2, 2), IFERROR( D84 * INDEX(GOOGLEFINANCE(CONCATENATE(""CURRENCY:"", C84, ""USD""), ""close"", B84 - 1), 2, 2), D84 *"&" INDEX(GOOGLEFINANCE(CONCATENATE(""CURRENCY:"", C84, ""USD""), ""close"", B84 + 1), 2, 2) ) ) )"),60.51) -> 60.51
A85: Amazon.fr | B85: 42519 | C85: USD | D85: 4.52 | E85: =IFERROR(__xludf.DUMMYFUNCTION("IF(C85=""USD"", D85, IFERROR( D85 * INDEX(GOOGLEFINANCE(CONCATENATE(""CURRENCY:"", C85, ""USD""), ""close"", B85), 2, 2), IFERROR( D85 * INDEX(GOOGLEFINANCE(CONCATENATE(""CURRENCY:"", C85, ""USD""), ""close"", B85 - 1), 2, 2), D85 *"&" INDEX(GOOGLEFINANCE(CONCATENATE(""CURRENCY:"", C85, ""USD""), ""close"", B85 + 1), 2, 2) ) ) )"),4.52) -> 4.52
A86: Amazon.co.uk | B86: 42519 | C86: USD | D86: 4.87 | E86: =IFERROR(__xludf.DUMMYFUNCTION("IF(C86=""USD"", D86, IFERROR( D86 * INDEX(GOOGLEFINANCE(CONCATENATE(""CURRENCY:"", C86, ""USD""), ""close"", B86), 2, 2), IFERROR( D86 * INDEX(GOOGLEFINANCE(CONCATENATE(""CURRENCY:"", C86, ""USD""), ""close"", B86 - 1), 2, 2), D86 *"&" INDEX(GOOGLEFINANCE(CONCATENATE(""CURRENCY:"", C86, ""USD""), ""close"", B86 + 1), 2, 2) ) ) )"),4.87) -> 4.87
A87: Amazon.com | B87: 42519 | C87: USD | D87: 29.67 | E87: =IFERROR(__xludf.DUMMYFUNCTION("IF(C87=""USD"", D87, IFERROR( D87 * INDEX(GOOGLEFINANCE(CONCATENATE(""CURRENCY:"", C87, ""USD""), ""close"", B87), 2, 2), IFERROR( D87 * INDEX(GOOGLEFINANCE(CONCATENATE(""CURRENCY:"", C87, ""USD""), ""close"", B87 - 1), 2, 2), D87 *"&" INDEX(GOOGLEFINANCE(CONCATENATE(""CURRENCY:"", C87, ""USD""), ""close"", B87 + 1), 2, 2) ) ) )"),29.67) -> 29.67
A88: CreateSpace UK | B88: 42519 | C88: USD | D88: 24.02 | E88: =IFERROR(__xludf.DUMMYFUNCTION("IF(C88=""USD"", D88, IFERROR( D88 * INDEX(GOOGLEFINANCE(CONCATENATE(""CURRENCY:"", C88, ""USD""), ""close"", B88), 2, 2), IFERROR( D88 * INDEX(GOOGLEFINANCE(CONCATENATE(""CURRENCY:"", C88, ""USD""), ""close"", B88 - 1), 2, 2), D88 *"&" INDEX(GOOGLEFINANCE(CONCATENATE(""CURRENCY:"", C88, ""USD""), ""close"", B88 + 1), 2, 2) ) ) )"),24.02) -> 24.02
A89: CreateSpace DE | B89: 42519 | C89: USD | D89: 8 | E89: =IFERROR(__xludf.DUMMYFUNCTION("IF(C89=""USD"", D89, IFERROR( D89 * INDEX(GOOGLEFINANCE(CONCATENATE(""CURRENCY:"", C89, ""USD""), ""close"", B89), 2, 2), IFERROR( D89 * INDEX(GOOGLEFINANCE(CONCATENATE(""CURRENCY:"", C89, ""USD""), ""close"", B89 - 1), 2, 2), D89 *"&" INDEX(GOOGLEFINANCE(CONCATENATE(""CURRENCY:"", C89, ""USD""), ""close"", B89 + 1), 2, 2) ) ) )"),8.0) -> 8
A90: CreateSpace DE | B90: 42550 | C90: USD | D90: 7.95 | E90: =IFERROR(__xludf.DUMMYFUNCTION("IF(C90=""USD"", D90, IFERROR( D90 * INDEX(GOOGLEFINANCE(CONCATENATE(""CURRENCY:"", C90, ""USD""), ""close"", B90), 2, 2), IFERROR( D90 * INDEX(GOOGLEFINANCE(CONCATENATE(""CURRENCY:"", C90, ""USD""), ""close"", B90 - 1), 2, 2), D90 *"&" INDEX(GOOGLEFINANCE(CONCATENATE(""CURRENCY:"", C90, ""USD""), ""close"", B90 + 1), 2, 2) ) ) )"),7.95) -> 7.95
A91: CreateSpace US | B91: 42550 | C91: USD | D91: 60.51 | E91: =IFERROR(__xludf.DUMMYFUNCTION("IF(C91=""USD"", D91, IFERROR( D91 * INDEX(GOOGLEFINANCE(CONCATENATE(""CURRENCY:"", C91, ""USD""), ""close"", B91), 2, 2), IFERROR( D91 * INDEX(GOOGLEFINANCE(CONCATENATE(""CURRENCY:"", C91, ""USD""), ""close"", B91 - 1), 2, 2), D91 *"&" INDEX(GOOGLEFINANCE(CONCATENATE(""CURRENCY:"", C91, ""USD""), ""close"", B91 + 1), 2, 2) ) ) )"),60.51) -> 60.51
A92: Amazon.fr | B92: 42550 | C92: USD | D92: 4.49 | E92: =IFERROR(__xludf.DUMMYFUNCTION("IF(C92=""USD"", D92, IFERROR( D92 * INDEX(GOOGLEFINANCE(CONCATENATE(""CURRENCY:"", C92, ""USD""), ""close"", B92), 2, 2), IFERROR( D92 * INDEX(GOOGLEFINANCE(CONCATENATE(""CURRENCY:"", C92, ""USD""), ""close"", B92 - 1), 2, 2), D92 *"&" INDEX(GOOGLEFINANCE(CONCATENATE(""CURRENCY:"", C92, ""USD""), ""close"", B92 + 1), 2, 2) ) ) )"),4.49) -> 4.49
A93: Amazon.co.uk | B93: 42550 | C93: USD | D93: 13.18 | E93: =IFERROR(__xludf.DUMMYFUNCTION("IF(C93=""USD"", D93, IFERROR( D93 * INDEX(GOOGLEFINANCE(CONCATENATE(""CURRENCY:"", C93, ""USD""), ""close"", B93), 2, 2), IFERROR( D93 * INDEX(GOOGLEFINANCE(CONCATENATE(""CURRENCY:"", C93, ""USD""), ""close"", B93 - 1), 2, 2), D93 *"&" INDEX(GOOGLEFINANCE(CONCATENATE(""CURRENCY:"", C93, ""USD""), ""close"", B93 + 1), 2, 2) ) ) )"),13.18) -> 13.18
A94: CreateSpace UK | B94: 42550 | C94: USD | D94: 7.29 | E94: =IFERROR(__xludf.DUMMYFUNCTION("IF(C94=""USD"", D94, IFERROR( D94 * INDEX(GOOGLEFINANCE(CONCATENATE(""CURRENCY:"", C94, ""USD""), ""close"", B94), 2, 2), IFERROR( D94 * INDEX(GOOGLEFINANCE(CONCATENATE(""CURRENCY:"", C94, ""USD""), ""close"", B94 - 1), 2, 2), D94 *"&" INDEX(GOOGLEFINANCE(CONCATENATE(""CURRENCY:"", C94, ""USD""), ""close"", B94 + 1), 2, 2) ) ) )"),7.29) -> 7.29
A95: Amazon.ca | B95: 42550 | C95: USD | D95: 4.55 | E95: =IFERROR(__xludf.DUMMYFUNCTION("IF(C95=""USD"", D95, IFERROR( D95 * INDEX(GOOGLEFINANCE(CONCATENATE(""CURRENCY:"", C95, ""USD""), ""close"", B95), 2, 2), IFERROR( D95 * INDEX(GOOGLEFINANCE(CONCATENATE(""CURRENCY:"", C95, ""USD""), ""close"", B95 - 1), 2, 2), D95 *"&" INDEX(GOOGLEFINANCE(CONCATENATE(""CURRENCY:"", C95, ""USD""), ""close"", B95 + 1), 2, 2) ) ) )"),4.55) -> 4.55
A96: Amazon.com | B96: 42550 | C96: USD | D96: 36.29 | E96: =IFERROR(__xludf.DUMMYFUNCTION("IF(C96=""USD"", D96, IFERROR( D96 * INDEX(GOOGLEFINANCE(CONCATENATE(""CURRENCY:"", C96, ""USD""), ""close"", B96), 2, 2), IFERROR( D96 * INDEX(GOOGLEFINANCE(CONCATENATE(""CURRENCY:"", C96, ""USD""), ""close"", B96 - 1), 2, 2), D96 *"&" INDEX(GOOGLEFINANCE(CONCATENATE(""CURRENCY:"", C96, ""USD""), ""close"", B96 + 1), 2, 2) ) ) )"),36.29) -> 36.29
A97: Amazon.com.au | B97: 42550 | C97: USD | D97: 4.29 | E97: =IFERROR(__xludf.DUMMYFUNCTION("IF(C97=""USD"", D97, IFERROR( D97 * INDEX(GOOGLEFINANCE(CONCATENATE(""CURRENCY:"", C97, ""USD""), ""close"", B97), 2, 2), IFERROR( D97 * INDEX(GOOGLEFINANCE(CONCATENATE(""CURRENCY:"", C97, ""USD""), ""close"", B97 - 1), 2, 2), D97 *"&" INDEX(GOOGLEFINANCE(CONCATENATE(""CURRENCY:"", C97, ""USD""), ""close"", B97 + 1), 2, 2) ) ) )"),4.29) -> 4.29
A98: CreateSpace DE | B98: 42580 | C98: USD | D98: 7.94 | E98: =IFERROR(__xludf.DUMMYFUNCTION("IF(C98=""USD"", D98, IFERROR( D98 * INDEX(GOOGLEFINANCE(CONCATENATE(""CURRENCY:"", C98, ""USD""), ""close"", B98), 2, 2), IFERROR( D98 * INDEX(GOOGLEFINANCE(CONCATENATE(""CURRENCY:"", C98, ""USD""), ""close"", B98 - 1), 2, 2), D98 *"&" INDEX(GOOGLEFINANCE(CONCATENATE(""CURRENCY:"", C98, ""USD""), ""close"", B98 + 1), 2, 2) ) ) )"),7.94) -> 7.94
A99: Amazon.co.uk | B99: 42580 | C99: USD | D99: 8.55 | E99: =IFERROR(__xludf.DUMMYFUNCTION("IF(C99=""USD"", D99, IFERROR( D99 * INDEX(GOOGLEFINANCE(CONCATENATE(""CURRENCY:"", C99, ""USD""), ""close"", B99), 2, 2), IFERROR( D99 * INDEX(GOOGLEFINANCE(CONCATENATE(""CURRENCY:"", C99, ""USD""), ""close"", B99 - 1), 2, 2), D99 *"&" INDEX(GOOGLEFINANCE(CONCATENATE(""CURRENCY:"", C99, ""USD""), ""close"", B99 + 1), 2, 2) ) ) )"),8.55) -> 8.55
A100: Amazon.com | B100: 42580 | C100: USD | D100: 23.58 | E100: =IFERROR(__xludf.DUMMYFUNCTION("IF(C100=""USD"", D100, IFERROR( D100 * INDEX(GOOGLEFINANCE(CONCATENATE(""CURRENCY:"", C100, ""USD""), ""close"", B100), 2, 2), IFERROR( D100 * INDEX(GOOGLEFINANCE(CONCATENATE(""CURRENCY:"", C100, ""USD""), ""close"", B100 - 1), 2, 2), "&" D100 * INDEX(GOOGLEFINANCE(CONCATENATE(""CURRENCY:"", C100, ""USD""), ""close"", B100 + 1), 2, 2) ) ) )"),23.58) -> 23.58
...

Sheet Pivot Table 4

Sheet Teacher Salaries
B1: Hours | M1: Salary | W1: Contract hours
A2: Payout Date | B2: Hiba | C2: Lynn | D2: Mireille | E2: Mohamed | F2: Adon | G2: Fatima | H2: Ella | I2: Ghina | J2: Maria | K2: Total | L2: Rate | M2: Hiba | N2: Lynn | O2: Mireille | P2: Mohamed | Q2: Adon | R2: Fatima | S2: Ella | T2: Ghina | U2: Maria | V2: Total | W2: Hiba | X2: Lynn | Y2: Mireille | Z2: Mohamed | AA2: Adon | AB2: Fatima | AC2: Ella | AD2: Ghina | AE2: Maria | AF2: Total | AG2: Utilization % | AH2: Taught Lessons Link | AI2: https://docs.google.com/spreadsheets/d/1IfFm3yuRKQRrZtwuRxmqV1rnTUYvaEWEhGIuLQG1hJM/edit?usp=sharing
A3: 44773.999 | B3: =IFERROR(__xludf.DUMMYFUNCTION("sumproduct(importrange($AI$2,""hours""),importrange($AI$2,""lessondate"")<($A3),importrange($AI$2,""teacher"")=B$2)"),2.0) -> 2 | C3: =IFERROR(__xludf.DUMMYFUNCTION("sumproduct(importrange($AI$2,""hours""),importrange($AI$2,""lessondate"")<($A3),importrange($AI$2,""teacher"")=C$2)"),0.0) -> 0 | D3: =IFERROR(__xludf.DUMMYFUNCTION("sumproduct(importrange($AI$2,""hours""),importrange($AI$2,""lessondate"")<=($A3),importrange($AI$2,""lessondate"")>($A2),importrange($AI$2,""teacher"")=D$2)"),0.0) -> 0 | E3: =IFERROR(__xludf.DUMMYFUNCTION("sumproduct(importrange($AI$2,""hours""),importrange($AI$2,""lessondate"")<=($A3),importrange($AI$2,""lessondate"")>($A2),importrange($AI$2,""teacher"")=E$2)"),0.0) -> 0 | F3: =IFERROR(__xludf.DUMMYFUNCTION("sumproduct(importrange($AI$2,""hours""),importrange($AI$2,""lessondate"")<=($A3),importrange($AI$2,""lessondate"")>($A2),importrange($AI$2,""teacher"")=F$2)"),0.0) -> 0 | G3: =IFERROR(__xludf.DUMMYFUNCTION("sumproduct(importrange($AI$2,""hours""),importrange($AI$2,""lessondate"")<=($A3),importrange($AI$2,""lessondate"")>($A2),importrange($AI$2,""teacher"")=G$2)"),0.0) -> 0 | H3: =IFERROR(__xludf.DUMMYFUNCTION("sumproduct(importrange($AI$2,""hours""),importrange($AI$2,""lessondate"")<=($A3),importrange($AI$2,""lessondate"")>($A2),importrange($AI$2,""teacher"")=H$2)"),0.0) -> 0 | I3: =IFERROR(__xludf.DUMMYFUNCTION("sumproduct(importrange($AI$2,""hours""),importrange($AI$2,""lessondate"")<=($A3),importrange($AI$2,""lessondate"")>($A2),importrange($AI$2,""teacher"")=I$2)"),0.0) -> 0 | J3: =IFERROR(__xludf.DUMMYFUNCTION("sumproduct(importrange($AI$2,""hours""),importrange($AI$2,""lessondate"")<=($A3),importrange($AI$2,""lessondate"")>($A2),importrange($AI$2,""teacher"")=J$2)"),0.0) -> 0 | K3: =SUM(B3:G3) -> 2 | L3: 15 | M3: 315 | N3: 0 | O3: -15 | P3: 0 | Q3: 0 | R3: 0 | S3: 0 | T3: 0 | U3: =(J3)*11 -> 0 | V3: 0 | W3: 0 | X3: 0 | Y3: 0 | Z3: 0 | AA3: 0 | AB3: 0 | AC3: 0 | AD3: 0 | AE3: 0 | AF3: =sum(W3:AE3) -> 0 | AG3: =if(and(K3>0,AF3>0),K3/AF3,0) -> 0
A4: 44804.999 | B4: =IFERROR(__xludf.DUMMYFUNCTION("sumproduct(importrange($AI$2,""hours""),importrange($AI$2,""lessondate"")<=($A4),importrange($AI$2,""lessondate"")>($A3),importrange($AI$2,""teacher"")=B$2)"),19.0) -> 19 | C4: =IFERROR(__xludf.DUMMYFUNCTION("sumproduct(importrange($AI$2,""hours""),importrange($AI$2,""lessondate"")<=($A4),importrange($AI$2,""lessondate"")>($A3),importrange($AI$2,""teacher"")=C$2)"),0.0) -> 0 | D4: =IFERROR(__xludf.DUMMYFUNCTION("sumproduct(importrange($AI$2,""hours""),importrange($AI$2,""lessondate"")<=($A4),importrange($AI$2,""lessondate"")>($A3),importrange($AI$2,""teacher"")=D$2)"),11.75) -> 11.75 | E4: =IFERROR(__xludf.DUMMYFUNCTION("sumproduct(importrange($AI$2,""hours""),importrange($AI$2,""lessondate"")<=($A4),importrange($AI$2,""lessondate"")>($A3),importrange($AI$2,""teacher"")=E$2)"),0.0) -> 0 | F4: =IFERROR(__xludf.DUMMYFUNCTION("sumproduct(importrange($AI$2,""hours""),importrange($AI$2,""lessondate"")<=($A4),importrange($AI$2,""lessondate"")>($A3),importrange($AI$2,""teacher"")=F$2)"),0.0) -> 0 | G4: =IFERROR(__xludf.DUMMYFUNCTION("sumproduct(importrange($AI$2,""hours""),importrange($AI$2,""lessondate"")<=($A4),importrange($AI$2,""lessondate"")>($A3),importrange($AI$2,""teacher"")=G$2)"),0.0) -> 0 | H4: =IFERROR(__xludf.DUMMYFUNCTION("sumproduct(importrange($AI$2,""hours""),importrange($AI$2,""lessondate"")<=($A4),importrange($AI$2,""lessondate"")>($A3),importrange($AI$2,""teacher"")=H$2)"),0.0) -> 0 | I4: =IFERROR(__xludf.DUMMYFUNCTION("sumproduct(importrange($AI$2,""hours""),importrange($AI$2,""lessondate"")<=($A4),importrange($AI$2,""lessondate"")>($A3),importrange($AI$2,""teacher"")=I$2)"),0.0) -> 0 | J4: =IFERROR(__xludf.DUMMYFUNCTION("sumproduct(importrange($AI$2,""hours""),importrange($AI$2,""lessondate"")<=($A4),importrange($AI$2,""lessondate"")>($A3),importrange($AI$2,""teacher"")=J$2)"),0.0) -> 0 | K4: =SUM(B4:G4) -> 30.75 | L4: 15 | M4: =B4*$L4 -> 285 | N4: =C4*$L4 -> 0 | O4: =D4*$L4 -> 176.25 | P4: 0 | Q4: 0 | R4: 0 | S4: 0 | T4: 0 | U4: =(J4)*11 -> 0 | V4: =O4+M4+V3+315 -> 776.25 | W4: 0 | X4: 0 | Y4: 0 | Z4: 0 | AA4: 0 | AB4: 0 | AC4: 0 | AD4: 0 | AE4: 0 | AF4: =sum(W4:AE4) -> 0 | AG4: =if(and(K4>0,AF4>0),K4/AF4,0) -> 0
A5: 44834.999 | B5: =IFERROR(__xludf.DUMMYFUNCTION("sumproduct(importrange($AI$2,""hours""),importrange($AI$2,""lessondate"")<=($A5),importrange($AI$2,""lessondate"")>($A4),importrange($AI$2,""teacher"")=B$2)"),38.0) -> 38 | C5: =IFERROR(__xludf.DUMMYFUNCTION("sumproduct(importrange($AI$2,""hours""),importrange($AI$2,""lessondate"")<=($A5),importrange($AI$2,""lessondate"")>($A4),importrange($AI$2,""teacher"")=C$2)"),0.0) -> 0 | D5: =IFERROR(__xludf.DUMMYFUNCTION("sumproduct(importrange($AI$2,""hours""),importrange($AI$2,""lessondate"")<=($A5),importrange($AI$2,""lessondate"")>($A4),importrange($AI$2,""teacher"")=D$2)"),20.25) -> 20.25 | E5: =IFERROR(__xludf.DUMMYFUNCTION("sumproduct(importrange($AI$2,""hours""),importrange($AI$2,""lessondate"")<=($A5),importrange($AI$2,""lessondate"")>($A4),importrange($AI$2,""teacher"")=E$2)"),0.0) -> 0 | F5: =IFERROR(__xludf.DUMMYFUNCTION("sumproduct(importrange($AI$2,""hours""),importrange($AI$2,""lessondate"")<=($A5),importrange($AI$2,""lessondate"")>($A4),importrange($AI$2,""teacher"")=F$2)"),0.0) -> 0 | G5: =IFERROR(__xludf.DUMMYFUNCTION("sumproduct(importrange($AI$2,""hours""),importrange($AI$2,""lessondate"")<=($A5),importrange($AI$2,""lessondate"")>($A4),importrange($AI$2,""teacher"")=G$2)"),0.0) -> 0 | H5: =IFERROR(__xludf.DUMMYFUNCTION("sumproduct(importrange($AI$2,""hours""),importrange($AI$2,""lessondate"")<=($A5),importrange($AI$2,""lessondate"")>($A4),importrange($AI$2,""teacher"")=H$2)"),0.0) -> 0 | I5: =IFERROR(__xludf.DUMMYFUNCTION("sumproduct(importrange($AI$2,""hours""),importrange($AI$2,""lessondate"")<=($A5),importrange($AI$2,""lessondate"")>($A4),importrange($AI$2,""teacher"")=I$2)"),0.0) -> 0 | J5: =IFERROR(__xludf.DUMMYFUNCTION("sumproduct(importrange($AI$2,""hours""),importrange($AI$2,""lessondate"")<=($A5),importrange($AI$2,""lessondate"")>($A4),importrange($AI$2,""teacher"")=J$2)"),0.0) -> 0 | K5: =SUM(B5:G5) -> 58.25 | L5: 15 | M5: =B5*$L5 -> 570 | N5: =C5*$L5 -> 0 | O5: =D5*$L5 -> 303.75 | P5: 0 | Q5: 0 | R5: 0 | S5: 0 | T5: 0 | U5: =(J5)*11 -> 0 | V5: =sum(M5:R5) -> 873.75 | W5: 0 | X5: 0 | Y5: 0 | Z5: 0 | AA5: 0 | AB5: 0 | AC5: 0 | AD5: 0 | AE5: 0 | AF5: =sum(W5:AE5) -> 0 | AG5: =if(and(K5>0,AF5>0),K5/AF5,0) -> 0
A6: 44865.999 | B6: =IFERROR(__xludf.DUMMYFUNCTION("sumproduct(importrange($AI$2,""hours""),importrange($AI$2,""lessondate"")<=($A6),importrange($AI$2,""lessondate"")>($A5),importrange($AI$2,""teacher"")=B$2)"),37.0) -> 37 | C6: =IFERROR(__xludf.DUMMYFUNCTION("sumproduct(importrange($AI$2,""hours""),importrange($AI$2,""lessondate"")<=($A6),importrange($AI$2,""lessondate"")>($A5),importrange($AI$2,""teacher"")=C$2)"),0.0) -> 0 | D6: =IFERROR(__xludf.DUMMYFUNCTION("sumproduct(importrange($AI$2,""hours""),importrange($AI$2,""lessondate"")<=($A6),importrange($AI$2,""lessondate"")>($A5),importrange($AI$2,""teacher"")=D$2)"),25.916666666666668) -> 25.916667 | E6: =IFERROR(__xludf.DUMMYFUNCTION("sumproduct(importrange($AI$2,""hours""),importrange($AI$2,""lessondate"")<=($A6),importrange($AI$2,""lessondate"")>($A5),importrange($AI$2,""teacher"")=E$2)"),0.0) -> 0 | F6: =IFERROR(__xludf.DUMMYFUNCTION("sumproduct(importrange($AI$2,""hours""),importrange($AI$2,""lessondate"")<=($A6),importrange($AI$2,""lessondate"")>($A5),importrange($AI$2,""teacher"")=F$2)"),0.0) -> 0 | G6: =IFERROR(__xludf.DUMMYFUNCTION("sumproduct(importrange($AI$2,""hours""),importrange($AI$2,""lessondate"")<=($A6),importrange($AI$2,""lessondate"")>($A5),importrange($AI$2,""teacher"")=G$2)"),0.0) -> 0 | H6: =IFERROR(__xludf.DUMMYFUNCTION("sumproduct(importrange($AI$2,""hours""),importrange($AI$2,""lessondate"")<=($A6),importrange($AI$2,""lessondate"")>($A5),importrange($AI$2,""teacher"")=H$2)"),0.0) -> 0 | I6: =IFERROR(__xludf.DUMMYFUNCTION("sumproduct(importrange($AI$2,""hours""),importrange($AI$2,""lessondate"")<=($A6),importrange($AI$2,""lessondate"")>($A5),importrange($AI$2,""teacher"")=I$2)"),0.0) -> 0 | J6: =IFERROR(__xludf.DUMMYFUNCTION("sumproduct(importrange($AI$2,""hours""),importrange($AI$2,""lessondate"")<=($A6),importrange($AI$2,""lessondate"")>($A5),importrange($AI$2,""teacher"")=J$2)"),0.0) -> 0 | K6: =SUM(B6:G6) -> 62.916667 | L6: 15 | M6: =B6*$L6 -> 555 | N6: =C6*$L6 -> 0 | O6: =D6*$L6 -> 388.75 | P6: 0 | Q6: 0 | R6: 0 | S6: 0 | T6: 0 | U6: =(J6)*11 -> 0 | V6: =sum(M6:R6) -> 943.75 | W6: 0 | X6: 0 | Y6: 0 | Z6: 0 | AA6: 0 | AB6: 0 | AC6: 0 | AD6: 0 | AE6: 0 | AF6: =sum(W6:AE6) -> 0 | AG6: =if(and(K6>0,AF6>0),K6/AF6,0) -> 0
A7: 44895.999 | B7: =IFERROR(__xludf.DUMMYFUNCTION("sumproduct(importrange($AI$2,""hours""),importrange($AI$2,""lessondate"")<=($A7),importrange($AI$2,""lessondate"")>($A6),importrange($AI$2,""teacher"")=B$2)"),12.0) -> 12 | C7: =IFERROR(__xludf.DUMMYFUNCTION("sumproduct(importrange($AI$2,""hours""),importrange($AI$2,""lessondate"")<=($A7),importrange($AI$2,""lessondate"")>($A6),importrange($AI$2,""teacher"")=C$2)"),0.0) -> 0 | D7: =IFERROR(__xludf.DUMMYFUNCTION("sumproduct(importrange($AI$2,""hours""),importrange($AI$2,""lessondate"")<=($A7),importrange($AI$2,""lessondate"")>($A6),importrange($AI$2,""teacher"")=D$2)"),25.0) -> 25 | E7: =IFERROR(__xludf.DUMMYFUNCTION("sumproduct(importrange($AI$2,""hours""),importrange($AI$2,""lessondate"")<=($A7),importrange($AI$2,""lessondate"")>($A6),importrange($AI$2,""teacher"")=E$2)"),0.0) -> 0 | F7: =IFERROR(__xludf.DUMMYFUNCTION("sumproduct(importrange($AI$2,""hours""),importrange($AI$2,""lessondate"")<=($A7),importrange($AI$2,""lessondate"")>($A6),importrange($AI$2,""teacher"")=F$2)"),0.0) -> 0 | G7: =IFERROR(__xludf.DUMMYFUNCTION("sumproduct(importrange($AI$2,""hours""),importrange($AI$2,""lessondate"")<=($A7),importrange($AI$2,""lessondate"")>($A6),importrange($AI$2,""teacher"")=G$2)"),0.0) -> 0 | H7: =IFERROR(__xludf.DUMMYFUNCTION("sumproduct(importrange($AI$2,""hours""),importrange($AI$2,""lessondate"")<=($A7),importrange($AI$2,""lessondate"")>($A6),importrange($AI$2,""teacher"")=H$2)"),0.0) -> 0 | I7: =IFERROR(__xludf.DUMMYFUNCTION("sumproduct(importrange($AI$2,""hours""),importrange($AI$2,""lessondate"")<=($A7),importrange($AI$2,""lessondate"")>($A6),importrange($AI$2,""teacher"")=I$2)"),0.0) -> 0 | J7: =IFERROR(__xludf.DUMMYFUNCTION("sumproduct(importrange($AI$2,""hours""),importrange($AI$2,""lessondate"")<=($A7),importrange($AI$2,""lessondate"")>($A6),importrange($AI$2,""teacher"")=J$2)"),0.0) -> 0 | K7: =SUM(B7:G7) -> 37 | L7: 15 | M7: =B7*$L7 -> 180 | N7: =C7*$L7 -> 0 | O7: =D7*$L7 -> 375 | P7: 0 | Q7: 0 | R7: 0 | S7: 0 | T7: 0 | U7: =(J7)*11 -> 0 | V7: =sum(M7:R7) -> 555 | W7: 0 | X7: 0 | Y7: 0 | Z7: 0 | AA7: 0 | AB7: 0 | AC7: 0 | AD7: 0 | AE7: 0 | AF7: =sum(W7:AE7) -> 0 | AG7: =if(and(K7>0,AF7>0),K7/AF7,0) -> 0
A8: 44926.999 | B8: =IFERROR(__xludf.DUMMYFUNCTION("sumproduct(importrange($AI$2,""hours""),importrange($AI$2,""lessondate"")<=($A8),importrange($AI$2,""lessondate"")>($A7),importrange($AI$2,""teacher"")=B$2)"),23.0) -> 23 | C8: =IFERROR(__xludf.DUMMYFUNCTION("sumproduct(importrange($AI$2,""hours""),importrange($AI$2,""lessondate"")<=($A8),importrange($AI$2,""lessondate"")>($A7),importrange($AI$2,""teacher"")=C$2)"),0.0) -> 0 | D8: =IFERROR(__xludf.DUMMYFUNCTION("sumproduct(importrange($AI$2,""hours""),importrange($AI$2,""lessondate"")<=($A8),importrange($AI$2,""lessondate"")>($A7),importrange($AI$2,""teacher"")=D$2)"),38.0) -> 38 | E8: =IFERROR(__xludf.DUMMYFUNCTION("sumproduct(importrange($AI$2,""hours""),importrange($AI$2,""lessondate"")<=($A8),importrange($AI$2,""lessondate"")>($A7),importrange($AI$2,""teacher"")=E$2)"),0.0) -> 0 | F8: =IFERROR(__xludf.DUMMYFUNCTION("sumproduct(importrange($AI$2,""hours""),importrange($AI$2,""lessondate"")<=($A8),importrange($AI$2,""lessondate"")>($A7),importrange($AI$2,""teacher"")=F$2)"),0.0) -> 0 | G8: =IFERROR(__xludf.DUMMYFUNCTION("sumproduct(importrange($AI$2,""hours""),importrange($AI$2,""lessondate"")<=($A8),importrange($AI$2,""lessondate"")>($A7),importrange($AI$2,""teacher"")=G$2)"),0.0) -> 0 | H8: =IFERROR(__xludf.DUMMYFUNCTION("sumproduct(importrange($AI$2,""hours""),importrange($AI$2,""lessondate"")<=($A8),importrange($AI$2,""lessondate"")>($A7),importrange($AI$2,""teacher"")=H$2)"),0.0) -> 0 | I8: =IFERROR(__xludf.DUMMYFUNCTION("sumproduct(importrange($AI$2,""hours""),importrange($AI$2,""lessondate"")<=($A8),importrange($AI$2,""lessondate"")>($A7),importrange($AI$2,""teacher"")=I$2)"),0.0) -> 0 | J8: =IFERROR(__xludf.DUMMYFUNCTION("sumproduct(importrange($AI$2,""hours""),importrange($AI$2,""lessondate"")<=($A8),importrange($AI$2,""lessondate"")>($A7),importrange($AI$2,""teacher"")=J$2)"),0.0) -> 0 | K8: =SUM(B8:G8) -> 61 | L8: 15 | M8: =B8*$L8 -> 345 | N8: =C8*$L8 -> 0 | O8: =D8*$L8 -> 570 | P8: 0 | Q8: 0 | R8: 0 | S8: 0 | T8: 0 | U8: =(J8)*11 -> 0 | V8: =sum(M8:U8) -> 915 | W8: 0 | X8: 0 | Y8: 0 | Z8: 0 | AA8: 0 | AB8: 0 | AC8: 0 | AD8: 0 | AE8: 0 | AF8: =sum(W8:AE8) -> 0 | AG8: =if(and(K8>0,AF8>0),K8/AF8,0) -> 0
A9: 44957.999 | B9: =IFERROR(__xludf.DUMMYFUNCTION("sumproduct(importrange($AI$2,""hours""),importrange($AI$2,""lessondate"")<=($A9),importrange($AI$2,""lessondate"")>($A8),importrange($AI$2,""teacher"")=B$2)"),49.0) -> 49 | C9: =IFERROR(__xludf.DUMMYFUNCTION("sumproduct(importrange($AI$2,""hours""),importrange($AI$2,""lessondate"")<=($A9),importrange($AI$2,""lessondate"")>($A8),importrange($AI$2,""teacher"")=C$2)"),0.0) -> 0 | D9: =IFERROR(__xludf.DUMMYFUNCTION("sumproduct(importrange($AI$2,""hours""),importrange($AI$2,""lessondate"")<=($A9),importrange($AI$2,""lessondate"")>($A8),importrange($AI$2,""teacher"")=D$2)"),55.0) -> 55 | E9: =IFERROR(__xludf.DUMMYFUNCTION("sumproduct(importrange($AI$2,""hours""),importrange($AI$2,""lessondate"")<=($A9),importrange($AI$2,""lessondate"")>($A8),importrange($AI$2,""teacher"")=E$2)"),0.0) -> 0 | F9: =IFERROR(__xludf.DUMMYFUNCTION("sumproduct(importrange($AI$2,""hours""),importrange($AI$2,""lessondate"")<=($A9),importrange($AI$2,""lessondate"")>($A8),importrange($AI$2,""teacher"")=F$2)"),0.0) -> 0 | G9: =IFERROR(__xludf.DUMMYFUNCTION("sumproduct(importrange($AI$2,""hours""),importrange($AI$2,""lessondate"")<=($A9),importrange($AI$2,""lessondate"")>($A8),importrange($AI$2,""teacher"")=G$2)"),0.0) -> 0 | H9: =IFERROR(__xludf.DUMMYFUNCTION("sumproduct(importrange($AI$2,""hours""),importrange($AI$2,""lessondate"")<=($A9),importrange($AI$2,""lessondate"")>($A8),importrange($AI$2,""teacher"")=H$2)"),0.0) -> 0 | I9: =IFERROR(__xludf.DUMMYFUNCTION("sumproduct(importrange($AI$2,""hours""),importrange($AI$2,""lessondate"")<=($A9),importrange($AI$2,""lessondate"")>($A8),importrange($AI$2,""teacher"")=I$2)"),0.0) -> 0 | J9: =IFERROR(__xludf.DUMMYFUNCTION("sumproduct(importrange($AI$2,""hours""),importrange($AI$2,""lessondate"")<=($A9),importrange($AI$2,""lessondate"")>($A8),importrange($AI$2,""teacher"")=J$2)"),0.0) -> 0 | K9: =SUM(B9:H9) -> 104 | L9: 15 | M9: =B9*$L9 -> 735 | N9: =C9*$L9 -> 0 | O9: =D9*$L9 -> 825 | P9: 0 | Q9: 0 | R9: 0 | S9: 0 | T9: 0 | U9: =(J9)*11 -> 0 | V9: =sum(M9:U9) -> 1560 | W9: 0 | X9: 0 | Y9: 0 | Z9: 0 | AA9: 0 | AB9: 0 | AC9: 0 | AD9: 0 | AE9: 0 | AF9: =sum(W9:AE9) -> 0 | AG9: =if(and(K9>0,AF9>0),K9/AF9,0) -> 0
A10: 44985 | B10: =IFERROR(__xludf.DUMMYFUNCTION("sumproduct(importrange($AI$2,""hours""),importrange($AI$2,""lessondate"")<=($A10),importrange($AI$2,""lessondate"")>($A9),importrange($AI$2,""teacher"")=B$2)"),48.0) -> 48 | C10: =IFERROR(__xludf.DUMMYFUNCTION("sumproduct(importrange($AI$2,""hours""),importrange($AI$2,""lessondate"")<=($A10),importrange($AI$2,""lessondate"")>($A9),importrange($AI$2,""teacher"")=C$2)"),1.25) -> 1.25 | D10: =IFERROR(__xludf.DUMMYFUNCTION("sumproduct(importrange($AI$2,""hours""),importrange($AI$2,""lessondate"")<=($A10),importrange($AI$2,""lessondate"")>($A9),importrange($AI$2,""teacher"")=D$2)"),69.5) -> 69.5 | E10: =IFERROR(__xludf.DUMMYFUNCTION("sumproduct(importrange($AI$2,""hours""),importrange($AI$2,""lessondate"")<=($A10),importrange($AI$2,""lessondate"")>($A9),importrange($AI$2,""teacher"")=E$2)"),0.0) -> 0 | F10: =IFERROR(__xludf.DUMMYFUNCTION("sumproduct(importrange($AI$2,""hours""),importrange($AI$2,""lessondate"")<=($A10),importrange($AI$2,""lessondate"")>($A9),importrange($AI$2,""teacher"")=F$2)"),0.0) -> 0 | G10: =IFERROR(__xludf.DUMMYFUNCTION("sumproduct(importrange($AI$2,""hours""),importrange($AI$2,""lessondate"")<=($A10),importrange($AI$2,""lessondate"")>($A9),importrange($AI$2,""teacher"")=G$2)"),0.0) -> 0 | H10: =IFERROR(__xludf.DUMMYFUNCTION("sumproduct(importrange($AI$2,""hours""),importrange($AI$2,""lessondate"")<=($A10),importrange($AI$2,""lessondate"")>($A9),importrange($AI$2,""teacher"")=H$2)"),0.0) -> 0 | I10: =IFERROR(__xludf.DUMMYFUNCTION("sumproduct(importrange($AI$2,""hours""),importrange($AI$2,""lessondate"")<=($A10),importrange($AI$2,""lessondate"")>($A9),importrange($AI$2,""teacher"")=I$2)"),0.0) -> 0 | J10: =IFERROR(__xludf.DUMMYFUNCTION("sumproduct(importrange($AI$2,""hours""),importrange($AI$2,""lessondate"")<=($A10),importrange($AI$2,""lessondate"")>($A9),importrange($AI$2,""teacher"")=J$2)"),0.0) -> 0 | K10: =SUM(B10:H10) -> 118.75 | L10: 15 | M10: =B10*$L10 -> 720 | N10: =C10*$L10 -> 18.75 | O10: =D10*$L10 -> 1042.5 | P10: 0 | Q10: 0 | R10: 0 | S10: 0 | T10: 0 | U10: =(J10)*11 -> 0 | V10: =sum(M10:U10) -> 1781.25 | W10: 0 | X10: 0 | Y10: 0 | Z10: 0 | AA10: 0 | AB10: 0 | AC10: 0 | AD10: 0 | AE10: 0 | AF10: =sum(W10:AE10) -> 0 | AG10: =if(and(K10>0,AF10>0),K10/AF10,0) -> 0
A11: 45016 | B11: =IFERROR(__xludf.DUMMYFUNCTION("sumproduct(importrange($AI$2,""hours""),importrange($AI$2,""lessondate"")<=($A11),importrange($AI$2,""lessondate"")>($A10),importrange($AI$2,""teacher"")=B$2)"),41.0) -> 41 | C11: =IFERROR(__xludf.DUMMYFUNCTION("sumproduct(importrange($AI$2,""hours""),importrange($AI$2,""lessondate"")<=($A11),importrange($AI$2,""lessondate"")>($A10),importrange($AI$2,""teacher"")=C$2)"),11.25) -> 11.25 | D11: =IFERROR(__xludf.DUMMYFUNCTION("sumproduct(importrange($AI$2,""hours""),importrange($AI$2,""lessondate"")<=($A11),importrange($AI$2,""lessondate"")>($A10),importrange($AI$2,""teacher"")=D$2)"),69.25) -> 69.25 | E11: =IFERROR(__xludf.DUMMYFUNCTION("sumproduct(importrange($AI$2,""hours""),importrange($AI$2,""lessondate"")<=($A11),importrange($AI$2,""lessondate"")>($A10),importrange($AI$2,""teacher"")=E$2)"),0.0) -> 0 | F11: =IFERROR(__xludf.DUMMYFUNCTION("sumproduct(importrange($AI$2,""hours""),importrange($AI$2,""lessondate"")<=($A11),importrange($AI$2,""lessondate"")>($A10),importrange($AI$2,""teacher"")=F$2)"),0.0) -> 0 | G11: =IFERROR(__xludf.DUMMYFUNCTION("sumproduct(importrange($AI$2,""hours""),importrange($AI$2,""lessondate"")<=($A11),importrange($AI$2,""lessondate"")>($A10),importrange($AI$2,""teacher"")=G$2)"),0.0) -> 0 | H11: =IFERROR(__xludf.DUMMYFUNCTION("sumproduct(importrange($AI$2,""hours""),importrange($AI$2,""lessondate"")<=($A11),importrange($AI$2,""lessondate"")>($A10),importrange($AI$2,""teacher"")=H$2)"),0.0) -> 0 | I11: =IFERROR(__xludf.DUMMYFUNCTION("sumproduct(importrange($AI$2,""hours""),importrange($AI$2,""lessondate"")<=($A11),importrange($AI$2,""lessondate"")>($A10),importrange($AI$2,""teacher"")=I$2)"),0.0) -> 0 | J11: =IFERROR(__xludf.DUMMYFUNCTION("sumproduct(importrange($AI$2,""hours""),importrange($AI$2,""lessondate"")<=($A11),importrange($AI$2,""lessondate"")>($A10),importrange($AI$2,""teacher"")=J$2)"),0.0) -> 0 | K11: =SUM(B11:H11) -> 121.5 | L11: 15 | M11: =B11*$L11 -> 615 | N11: =C11*$L11 -> 168.75 | O11: =D11*$L11 -> 1038.75 | P11: 0 | Q11: 0 | R11: 0 | S11: 0 | T11: 0 | U11: =(J11)*11 -> 0 | V11: =sum(M11:U11) -> 1822.5 | W11: 0 | X11: 0 | Y11: 0 | Z11: 0 | AA11: 0 | AB11: 0 | AC11: 0 | AD11: 0 | AE11: 0 | AF11: =sum(W11:AE11) -> 0 | AG11: =if(and(K11>0,AF11>0),K11/AF11,0) -> 0
A12: 45046 | B12: =IFERROR(__xludf.DUMMYFUNCTION("sumproduct(importrange($AI$2,""hours""),importrange($AI$2,""lessondate"")<=($A12),importrange($AI$2,""lessondate"")>($A11),importrange($AI$2,""teacher"")=B$2)"),26.0) -> 26 | C12: =IFERROR(__xludf.DUMMYFUNCTION("sumproduct(importrange($AI$2,""hours""),importrange($AI$2,""lessondate"")<=($A12),importrange($AI$2,""lessondate"")>($A11),importrange($AI$2,""teacher"")=C$2)"),2.5) -> 2.5 | D12: =IFERROR(__xludf.DUMMYFUNCTION("sumproduct(importrange($AI$2,""hours""),importrange($AI$2,""lessondate"")<=($A12),importrange($AI$2,""lessondate"")>($A11),importrange($AI$2,""teacher"")=D$2)"),56.0) -> 56 | E12: =IFERROR(__xludf.DUMMYFUNCTION("sumproduct(importrange($AI$2,""hours""),importrange($AI$2,""lessondate"")<=($A12),importrange($AI$2,""lessondate"")>($A11),importrange($AI$2,""teacher"")=E$2)"),0.0) -> 0 | F12: =IFERROR(__xludf.DUMMYFUNCTION("sumproduct(importrange($AI$2,""hours""),importrange($AI$2,""lessondate"")<=($A12),importrange($AI$2,""lessondate"")>($A11),importrange($AI$2,""teacher"")=F$2)"),0.0) -> 0 | G12: =IFERROR(__xludf.DUMMYFUNCTION("sumproduct(importrange($AI$2,""hours""),importrange($AI$2,""lessondate"")<=($A12),importrange($AI$2,""lessondate"")>($A11),importrange($AI$2,""teacher"")=G$2)"),0.0) -> 0 | H12: =IFERROR(__xludf.DUMMYFUNCTION("sumproduct(importrange($AI$2,""hours""),importrange($AI$2,""lessondate"")<=($A12),importrange($AI$2,""lessondate"")>($A11),importrange($AI$2,""teacher"")=H$2)"),0.0) -> 0 | I12: =IFERROR(__xludf.DUMMYFUNCTION("sumproduct(importrange($AI$2,""hours""),importrange($AI$2,""lessondate"")<=($A12),importrange($AI$2,""lessondate"")>($A11),importrange($AI$2,""teacher"")=I$2)"),0.0) -> 0 | J12: =IFERROR(__xludf.DUMMYFUNCTION("sumproduct(importrange($AI$2,""hours""),importrange($AI$2,""lessondate"")<=($A12),importrange($AI$2,""lessondate"")>($A11),importrange($AI$2,""teacher"")=J$2)"),0.0) -> 0 | K12: =SUM(B12:H12) -> 84.5 | L12: 15 | M12: =B12*$L12 -> 390 | N12: =C12*$L12 -> 37.5 | O12: =D12*$L12 -> 840 | P12: 0 | Q12: 0 | R12: 0 | S12: 0 | T12: 0 | U12: =(J12)*11 -> 0 | V12: =sum(M12:U12) -> 1267.5 | W12: 0 | X12: 0 | Y12: 0 | Z12: 0 | AA12: 0 | AB12: 0 | AC12: 0 | AD12: 0 | AE12: 0 | AF12: =sum(W12:AE12) -> 0 | AG12: =if(and(K12>0,AF12>0),K12/AF12,0) -> 0
A13: 45077 | B13: =IFERROR(__xludf.DUMMYFUNCTION("sumproduct(importrange($AI$2,""hours""),importrange($AI$2,""lessondate"")<=($A13),importrange($AI$2,""lessondate"")>($A12),importrange($AI$2,""teacher"")=B$2)"),50.0) -> 50 | C13: =IFERROR(__xludf.DUMMYFUNCTION("sumproduct(importrange($AI$2,""hours""),importrange($AI$2,""lessondate"")<=($A13),importrange($AI$2,""lessondate"")>($A12),importrange($AI$2,""teacher"")=C$2)"),0.0) -> 0 | D13: =IFERROR(__xludf.DUMMYFUNCTION("sumproduct(importrange($AI$2,""hours""),importrange($AI$2,""lessondate"")<=($A13),importrange($AI$2,""lessondate"")>($A12),importrange($AI$2,""teacher"")=D$2)"),65.25) -> 65.25 | E13: =IFERROR(__xludf.DUMMYFUNCTION("sumproduct(importrange($AI$2,""hours""),importrange($AI$2,""lessondate"")<=($A13),importrange($AI$2,""lessondate"")>($A12),importrange($AI$2,""teacher"")=E$2)"),0.0) -> 0 | F13: =IFERROR(__xludf.DUMMYFUNCTION("sumproduct(importrange($AI$2,""hours""),importrange($AI$2,""lessondate"")<=($A13),importrange($AI$2,""lessondate"")>($A12),importrange($AI$2,""teacher"")=F$2)"),0.0) -> 0 | G13: =IFERROR(__xludf.DUMMYFUNCTION("sumproduct(importrange($AI$2,""hours""),importrange($AI$2,""lessondate"")<=($A13),importrange($AI$2,""lessondate"")>($A12),importrange($AI$2,""teacher"")=G$2)"),0.0) -> 0 | H13: =IFERROR(__xludf.DUMMYFUNCTION("sumproduct(importrange($AI$2,""hours""),importrange($AI$2,""lessondate"")<=($A13),importrange($AI$2,""lessondate"")>($A12),importrange($AI$2,""teacher"")=H$2)"),0.0) -> 0 | I13: =IFERROR(__xludf.DUMMYFUNCTION("sumproduct(importrange($AI$2,""hours""),importrange($AI$2,""lessondate"")<=($A13),importrange($AI$2,""lessondate"")>($A12),importrange($AI$2,""teacher"")=I$2)"),0.0) -> 0 | J13: =IFERROR(__xludf.DUMMYFUNCTION("sumproduct(importrange($AI$2,""hours""),importrange($AI$2,""lessondate"")<=($A13),importrange($AI$2,""lessondate"")>($A12),importrange($AI$2,""teacher"")=J$2)"),0.0) -> 0 | K13: =SUM(B13:H13) -> 115.25 | L13: 15 | M13: =B13*$L13 -> 750 | N13: =C13*$L13 -> 0 | O13: =D13*$L13 -> 978.75 | P13: 0 | Q13: 0 | R13: 0 | S13: 0 | T13: 0 | U13: =(J13)*11 -> 0 | V13: =sum(M13:U13) -> 1728.75 | W13: 0 | X13: 0 | Y13: 0 | Z13: 0 | AA13: 0 | AB13: 0 | AC13: 0 | AD13: 0 | AE13: 0 | AF13: =sum(W13:AE13) -> 0 | AG13: =if(and(K13>0,AF13>0),K13/AF13,0) -> 0
A14: 45107 | B14: =IFERROR(__xludf.DUMMYFUNCTION("sumproduct(importrange($AI$2,""hours""),importrange($AI$2,""lessondate"")<=($A14),importrange($AI$2,""lessondate"")>($A13),importrange($AI$2,""teacher"")=B$2)"),28.0) -> 28 | C14: =IFERROR(__xludf.DUMMYFUNCTION("sumproduct(importrange($AI$2,""hours""),importrange($AI$2,""lessondate"")<=($A14),importrange($AI$2,""lessondate"")>($A13),importrange($AI$2,""teacher"")=C$2)"),0.0) -> 0 | D14: =IFERROR(__xludf.DUMMYFUNCTION("sumproduct(importrange($AI$2,""hours""),importrange($AI$2,""lessondate"")<=($A14),importrange($AI$2,""lessondate"")>($A13),importrange($AI$2,""teacher"")=D$2)"),58.5) -> 58.5 | E14: =IFERROR(__xludf.DUMMYFUNCTION("sumproduct(importrange($AI$2,""hours""),importrange($AI$2,""lessondate"")<=($A14),importrange($AI$2,""lessondate"")>($A13),importrange($AI$2,""teacher"")=E$2)"),11.0) -> 11 | F14: =IFERROR(__xludf.DUMMYFUNCTION("sumproduct(importrange($AI$2,""hours""),importrange($AI$2,""lessondate"")<=($A14),importrange($AI$2,""lessondate"")>($A13),importrange($AI$2,""teacher"")=F$2)"),0.0) -> 0 | G14: =IFERROR(__xludf.DUMMYFUNCTION("sumproduct(importrange($AI$2,""hours""),importrange($AI$2,""lessondate"")<=($A14),importrange($AI$2,""lessondate"")>($A13),importrange($AI$2,""teacher"")=G$2)"),0.0) -> 0 | H14: =IFERROR(__xludf.DUMMYFUNCTION("sumproduct(importrange($AI$2,""hours""),importrange($AI$2,""lessondate"")<=($A14),importrange($AI$2,""lessondate"")>($A13),importrange($AI$2,""teacher"")=H$2)"),0.0) -> 0 | I14: =IFERROR(__xludf.DUMMYFUNCTION("sumproduct(importrange($AI$2,""hours""),importrange($AI$2,""lessondate"")<=($A14),importrange($AI$2,""lessondate"")>($A13),importrange($AI$2,""teacher"")=I$2)"),0.0) -> 0 | J14: =IFERROR(__xludf.DUMMYFUNCTION("sumproduct(importrange($AI$2,""hours""),importrange($AI$2,""lessondate"")<=($A14),importrange($AI$2,""lessondate"")>($A13),importrange($AI$2,""teacher"")=J$2)"),0.0) -> 0 | K14: =SUM(B14:H14) -> 97.5 | L14: 15 | M14: =B14*$L14 -> 420 | N14: =C14*$L14 -> 0 | O14: =D14*$L14 -> 877.5 | P14: 0 | Q14: 0 | R14: 0 | S14: 0 | T14: 0 | U14: =(J14)*11 -> 0 | V14: =sum(M14:U14) -> 1297.5 | W14: 0 | X14: 0 | Y14: 0 | Z14: 0 | AA14: 0 | AB14: 0 | AC14: 0 | AD14: 0 | AE14: 0 | AF14: =sum(W14:AE14) -> 0 | AG14: =if(and(K14>0,AF14>0),K14/AF14,0) -> 0
A15: 45138 | B15: =IFERROR(__xludf.DUMMYFUNCTION("sumproduct(importrange($AI$2,""hours""),importrange($AI$2,""lessondate"")<=($A15),importrange($AI$2,""lessondate"")>($A14),importrange($AI$2,""teacher"")=B$2)"),0.0) -> 0 | C15: =IFERROR(__xludf.DUMMYFUNCTION("sumproduct(importrange($AI$2,""hours""),importrange($AI$2,""lessondate"")<=($A15),importrange($AI$2,""lessondate"")>($A14),importrange($AI$2,""teacher"")=C$2)"),0.0) -> 0 | D15: =IFERROR(__xludf.DUMMYFUNCTION("sumproduct(importrange($AI$2,""hours""),importrange($AI$2,""lessondate"")<=($A15),importrange($AI$2,""lessondate"")>($A14),importrange($AI$2,""teacher"")=D$2)"),29.5) -> 29.5 | E15: =IFERROR(__xludf.DUMMYFUNCTION("sumproduct(importrange($AI$2,""hours""),importrange($AI$2,""lessondate"")<=($A15),importrange($AI$2,""lessondate"")>($A14),importrange($AI$2,""teacher"")=E$2)"),23.0) -> 23 | F15: =IFERROR(__xludf.DUMMYFUNCTION("sumproduct(importrange($AI$2,""hours""),importrange($AI$2,""lessondate"")<=($A15),importrange($AI$2,""lessondate"")>($A14),importrange($AI$2,""teacher"")=F$2)"),2.0) -> 2 | G15: =IFERROR(__xludf.DUMMYFUNCTION("sumproduct(importrange($AI$2,""hours""),importrange($AI$2,""lessondate"")<=($A15),importrange($AI$2,""lessondate"")>($A14),importrange($AI$2,""teacher"")=G$2)"),0.0) -> 0 | H15: =IFERROR(__xludf.DUMMYFUNCTION("sumproduct(importrange($AI$2,""hours""),importrange($AI$2,""lessondate"")<=($A15),importrange($AI$2,""lessondate"")>($A14),importrange($AI$2,""teacher"")=H$2)"),0.0) -> 0 | I15: =IFERROR(__xludf.DUMMYFUNCTION("sumproduct(importrange($AI$2,""hours""),importrange($AI$2,""lessondate"")<=($A15),importrange($AI$2,""lessondate"")>($A14),importrange($AI$2,""teacher"")=I$2)"),0.0) -> 0 | J15: =IFERROR(__xludf.DUMMYFUNCTION("sumproduct(importrange($AI$2,""hours""),importrange($AI$2,""lessondate"")<=($A15),importrange($AI$2,""lessondate"")>($A14),importrange($AI$2,""teacher"")=J$2)"),0.0) -> 0 | K15: =SUM(B15:H15) -> 54.5 | L15: 15 | M15: =B15*$L15 -> 0 | N15: =C15*$L15 -> 0 | O15: =D15*$L15 -> 442.5 | P15: 200 | Q15: 100 | R15: 0 | S15: 0 | T15: 0 | U15: =(J15)*11 -> 0 | V15: =sum(M15:U15) -> 742.5 | W15: 0 | X15: 0 | Y15: 0 | Z15: 0 | AA15: 0 | AB15: 0 | AC15: 0 | AD15: 0 | AE15: 0 | AF15: =sum(W15:AE15) -> 0 | AG15: =if(and(K15>0,AF15>0),K15/AF15,0) -> 0
A16: 45169 | B16: =IFERROR(__xludf.DUMMYFUNCTION("sumproduct(importrange($AI$2,""hours""),importrange($AI$2,""lessondate"")<=($A16),importrange($AI$2,""lessondate"")>($A15),importrange($AI$2,""teacher"")=B$2)"),0.0) -> 0 | C16: =IFERROR(__xludf.DUMMYFUNCTION("sumproduct(importrange($AI$2,""hours""),importrange($AI$2,""lessondate"")<=($A16),importrange($AI$2,""lessondate"")>($A15),importrange($AI$2,""teacher"")=C$2)"),0.0) -> 0 | D16: =IFERROR(__xludf.DUMMYFUNCTION("sumproduct(importrange($AI$2,""hours""),importrange($AI$2,""lessondate"")<=($A16),importrange($AI$2,""lessondate"")>($A15),importrange($AI$2,""teacher"")=D$2)"),24.75) -> 24.75 | E16: =IFERROR(__xludf.DUMMYFUNCTION("sumproduct(importrange($AI$2,""hours""),importrange($AI$2,""lessondate"")<=($A16),importrange($AI$2,""lessondate"")>($A15),importrange($AI$2,""teacher"")=E$2)"),14.0) -> 14 | F16: =IFERROR(__xludf.DUMMYFUNCTION("sumproduct(importrange($AI$2,""hours""),importrange($AI$2,""lessondate"")<=($A16),importrange($AI$2,""lessondate"")>($A15),importrange($AI$2,""teacher"")=F$2)"),28.0) -> 28 | G16: =IFERROR(__xludf.DUMMYFUNCTION("sumproduct(importrange($AI$2,""hours""),importrange($AI$2,""lessondate"")<=($A16),importrange($AI$2,""lessondate"")>($A15),importrange($AI$2,""teacher"")=G$2)"),21.0) -> 21 | H16: =IFERROR(__xludf.DUMMYFUNCTION("sumproduct(importrange($AI$2,""hours""),importrange($AI$2,""lessondate"")<=($A16),importrange($AI$2,""lessondate"")>($A15),importrange($AI$2,""teacher"")=H$2)"),0.0) -> 0 | I16: =IFERROR(__xludf.DUMMYFUNCTION("sumproduct(importrange($AI$2,""hours""),importrange($AI$2,""lessondate"")<=($A16),importrange($AI$2,""lessondate"")>($A15),importrange($AI$2,""teacher"")=I$2)"),0.0) -> 0 | J16: =IFERROR(__xludf.DUMMYFUNCTION("sumproduct(importrange($AI$2,""hours""),importrange($AI$2,""lessondate"")<=($A16),importrange($AI$2,""lessondate"")>($A15),importrange($AI$2,""teacher"")=J$2)"),0.0) -> 0 | K16: =SUM(B16:H16) -> 87.75 | L16: 15 | M16: =B16*$L16 -> 0 | N16: =C16*$L16 -> 0 | O16: =D16*$L16 -> 371.25 | P16: 200 | Q16: 200 | R16: 200 | S16: 0 | T16: 0 | U16: =(J16)*11 -> 0 | V16: =sum(M16:U16) -> 971.25 | W16: 0 | X16: 0 | Y16: 0 | Z16: 0 | AA16: 0 | AB16: 28 | AC16: 0 | AD16: 0 | AE16: 0 | AF16: =sum(W16:AE16) -> 28 | AG16: =if(and(K16>0,AF16>0),K16/AF16,0) -> 3.1339286
A17: 45199 | B17: =IFERROR(__xludf.DUMMYFUNCTION("sumproduct(importrange($AI$2,""hours""),importrange($AI$2,""lessondate"")<=($A17),importrange($AI$2,""lessondate"")>($A16),importrange($AI$2,""teacher"")=B$2)"),0.0) -> 0 | C17: =IFERROR(__xludf.DUMMYFUNCTION("sumproduct(importrange($AI$2,""hours""),importrange($AI$2,""lessondate"")<=($A17),importrange($AI$2,""lessondate"")>($A16),importrange($AI$2,""teacher"")=C$2)"),0.0) -> 0 | D17: =IFERROR(__xludf.DUMMYFUNCTION("sumproduct(importrange($AI$2,""hours""),importrange($AI$2,""lessondate"")<=($A17),importrange($AI$2,""lessondate"")>($A16),importrange($AI$2,""teacher"")=D$2)"),61.25) -> 61.25 | E17: =IFERROR(__xludf.DUMMYFUNCTION("sumproduct(importrange($AI$2,""hours""),importrange($AI$2,""lessondate"")<=($A17),importrange($AI$2,""lessondate"")>($A16),importrange($AI$2,""teacher"")=E$2)"),0.0) -> 0 | F17: =IFERROR(__xludf.DUMMYFUNCTION("sumproduct(importrange($AI$2,""hours""),importrange($AI$2,""lessondate"")<=($A17),importrange($AI$2,""lessondate"")>($A16),importrange($AI$2,""teacher"")=F$2)"),20.0) -> 20 | G17: =IFERROR(__xludf.DUMMYFUNCTION("sumproduct(importrange($AI$2,""hours""),importrange($AI$2,""lessondate"")<=($A17),importrange($AI$2,""lessondate"")>($A16),importrange($AI$2,""teacher"")=G$2)"),29.0) -> 29 | H17: =IFERROR(__xludf.DUMMYFUNCTION("sumproduct(importrange($AI$2,""hours""),importrange($AI$2,""lessondate"")<=($A17),importrange($AI$2,""lessondate"")>($A16),importrange($AI$2,""teacher"")=H$2)"),0.0) -> 0 | I17: =IFERROR(__xludf.DUMMYFUNCTION("sumproduct(importrange($AI$2,""hours""),importrange($AI$2,""lessondate"")<=($A17),importrange($AI$2,""lessondate"")>($A16),importrange($AI$2,""teacher"")=I$2)"),0.0) -> 0 | J17: =IFERROR(__xludf.DUMMYFUNCTION("sumproduct(importrange($AI$2,""hours""),importrange($AI$2,""lessondate"")<=($A17),importrange($AI$2,""lessondate"")>($A16),importrange($AI$2,""teacher"")=J$2)"),0.0) -> 0 | K17: =SUM(B17:H17) -> 110.25 | L17: 15 | M17: =B17*$L17 -> 0 | N17: =C17*$L17 -> 0 | O17: 1200 | P17: 0 | Q17: 200 | R17: 200 | S17: 0 | T17: 0 | U17: =(J17)*11 -> 0 | V17: =sum(M17:U17) -> 1600 | W17: 0 | X17: 0 | Y17: 116 | Z17: 0 | AA17: 0 | AB17: 28 | AC17: 0 | AD17: 0 | AE17: 0 | AF17: =sum(W17:AE17) -> 144 | AG17: =if(and(K17>0,AF17>0),K17/AF17,0) -> 0.765625
A18: 45230 | B18: =IFERROR(__xludf.DUMMYFUNCTION("sumproduct(importrange($AI$2,""hours""),importrange($AI$2,""lessondate"")<=($A18),importrange($AI$2,""lessondate"")>($A17),importrange($AI$2,""teacher"")=B$2)"),0.0) -> 0 | C18: =IFERROR(__xludf.DUMMYFUNCTION("sumproduct(importrange($AI$2,""hours""),importrange($AI$2,""lessondate"")<=($A18),importrange($AI$2,""lessondate"")>($A17),importrange($AI$2,""teacher"")=C$2)"),0.0) -> 0 | D18: =IFERROR(__xludf.DUMMYFUNCTION("sumproduct(importrange($AI$2,""hours""),importrange($AI$2,""lessondate"")<=($A18),importrange($AI$2,""lessondate"")>($A17),importrange($AI$2,""teacher"")=D$2)"),90.5) -> 90.5 | E18: =IFERROR(__xludf.DUMMYFUNCTION("sumproduct(importrange($AI$2,""hours""),importrange($AI$2,""lessondate"")<=($A18),importrange($AI$2,""lessondate"")>($A17),importrange($AI$2,""teacher"")=E$2)"),0.0) -> 0 | F18: =IFERROR(__xludf.DUMMYFUNCTION("sumproduct(importrange($AI$2,""hours""),importrange($AI$2,""lessondate"")<=($A18),importrange($AI$2,""lessondate"")>($A17),importrange($AI$2,""teacher"")=F$2)"),22.0) -> 22 | G18: =IFERROR(__xludf.DUMMYFUNCTION("sumproduct(importrange($AI$2,""hours""),importrange($AI$2,""lessondate"")<=($A18),importrange($AI$2,""lessondate"")>($A17),importrange($AI$2,""teacher"")=G$2)"),26.0) -> 26 | H18: =IFERROR(__xludf.DUMMYFUNCTION("sumproduct(importrange($AI$2,""hours""),importrange($AI$2,""lessondate"")<=($A18),importrange($AI$2,""lessondate"")>($A17),importrange($AI$2,""teacher"")=H$2)"),0.0) -> 0 | I18: =IFERROR(__xludf.DUMMYFUNCTION("sumproduct(importrange($AI$2,""hours""),importrange($AI$2,""lessondate"")<=($A18),importrange($AI$2,""lessondate"")>($A17),importrange($AI$2,""teacher"")=I$2)"),0.0) -> 0 | J18: =IFERROR(__xludf.DUMMYFUNCTION("sumproduct(importrange($AI$2,""hours""),importrange($AI$2,""lessondate"")<=($A18),importrange($AI$2,""lessondate"")>($A17),importrange($AI$2,""teacher"")=J$2)"),0.0) -> 0 | K18: =SUM(B18:H18) -> 138.5 | L18: 15 | M18: =B18*$L18 -> 0 | N18: =C18*$L18 -> 0 | O18: 1200 | P18: 0 | Q18: 200 | R18: 200 | S18: 0 | T18: 0 | U18: =(J18)*11 -> 0 | V18: =sum(M18:U18) -> 1600 | W18: 0 | X18: 0 | Y18: 116 | Z18: 0 | AA18: 0 | AB18: 28 | AC18: 0 | AD18: 0 | AE18: 0 | AF18: =sum(W18:AE18) -> 144 | AG18: =if(and(K18>0,AF18>0),K18/AF18,0) -> 0.96180556
A19: 45260 | B19: =IFERROR(__xludf.DUMMYFUNCTION("sumproduct(importrange($AI$2,""hours""),importrange($AI$2,""lessondate"")<=($A19),importrange($AI$2,""lessondate"")>($A18),importrange($AI$2,""teacher"")=B$2)"),0.0) -> 0 | C19: =IFERROR(__xludf.DUMMYFUNCTION("sumproduct(importrange($AI$2,""hours""),importrange($AI$2,""lessondate"")<=($A19),importrange($AI$2,""lessondate"")>($A18),importrange($AI$2,""teacher"")=C$2)"),0.0) -> 0 | D19: =IFERROR(__xludf.DUMMYFUNCTION("sumproduct(importrange($AI$2,""hours""),importrange($AI$2,""lessondate"")<=($A19),importrange($AI$2,""lessondate"")>($A18),importrange($AI$2,""teacher"")=D$2)"),91.25) -> 91.25 | E19: =IFERROR(__xludf.DUMMYFUNCTION("sumproduct(importrange($AI$2,""hours""),importrange($AI$2,""lessondate"")<=($A19),importrange($AI$2,""lessondate"")>($A18),importrange($AI$2,""teacher"")=E$2)"),0.0) -> 0 | F19: =IFERROR(__xludf.DUMMYFUNCTION("sumproduct(importrange($AI$2,""hours""),importrange($AI$2,""lessondate"")<=($A19),importrange($AI$2,""lessondate"")>($A18),importrange($AI$2,""teacher"")=F$2)"),24.0) -> 24 | G19: =IFERROR(__xludf.DUMMYFUNCTION("sumproduct(importrange($AI$2,""hours""),importrange($AI$2,""lessondate"")<=($A19),importrange($AI$2,""lessondate"")>($A18),importrange($AI$2,""teacher"")=G$2)"),39.0) -> 39 | H19: =IFERROR(__xludf.DUMMYFUNCTION("sumproduct(importrange($AI$2,""hours""),importrange($AI$2,""lessondate"")<=($A19),importrange($AI$2,""lessondate"")>($A18),importrange($AI$2,""teacher"")=H$2)"),0.0) -> 0 | I19: =IFERROR(__xludf.DUMMYFUNCTION("sumproduct(importrange($AI$2,""hours""),importrange($AI$2,""lessondate"")<=($A19),importrange($AI$2,""lessondate"")>($A18),importrange($AI$2,""teacher"")=I$2)"),0.0) -> 0 | J19: =IFERROR(__xludf.DUMMYFUNCTION("sumproduct(importrange($AI$2,""hours""),importrange($AI$2,""lessondate"")<=($A19),importrange($AI$2,""lessondate"")>($A18),importrange($AI$2,""teacher"")=J$2)"),2.0) -> 2 | K19: =SUM(B19:H19) -> 154.25 | L19: 15 | M19: =B19*$L19 -> 0 | N19: =C19*$L19 -> 0 | O19: 1200 | P19: 0 | Q19: 200 | R19: 300 | S19: 0 | T19: 0 | U19: =(J19)*11 -> 22 | V19: =sum(M19:U19) -> 1722 | W19: 0 | X19: 0 | Y19: 116 | Z19: 0 | AA19: 0 | AB19: 28 | AC19: 0 | AD19: 0 | AE19: 0 | AF19: =sum(W19:AE19) -> 144 | AG19: =if(and(K19>0,AF19>0),K19/AF19,0) -> 1.0711806
A20: 45291 | B20: =IFERROR(__xludf.DUMMYFUNCTION("sumproduct(importrange($AI$2,""hours""),importrange($AI$2,""lessondate"")<=($A20),importrange($AI$2,""lessondate"")>($A19),importrange($AI$2,""teacher"")=B$2)"),0.0) -> 0 | C20: =IFERROR(__xludf.DUMMYFUNCTION("sumproduct(importrange($AI$2,""hours""),importrange($AI$2,""lessondate"")<=($A20),importrange($AI$2,""lessondate"")>($A19),importrange($AI$2,""teacher"")=C$2)"),0.0) -> 0 | D20: =IFERROR(__xludf.DUMMYFUNCTION("sumproduct(importrange($AI$2,""hours""),importrange($AI$2,""lessondate"")<=($A20),importrange($AI$2,""lessondate"")>($A19),importrange($AI$2,""teacher"")=D$2)"),72.5) -> 72.5 | E20: =IFERROR(__xludf.DUMMYFUNCTION("sumproduct(importrange($AI$2,""hours""),importrange($AI$2,""lessondate"")<=($A20),importrange($AI$2,""lessondate"")>($A19),importrange($AI$2,""teacher"")=E$2)"),0.0) -> 0 | F20: =IFERROR(__xludf.DUMMYFUNCTION("sumproduct(importrange($AI$2,""hours""),importrange($AI$2,""lessondate"")<=($A20),importrange($AI$2,""lessondate"")>($A19),importrange($AI$2,""teacher"")=F$2)"),22.0) -> 22 | G20: =IFERROR(__xludf.DUMMYFUNCTION("sumproduct(importrange($AI$2,""hours""),importrange($AI$2,""lessondate"")<=($A20),importrange($AI$2,""lessondate"")>($A19),importrange($AI$2,""teacher"")=G$2)"),45.5) -> 45.5 | H20: =IFERROR(__xludf.DUMMYFUNCTION("sumproduct(importrange($AI$2,""hours""),importrange($AI$2,""lessondate"")<=($A20),importrange($AI$2,""lessondate"")>($A19),importrange($AI$2,""teacher"")=H$2)"),17.0) -> 17 | I20: =IFERROR(__xludf.DUMMYFUNCTION("sumproduct(importrange($AI$2,""hours""),importrange($AI$2,""lessondate"")<=($A20),importrange($AI$2,""lessondate"")>($A19),importrange($AI$2,""teacher"")=I$2)"),0.0) -> 0 | J20: =IFERROR(__xludf.DUMMYFUNCTION("sumproduct(importrange($AI$2,""hours""),importrange($AI$2,""lessondate"")<=($A20),importrange($AI$2,""lessondate"")>($A19),importrange($AI$2,""teacher"")=J$2)"),0.0) -> 0 | K20: =SUM(B20:H20) -> 157 | L20: 15 | M20: =B20*$L20 -> 0 | N20: =C20*$L20 -> 0 | O20: 1200 | P20: 0 | Q20: =MAX(200,200+(F20-28)*8) -> 200 | R20: 376 | S20: =MAX(200,200+(H20-28)*8) -> 200 | T20: 0 | U20: =(J20)*11 -> 0 | V20: =sum(M20:U20) -> 1976 | W20: 0 | X20: 0 | Y20: 116 | Z20: 0 | AA20: 0 | AB20: 28 | AC20: 28 | AD20: 0 | AE20: 0 | AF20: =sum(W20:AE20) -> 172 | AG20: =if(and(K20>0,AF20>0),K20/AF20,0) -> 0.9127907
A21: 45322 | B21: =IFERROR(__xludf.DUMMYFUNCTION("sumproduct(importrange($AI$2,""hours""),importrange($AI$2,""lessondate"")<=($A21),importrange($AI$2,""lessondate"")>($A20),importrange($AI$2,""teacher"")=B$2)"),0.0) -> 0 | C21: =IFERROR(__xludf.DUMMYFUNCTION("sumproduct(importrange($AI$2,""hours""),importrange($AI$2,""lessondate"")<=($A21),importrange($AI$2,""lessondate"")>($A20),importrange($AI$2,""teacher"")=C$2)"),0.0) -> 0 | D21: =IFERROR(__xludf.DUMMYFUNCTION("sumproduct(importrange($AI$2,""hours""),importrange($AI$2,""lessondate"")<=($A21),importrange($AI$2,""lessondate"")>($A20),importrange($AI$2,""teacher"")=D$2)"),99.25) -> 99.25 | E21: =IFERROR(__xludf.DUMMYFUNCTION("sumproduct(importrange($AI$2,""hours""),importrange($AI$2,""lessondate"")<=($A21),importrange($AI$2,""lessondate"")>($A20),importrange($AI$2,""teacher"")=E$2)"),0.0) -> 0 | F21: =IFERROR(__xludf.DUMMYFUNCTION("sumproduct(importrange($AI$2,""hours""),importrange($AI$2,""lessondate"")<=($A21),importrange($AI$2,""lessondate"")>($A20),importrange($AI$2,""teacher"")=F$2)"),12.0) -> 12 | G21: =IFERROR(__xludf.DUMMYFUNCTION("sumproduct(importrange($AI$2,""hours""),importrange($AI$2,""lessondate"")<=($A21),importrange($AI$2,""lessondate"")>($A20),importrange($AI$2,""teacher"")=G$2)"),36.0) -> 36 | H21: =IFERROR(__xludf.DUMMYFUNCTION("sumproduct(importrange($AI$2,""hours""),importrange($AI$2,""lessondate"")<=($A21),importrange($AI$2,""lessondate"")>($A20),importrange($AI$2,""teacher"")=H$2)"),24.0) -> 24 | I21: =IFERROR(__xludf.DUMMYFUNCTION("sumproduct(importrange($AI$2,""hours""),importrange($AI$2,""lessondate"")<=($A21),importrange($AI$2,""lessondate"")>($A20),importrange($AI$2,""teacher"")=I$2)"),0.0) -> 0 | J21: =IFERROR(__xludf.DUMMYFUNCTION("sumproduct(importrange($AI$2,""hours""),importrange($AI$2,""lessondate"")<=($A21),importrange($AI$2,""lessondate"")>($A20),importrange($AI$2,""teacher"")=J$2)"),0.0) -> 0 | K21: =SUM(B21:H21) -> 171.25 | L21: 15 | M21: =B21*$L21 -> 0 | N21: =C21*$L21 -> 0 | O21: 1200 | P21: 0 | Q21: =(F21)*8 -> 96 | R21: =MAX(200,200+(G21-28)*8) -> 264 | S21: =MAX(600,600+(H21-64)*8) -> 600 | T21: 0 | U21: =(J21)*11 -> 0 | V21: =sum(M21:U21) -> 2160 | W21: 0 | X21: 0 | Y21: 116 | Z21: 0 | AA21: 0 | AB21: 28 | AC21: 64 | AD21: 0 | AE21: 0 | AF21: =sum(W21:AE21) -> 208 | AG21: =if(and(K21>0,AF21>0),K21/AF21,0) -> 0.82331731
A22: 45351 | B22: =IFERROR(__xludf.DUMMYFUNCTION("sumproduct(importrange($AI$2,""hours""),importrange($AI$2,""lessondate"")<=($A22),importrange($AI$2,""lessondate"")>($A21),importrange($AI$2,""teacher"")=B$2)"),0.0) -> 0 | C22: =IFERROR(__xludf.DUMMYFUNCTION("sumproduct(importrange($AI$2,""hours""),importrange($AI$2,""lessondate"")<=($A22),importrange($AI$2,""lessondate"")>($A21),importrange($AI$2,""teacher"")=C$2)"),0.0) -> 0 | D22: =IFERROR(__xludf.DUMMYFUNCTION("sumproduct(importrange($AI$2,""hours""),importrange($AI$2,""lessondate"")<=($A22),importrange($AI$2,""lessondate"")>($A21),importrange($AI$2,""teacher"")=D$2)"),101.41666666666666) -> 101.41667 | E22: =IFERROR(__xludf.DUMMYFUNCTION("sumproduct(importrange($AI$2,""hours""),importrange($AI$2,""lessondate"")<=($A22),importrange($AI$2,""lessondate"")>($A21),importrange($AI$2,""teacher"")=E$2)"),0.0) -> 0 | F22: =IFERROR(__xludf.DUMMYFUNCTION("sumproduct(importrange($AI$2,""hours""),importrange($AI$2,""lessondate"")<=($A22),importrange($AI$2,""lessondate"")>($A21),importrange($AI$2,""teacher"")=F$2)"),12.0) -> 12 | G22: =IFERROR(__xludf.DUMMYFUNCTION("sumproduct(importrange($AI$2,""hours""),importrange($AI$2,""lessondate"")<=($A22),importrange($AI$2,""lessondate"")>($A21),importrange($AI$2,""teacher"")=G$2)"),23.0) -> 23 | H22: =IFERROR(__xludf.DUMMYFUNCTION("sumproduct(importrange($AI$2,""hours""),importrange($AI$2,""lessondate"")<=($A22),importrange($AI$2,""lessondate"")>($A21),importrange($AI$2,""teacher"")=H$2)"),36.0) -> 36 | I22: =IFERROR(__xludf.DUMMYFUNCTION("sumproduct(importrange($AI$2,""hours""),importrange($AI$2,""lessondate"")<=($A22),importrange($AI$2,""lessondate"")>($A21),importrange($AI$2,""teacher"")=I$2)"),0.0) -> 0 | J22: =IFERROR(__xludf.DUMMYFUNCTION("sumproduct(importrange($AI$2,""hours""),importrange($AI$2,""lessondate"")<=($A22),importrange($AI$2,""lessondate"")>($A21),importrange($AI$2,""teacher"")=J$2)"),0.0) -> 0 | K22: =SUM(B22:H22) -> 172.41667 | L22: 15 | M22: =B22*$L22 -> 0 | N22: =C22*$L22 -> 0 | O22: 1200 | P22: 0 | Q22: =(F22)*8 -> 96 | R22: =MAX(200,200+(G22-28)*8) -> 200 | S22: =MAX(600,600+(H22-64)*8) -> 600 | T22: 0 | U22: =(J22)*11 -> 0 | V22: =sum(M22:U22) -> 2096 | W22: 0 | X22: 0 | Y22: 116 | Z22: 0 | AA22: 0 | AB22: 28 | AC22: 64 | AD22: 0 | AE22: 0 | AF22: =sum(W22:AE22) -> 208 | AG22: =if(and(K22>0,AF22>0),K22/AF22,0) -> 0.82892628
A23: 45382 | B23: =IFERROR(__xludf.DUMMYFUNCTION("sumproduct(importrange($AI$2,""hours""),importrange($AI$2,""lessondate"")<=($A23),importrange($AI$2,""lessondate"")>($A22),importrange($AI$2,""teacher"")=B$2)"),0.0) -> 0 | C23: =IFERROR(__xludf.DUMMYFUNCTION("sumproduct(importrange($AI$2,""hours""),importrange($AI$2,""lessondate"")<=($A23),importrange($AI$2,""lessondate"")>($A22),importrange($AI$2,""teacher"")=C$2)"),0.0) -> 0 | D23: =IFERROR(__xludf.DUMMYFUNCTION("sumproduct(importrange($AI$2,""hours""),importrange($AI$2,""lessondate"")<=($A23),importrange($AI$2,""lessondate"")>($A22),importrange($AI$2,""teacher"")=D$2)"),102.5) -> 102.5 | E23: =IFERROR(__xludf.DUMMYFUNCTION("sumproduct(importrange($AI$2,""hours""),importrange($AI$2,""lessondate"")<=($A23),importrange($AI$2,""lessondate"")>($A22),importrange($AI$2,""teacher"")=E$2)"),0.0) -> 0 | F23: =IFERROR(__xludf.DUMMYFUNCTION("sumproduct(importrange($AI$2,""hours""),importrange($AI$2,""lessondate"")<=($A23),importrange($AI$2,""lessondate"")>($A22),importrange($AI$2,""teacher"")=F$2)"),14.0) -> 14 | G23: =IFERROR(__xludf.DUMMYFUNCTION("sumproduct(importrange($AI$2,""hours""),importrange($AI$2,""lessondate"")<=($A23),importrange($AI$2,""lessondate"")>($A22),importrange($AI$2,""teacher"")=G$2)"),23.0) -> 23 | H23: =IFERROR(__xludf.DUMMYFUNCTION("sumproduct(importrange($AI$2,""hours""),importrange($AI$2,""lessondate"")<=($A23),importrange($AI$2,""lessondate"")>($A22),importrange($AI$2,""teacher"")=H$2)"),43.0) -> 43 | I23: =IFERROR(__xludf.DUMMYFUNCTION("sumproduct(importrange($AI$2,""hours""),importrange($AI$2,""lessondate"")<=($A23),importrange($AI$2,""lessondate"")>($A22),importrange($AI$2,""teacher"")=I$2)"),0.0) -> 0 | J23: =IFERROR(__xludf.DUMMYFUNCTION("sumproduct(importrange($AI$2,""hours""),importrange($AI$2,""lessondate"")<=($A23),importrange($AI$2,""lessondate"")>($A22),importrange($AI$2,""teacher"")=J$2)"),0.0) -> 0 | K23: =SUM(B23:H23) -> 182.5 | L23: 15 | M23: =B23*$L23 -> 0 | N23: =C23*$L23 -> 0 | O23: 1200 | P23: 0 | Q23: =(F23)*8 -> 112 | R23: =MAX(200,200+(G23-28)*8) -> 200 | S23: =MAX(600,600+(H23-64)*8) -> 600 | T23: 0 | U23: =(J23)*11 -> 0 | V23: =sum(M23:U23) -> 2112 | W23: 0 | X23: 0 | Y23: 116 | Z23: 0 | AA23: 0 | AB23: 28 | AC23: 64 | AD23: 0 | AE23: 0 | AF23: =sum(W23:AE23) -> 208 | AG23: =if(and(K23>0,AF23>0),K23/AF23,0) -> 0.87740385
A24: 45412 | B24: =IFERROR(__xludf.DUMMYFUNCTION("sumproduct(importrange($AI$2,""hours""),importrange($AI$2,""lessondate"")<=($A24),importrange($AI$2,""lessondate"")>($A23),importrange($AI$2,""teacher"")=B$2)"),0.0) -> 0 | C24: =IFERROR(__xludf.DUMMYFUNCTION("sumproduct(importrange($AI$2,""hours""),importrange($AI$2,""lessondate"")<=($A24),importrange($AI$2,""lessondate"")>($A23),importrange($AI$2,""teacher"")=C$2)"),0.0) -> 0 | D24: =IFERROR(__xludf.DUMMYFUNCTION("sumproduct(importrange($AI$2,""hours""),importrange($AI$2,""lessondate"")<=($A24),importrange($AI$2,""lessondate"")>($A23),importrange($AI$2,""teacher"")=D$2)"),63.75) -> 63.75 | E24: =IFERROR(__xludf.DUMMYFUNCTION("sumproduct(importrange($AI$2,""hours""),importrange($AI$2,""lessondate"")<=($A24),importrange($AI$2,""lessondate"")>($A23),importrange($AI$2,""teacher"")=E$2)"),0.0) -> 0 | F24: =IFERROR(__xludf.DUMMYFUNCTION("sumproduct(importrange($AI$2,""hours""),importrange($AI$2,""lessondate"")<=($A24),importrange($AI$2,""lessondate"")>($A23),importrange($AI$2,""teacher"")=F$2)"),17.0) -> 17 | G24: =IFERROR(__xludf.DUMMYFUNCTION("sumproduct(importrange($AI$2,""hours""),importrange($AI$2,""lessondate"")<=($A24),importrange($AI$2,""lessondate"")>($A23),importrange($AI$2,""teacher"")=G$2)"),24.0) -> 24 | H24: =IFERROR(__xludf.DUMMYFUNCTION("sumproduct(importrange($AI$2,""hours""),importrange($AI$2,""lessondate"")<=($A24),importrange($AI$2,""lessondate"")>($A23),importrange($AI$2,""teacher"")=H$2)"),41.666666666666664) -> 41.666667 | I24: =IFERROR(__xludf.DUMMYFUNCTION("sumproduct(importrange($AI$2,""hours""),importrange($AI$2,""lessondate"")<=($A24),importrange($AI$2,""lessondate"")>($A23),importrange($AI$2,""teacher"")=I$2)"),0.0) -> 0 | J24: =IFERROR(__xludf.DUMMYFUNCTION("sumproduct(importrange($AI$2,""hours""),importrange($AI$2,""lessondate"")<=($A24),importrange($AI$2,""lessondate"")>($A23),importrange($AI$2,""teacher"")=J$2)"),0.0) -> 0 | K24: =SUM(B24:J24) -> 146.41667 | L24: 15 | M24: =B24*$L24 -> 0 | N24: =C24*$L24 -> 0 | O24: 1200 | P24: 0 | Q24: =(F24)*8 -> 136 | R24: =MAX(200,200+(G24-28)*8) -> 200 | S24: =MAX(600,600+(H24-64)*8) -> 600 | T24: 0 | U24: =(J24)*11 -> 0 | V24: =sum(M24:U24) -> 2136 | W24: 0 | X24: 0 | Y24: 116 | Z24: 0 | AA24: 0 | AB24: 28 | AC24: 64 | AD24: 0 | AE24: 0 | AF24: =sum(W24:AE24) -> 208 | AG24: =if(and(K24>0,AF24>0),K24/AF24,0) -> 0.70392628
A25: 45443 | B25: =IFERROR(__xludf.DUMMYFUNCTION("sumproduct(importrange($AI$2,""hours""),importrange($AI$2,""lessondate"")<=($A25),importrange($AI$2,""lessondate"")>($A24),importrange($AI$2,""teacher"")=B$2)"),0.0) -> 0 | C25: =IFERROR(__xludf.DUMMYFUNCTION("sumproduct(importrange($AI$2,""hours""),importrange($AI$2,""lessondate"")<=($A25),importrange($AI$2,""lessondate"")>($A24),importrange($AI$2,""teacher"")=C$2)"),0.0) -> 0 | D25: =IFERROR(__xludf.DUMMYFUNCTION("sumproduct(importrange($AI$2,""hours""),importrange($AI$2,""lessondate"")<=($A25),importrange($AI$2,""lessondate"")>($A24),importrange($AI$2,""teacher"")=D$2)"),83.0) -> 83 | E25: =IFERROR(__xludf.DUMMYFUNCTION("sumproduct(importrange($AI$2,""hours""),importrange($AI$2,""lessondate"")<=($A25),importrange($AI$2,""lessondate"")>($A24),importrange($AI$2,""teacher"")=E$2)"),0.0) -> 0 | F25: =IFERROR(__xludf.DUMMYFUNCTION("sumproduct(importrange($AI$2,""hours""),importrange($AI$2,""lessondate"")<=($A25),importrange($AI$2,""lessondate"")>($A24),importrange($AI$2,""teacher"")=F$2)"),13.0) -> 13 | G25: =IFERROR(__xludf.DUMMYFUNCTION("sumproduct(importrange($AI$2,""hours""),importrange($AI$2,""lessondate"")<=($A25),importrange($AI$2,""lessondate"")>($A24),importrange($AI$2,""teacher"")=G$2)"),17.0) -> 17 | H25: =IFERROR(__xludf.DUMMYFUNCTION("sumproduct(importrange($AI$2,""hours""),importrange($AI$2,""lessondate"")<=($A25),importrange($AI$2,""lessondate"")>($A24),importrange($AI$2,""teacher"")=H$2)"),53.0) -> 53 | I25: =IFERROR(__xludf.DUMMYFUNCTION("sumproduct(importrange($AI$2,""hours""),importrange($AI$2,""lessondate"")<=($A25),importrange($AI$2,""lessondate"")>($A24),importrange($AI$2,""teacher"")=I$2)"),8.0) -> 8 | J25: =IFERROR(__xludf.DUMMYFUNCTION("sumproduct(importrange($AI$2,""hours""),importrange($AI$2,""lessondate"")<=($A25),importrange($AI$2,""lessondate"")>($A24),importrange($AI$2,""teacher"")=J$2)"),0.0) -> 0 | K25: =SUM(B25:J25) -> 174 | L25: 15 | M25: =B25*$L25 -> 0 | N25: =C25*$L25 -> 0 | O25: 1200 | P25: 0 | Q25: =(F25)*8 -> 104 | R25: =MAX(200,200+(G25-28)*8) -> 200 | S25: =MAX(600,600+(H25-64)*8) -> 600 | T25: =MAX(375,375+(I25-48)*8) -> 375 | U25: =(J25)*11 -> 0 | V25: =sum(M25:U25) -> 2479 | W25: 0 | X25: 0 | Y25: 116 | Z25: 0 | AA25: 0 | AB25: 28 | AC25: 64 | AD25: 48 | AE25: 0 | AF25: =sum(W25:AE25) -> 256 | AG25: =if(and(K25>0,AF25>0),K25/AF25,0) -> 0.6796875
A26: 45473 | B26: =IFERROR(__xludf.DUMMYFUNCTION("sumproduct(importrange($AI$2,""hours""),importrange($AI$2,""lessondate"")<=($A26),importrange($AI$2,""lessondate"")>($A25),importrange($AI$2,""teacher"")=B$2)"),0.0) -> 0 | C26: =IFERROR(__xludf.DUMMYFUNCTION("sumproduct(importrange($AI$2,""hours""),importrange($AI$2,""lessondate"")<=($A26),importrange($AI$2,""lessondate"")>($A25),importrange($AI$2,""teacher"")=C$2)"),0.0) -> 0 | D26: =IFERROR(__xludf.DUMMYFUNCTION("sumproduct(importrange($AI$2,""hours""),importrange($AI$2,""lessondate"")<=($A26),importrange($AI$2,""lessondate"")>($A25),importrange($AI$2,""teacher"")=D$2)"),71.75) -> 71.75 | E26: =IFERROR(__xludf.DUMMYFUNCTION("sumproduct(importrange($AI$2,""hours""),importrange($AI$2,""lessondate"")<=($A26),importrange($AI$2,""lessondate"")>($A25),importrange($AI$2,""teacher"")=E$2)"),0.0) -> 0 | F26: =IFERROR(__xludf.DUMMYFUNCTION("sumproduct(importrange($AI$2,""hours""),importrange($AI$2,""lessondate"")<=($A26),importrange($AI$2,""lessondate"")>($A25),importrange($AI$2,""teacher"")=F$2)"),14.0) -> 14 | G26: =IFERROR(__xludf.DUMMYFUNCTION("sumproduct(importrange($AI$2,""hours""),importrange($AI$2,""lessondate"")<=($A26),importrange($AI$2,""lessondate"")>($A25),importrange($AI$2,""teacher"")=G$2)"),17.0) -> 17 | H26: =IFERROR(__xludf.DUMMYFUNCTION("sumproduct(importrange($AI$2,""hours""),importrange($AI$2,""lessondate"")<=($A26),importrange($AI$2,""lessondate"")>($A25),importrange($AI$2,""teacher"")=H$2)"),42.0) -> 42 | I26: =IFERROR(__xludf.DUMMYFUNCTION("sumproduct(importrange($AI$2,""hours""),importrange($AI$2,""lessondate"")<=($A26),importrange($AI$2,""lessondate"")>($A25),importrange($AI$2,""teacher"")=I$2)"),15.0) -> 15 | J26: =IFERROR(__xludf.DUMMYFUNCTION("sumproduct(importrange($AI$2,""hours""),importrange($AI$2,""lessondate"")<=($A26),importrange($AI$2,""lessondate"")>($A25),importrange($AI$2,""teacher"")=J$2)"),0.0) -> 0 | K26: =SUM(B26:J26) -> 159.75 | L26: 15 | M26: =B26*$L26 -> 0 | N26: =C26*$L26 -> 0 | O26: 1200 | P26: 0 | Q26: =(F26)*8 -> 112 | R26: =MAX(200,200+(G26-28)*8) -> 200 | S26: =MAX(600,600+(H26-64)*8) -> 600 | T26: =MAX(375,375+(I26-48)*8) -> 375 | U26: =(J26)*11 -> 0 | V26: =sum(M26:U26) -> 2487 | W26: 0 | X26: 0 | Y26: 116 | Z26: 0 | AA26: 0 | AB26: 28 | AC26: 64 | AD26: 48 | AE26: 0 | AF26: =sum(W26:AE26) -> 256 | AG26: =if(and(K26>0,AF26>0),K26/AF26,0) -> 0.62402344
A27: 45504 | B27: =IFERROR(__xludf.DUMMYFUNCTION("sumproduct(importrange($AI$2,""hours""),importrange($AI$2,""lessondate"")<=($A27),importrange($AI$2,""lessondate"")>($A26),importrange($AI$2,""teacher"")=B$2)"),0.0) -> 0 | C27: =IFERROR(__xludf.DUMMYFUNCTION("sumproduct(importrange($AI$2,""hours""),importrange($AI$2,""lessondate"")<=($A27),importrange($AI$2,""lessondate"")>($A26),importrange($AI$2,""teacher"")=C$2)"),0.0) -> 0 | D27: =IFERROR(__xludf.DUMMYFUNCTION("sumproduct(importrange($AI$2,""hours""),importrange($AI$2,""lessondate"")<=($A27),importrange($AI$2,""lessondate"")>($A26),importrange($AI$2,""teacher"")=D$2)"),80.25) -> 80.25 | E27: =IFERROR(__xludf.DUMMYFUNCTION("sumproduct(importrange($AI$2,""hours""),importrange($AI$2,""lessondate"")<=($A27),importrange($AI$2,""lessondate"")>($A26),importrange($AI$2,""teacher"")=E$2)"),0.0) -> 0 | F27: =IFERROR(__xludf.DUMMYFUNCTION("sumproduct(importrange($AI$2,""hours""),importrange($AI$2,""lessondate"")<=($A27),importrange($AI$2,""lessondate"")>($A26),importrange($AI$2,""teacher"")=F$2)"),10.0) -> 10 | G27: =IFERROR(__xludf.DUMMYFUNCTION("sumproduct(importrange($AI$2,""hours""),importrange($AI$2,""lessondate"")<=($A27),importrange($AI$2,""lessondate"")>($A26),importrange($AI$2,""teacher"")=G$2)"),1.0) -> 1 | H27: =IFERROR(__xludf.DUMMYFUNCTION("sumproduct(importrange($AI$2,""hours""),importrange($AI$2,""lessondate"")<=($A27),importrange($AI$2,""lessondate"")>($A26),importrange($AI$2,""teacher"")=H$2)"),50.0) -> 50 | I27: =IFERROR(__xludf.DUMMYFUNCTION("sumproduct(importrange($AI$2,""hours""),importrange($AI$2,""lessondate"")<=($A27),importrange($AI$2,""lessondate"")>($A26),importrange($AI$2,""teacher"")=I$2)"),14.0) -> 14 | J27: =IFERROR(__xludf.DUMMYFUNCTION("sumproduct(importrange($AI$2,""hours""),importrange($AI$2,""lessondate"")<=($A27),importrange($AI$2,""lessondate"")>($A26),importrange($AI$2,""teacher"")=J$2)"),0.0) -> 0 | K27: =SUM(B27:J27) -> 155.25 | L27: 15 | M27: =B27*$L27 -> 0 | N27: =C27*$L27 -> 0 | O27: 1200 | P27: 0 | Q27: =(F27)*8 -> 80 | R27: =0 -> 0 | S27: =MAX(600,600+(H27-64)*8) -> 600 | T27: =MAX(375,375+(I27-48)*8) -> 375 | U27: =(J27)*11 -> 0 | V27: =sum(M27:U27) -> 2255 | W27: 0 | X27: 0 | Y27: 116 | Z27: 0 | AA27: 0 | AB27: 0 | AC27: 64 | AD27: 48 | AE27: 0 | AF27: =sum(W27:AE27) -> 228 | AG27: =if(and(K27>0,AF27>0),K27/AF27,0) -> 0.68092105
A28: 45535 | B28: =IFERROR(__xludf.DUMMYFUNCTION("sumproduct(importrange($AI$2,""hours""),importrange($AI$2,""lessondate"")<=($A28),importrange($AI$2,""lessondate"")>($A27),importrange($AI$2,""teacher"")=B$2)"),0.0) -> 0 | C28: =IFERROR(__xludf.DUMMYFUNCTION("sumproduct(importrange($AI$2,""hours""),importrange($AI$2,""lessondate"")<=($A28),importrange($AI$2,""lessondate"")>($A27),importrange($AI$2,""teacher"")=C$2)"),0.0) -> 0 | D28: =IFERROR(__xludf.DUMMYFUNCTION("sumproduct(importrange($AI$2,""hours""),importrange($AI$2,""lessondate"")<=($A28),importrange($AI$2,""lessondate"")>($A27),importrange($AI$2,""teacher"")=D$2)"),62.25) -> 62.25 | E28: =IFERROR(__xludf.DUMMYFUNCTION("sumproduct(importrange($AI$2,""hours""),importrange($AI$2,""lessondate"")<=($A28),importrange($AI$2,""lessondate"")>($A27),importrange($AI$2,""teacher"")=E$2)"),0.0) -> 0 | F28: =IFERROR(__xludf.DUMMYFUNCTION("sumproduct(importrange($AI$2,""hours""),importrange($AI$2,""lessondate"")<=($A28),importrange($AI$2,""lessondate"")>($A27),importrange($AI$2,""teacher"")=F$2)"),9.0) -> 9 | G28: =IFERROR(__xludf.DUMMYFUNCTION("sumproduct(importrange($AI$2,""hours""),importrange($AI$2,""lessondate"")<=($A28),importrange($AI$2,""lessondate"")>($A27),importrange($AI$2,""teacher"")=G$2)"),0.0) -> 0 | H28: =IFERROR(__xludf.DUMMYFUNCTION("sumproduct(importrange($AI$2,""hours""),importrange($AI$2,""lessondate"")<=($A28),importrange($AI$2,""lessondate"")>($A27),importrange($AI$2,""teacher"")=H$2)"),59.0) -> 59 | I28: =IFERROR(__xludf.DUMMYFUNCTION("sumproduct(importrange($AI$2,""hours""),importrange($AI$2,""lessondate"")<=($A28),importrange($AI$2,""lessondate"")>($A27),importrange($AI$2,""teacher"")=I$2)"),17.0) -> 17 | J28: =IFERROR(__xludf.DUMMYFUNCTION("sumproduct(importrange($AI$2,""hours""),importrange($AI$2,""lessondate"")<=($A28),importrange($AI$2,""lessondate"")>($A27),importrange($AI$2,""teacher"")=J$2)"),6.0) -> 6 | K28: =SUM(B28:J28) -> 153.25 | L28: 15 | M28: =B28*$L28 -> 0 | N28: =C28*$L28 -> 0 | O28: 1200 | P28: 0 | Q28: =(F28)*8 -> 72 | R28: =0 -> 0 | S28: =MAX(700,700+(H28-64)*8) -> 700 | T28: =MAX(375,375+(I28-48)*8) -> 375 | U28: =(J28)*11 -> 66 | V28: =sum(M28:U28) -> 2413 | W28: 0 | X28: 0 | Y28: 116 | Z28: 0 | AA28: 0 | AB28: 0 | AC28: 64 | AD28: 48 | AE28: 0 | AF28: =sum(W28:AE28) -> 228 | AG28: =if(and(K28>0,AF28>0),K28/AF28,0) -> 0.67214912
A29: 45565 | B29: =IFERROR(__xludf.DUMMYFUNCTION("sumproduct(importrange($AI$2,""hours""),importrange($AI$2,""lessondate"")<=($A29),importrange($AI$2,""lessondate"")>($A28),importrange($AI$2,""teacher"")=B$2)"),0.0) -> 0 | C29: =IFERROR(__xludf.DUMMYFUNCTION("sumproduct(importrange($AI$2,""hours""),importrange($AI$2,""lessondate"")<=($A29),importrange($AI$2,""lessondate"")>($A28),importrange($AI$2,""teacher"")=C$2)"),0.0) -> 0 | D29: =IFERROR(__xludf.DUMMYFUNCTION("sumproduct(importrange($AI$2,""hours""),importrange($AI$2,""lessondate"")<=($A29),importrange($AI$2,""lessondate"")>($A28),importrange($AI$2,""teacher"")=D$2)"),62.5) -> 62.5 | E29: =IFERROR(__xludf.DUMMYFUNCTION("sumproduct(importrange($AI$2,""hours""),importrange($AI$2,""lessondate"")<=($A29),importrange($AI$2,""lessondate"")>($A28),importrange($AI$2,""teacher"")=E$2)"),0.0) -> 0 | F29: =IFERROR(__xludf.DUMMYFUNCTION("sumproduct(importrange($AI$2,""hours""),importrange($AI$2,""lessondate"")<=($A29),importrange($AI$2,""lessondate"")>($A28),importrange($AI$2,""teacher"")=F$2)"),3.0) -> 3 | G29: =IFERROR(__xludf.DUMMYFUNCTION("sumproduct(importrange($AI$2,""hours""),importrange($AI$2,""lessondate"")<=($A29),importrange($AI$2,""lessondate"")>($A28),importrange($AI$2,""teacher"")=G$2)"),0.0) -> 0 | H29: =IFERROR(__xludf.DUMMYFUNCTION("sumproduct(importrange($AI$2,""hours""),importrange($AI$2,""lessondate"")<=($A29),importrange($AI$2,""lessondate"")>($A28),importrange($AI$2,""teacher"")=H$2)"),44.0) -> 44 | I29: =IFERROR(__xludf.DUMMYFUNCTION("sumproduct(importrange($AI$2,""hours""),importrange($AI$2,""lessondate"")<=($A29),importrange($AI$2,""lessondate"")>($A28),importrange($AI$2,""teacher"")=I$2)"),29.0) -> 29 | J29: =IFERROR(__xludf.DUMMYFUNCTION("sumproduct(importrange($AI$2,""hours""),importrange($AI$2,""lessondate"")<=($A29),importrange($AI$2,""lessondate"")>($A28),importrange($AI$2,""teacher"")=J$2)"),29.0) -> 29 | K29: =SUM(B29:J29) -> 167.5 | L29: 15 | M29: =B29*$L29 -> 0 | N29: =C29*$L29 -> 0 | O29: 1200 | P29: 0 | Q29: =(F29)*8 -> 24 | R29: =0 -> 0 | S29: =MAX(700,700+(H29-64)*8) -> 700 | T29: =MAX(375,375+(I29-48)*8) -> 375 | U29: =(J29)*11 -> 319 | V29: =sum(M29:U29) -> 2618 | W29: 0 | X29: 0 | Y29: 116 | Z29: 0 | AA29: 0 | AB29: 0 | AC29: 64 | AD29: 48 | AE29: 0 | AF29: =sum(W29:AE29) -> 228 | AG29: =if(and(K29>0,AF29>0),K29/AF29,0) -> 0.73464912
A30: 45596 | B30: =IFERROR(__xludf.DUMMYFUNCTION("sumproduct(importrange($AI$2,""hours""),importrange($AI$2,""lessondate"")<=($A30),importrange($AI$2,""lessondate"")>($A29),importrange($AI$2,""teacher"")=B$2)"),0.0) -> 0 | C30: =IFERROR(__xludf.DUMMYFUNCTION("sumproduct(importrange($AI$2,""hours""),importrange($AI$2,""lessondate"")<=($A30),importrange($AI$2,""lessondate"")>($A29),importrange($AI$2,""teacher"")=C$2)"),0.0) -> 0 | D30: =IFERROR(__xludf.DUMMYFUNCTION("sumproduct(importrange($AI$2,""hours""),importrange($AI$2,""lessondate"")<=($A30),importrange($AI$2,""lessondate"")>($A29),importrange($AI$2,""teacher"")=D$2)"),58.5) -> 58.5 | E30: =IFERROR(__xludf.DUMMYFUNCTION("sumproduct(importrange($AI$2,""hours""),importrange($AI$2,""lessondate"")<=($A30),importrange($AI$2,""lessondate"")>($A29),importrange($AI$2,""teacher"")=E$2)"),0.0) -> 0 | F30: =IFERROR(__xludf.DUMMYFUNCTION("sumproduct(importrange($AI$2,""hours""),importrange($AI$2,""lessondate"")<=($A30),importrange($AI$2,""lessondate"")>($A29),importrange($AI$2,""teacher"")=F$2)"),11.0) -> 11 | G30: =IFERROR(__xludf.DUMMYFUNCTION("sumproduct(importrange($AI$2,""hours""),importrange($AI$2,""lessondate"")<=($A30),importrange($AI$2,""lessondate"")>($A29),importrange($AI$2,""teacher"")=G$2)"),0.0) -> 0 | H30: =IFERROR(__xludf.DUMMYFUNCTION("sumproduct(importrange($AI$2,""hours""),importrange($AI$2,""lessondate"")<=($A30),importrange($AI$2,""lessondate"")>($A29),importrange($AI$2,""teacher"")=H$2)"),56.0) -> 56 | I30: =IFERROR(__xludf.DUMMYFUNCTION("sumproduct(importrange($AI$2,""hours""),importrange($AI$2,""lessondate"")<=($A30),importrange($AI$2,""lessondate"")>($A29),importrange($AI$2,""teacher"")=I$2)"),29.0) -> 29 | J30: =IFERROR(__xludf.DUMMYFUNCTION("sumproduct(importrange($AI$2,""hours""),importrange($AI$2,""lessondate"")<=($A30),importrange($AI$2,""lessondate"")>($A29),importrange($AI$2,""teacher"")=J$2)"),65.0) -> 65 | K30: =SUM(B30:J30) -> 219.5 | L30: 15 | M30: =B30*$L30 -> 0 | N30: =C30*$L30 -> 0 | O30: =MAX(840,840+(H30-81.7)*8) -> 840 | P30: 0 | Q30: =(F30)*8 -> 88 | R30: =0 -> 0 | S30: =MAX(700,700+(H30-64)*8) -> 700 | T30: =MAX(375,375+(I30-48)*8) -> 375 | U30: =MAX(900,900+(H30-86)*8) -> 900 | V30: =sum(M30:U30) -> 2903 | W30: 0 | X30: 0 | Y30: 87 | Z30: 0 | AA30: 0 | AB30: 0 | AC30: 64 | AD30: 48 | AE30: 86 | AF30: =sum(W30:AE30) -> 285 | AG30: =if(and(K30>0,AF30>0),K30/AF30,0) -> 0.77017544
A31: 45626 | B31: =IFERROR(__xludf.DUMMYFUNCTION("sumproduct(importrange($AI$2,""hours""),importrange($AI$2,""lessondate"")<=($A31),importrange($AI$2,""lessondate"")>($A30),importrange($AI$2,""teacher"")=B$2)"),0.0) -> 0 | C31: =IFERROR(__xludf.DUMMYFUNCTION("sumproduct(importrange($AI$2,""hours""),importrange($AI$2,""lessondate"")<=($A31),importrange($AI$2,""lessondate"")>($A30),importrange($AI$2,""teacher"")=C$2)"),0.0) -> 0 | D31: =IFERROR(__xludf.DUMMYFUNCTION("sumproduct(importrange($AI$2,""hours""),importrange($AI$2,""lessondate"")<=($A31),importrange($AI$2,""lessondate"")>($A30),importrange($AI$2,""teacher"")=D$2)"),55.5) -> 55.5 | E31: =IFERROR(__xludf.DUMMYFUNCTION("sumproduct(importrange($AI$2,""hours""),importrange($AI$2,""lessondate"")<=($A31),importrange($AI$2,""lessondate"")>($A30),importrange($AI$2,""teacher"")=E$2)"),0.0) -> 0 | F31: =IFERROR(__xludf.DUMMYFUNCTION("sumproduct(importrange($AI$2,""hours""),importrange($AI$2,""lessondate"")<=($A31),importrange($AI$2,""lessondate"")>($A30),importrange($AI$2,""teacher"")=F$2)"),16.0) -> 16 | G31: =IFERROR(__xludf.DUMMYFUNCTION("sumproduct(importrange($AI$2,""hours""),importrange($AI$2,""lessondate"")<=($A31),importrange($AI$2,""lessondate"")>($A30),importrange($AI$2,""teacher"")=G$2)"),0.0) -> 0 | H31: =IFERROR(__xludf.DUMMYFUNCTION("sumproduct(importrange($AI$2,""hours""),importrange($AI$2,""lessondate"")<=($A31),importrange($AI$2,""lessondate"")>($A30),importrange($AI$2,""teacher"")=H$2)"),51.0) -> 51 | I31: =IFERROR(__xludf.DUMMYFUNCTION("sumproduct(importrange($AI$2,""hours""),importrange($AI$2,""lessondate"")<=($A31),importrange($AI$2,""lessondate"")>($A30),importrange($AI$2,""teacher"")=I$2)"),21.0) -> 21 | J31: =IFERROR(__xludf.DUMMYFUNCTION("sumproduct(importrange($AI$2,""hours""),importrange($AI$2,""lessondate"")<=($A31),importrange($AI$2,""lessondate"")>($A30),importrange($AI$2,""teacher"")=J$2)"),70.25) -> 70.25 | K31: =SUM(B31:J31) -> 213.75 | L31: 15 | M31: =B31*$L31 -> 0 | N31: =C31*$L31 -> 0 | O31: =MAX(840,840+(H31-81.7)*8) -> 840 | P31: 0 | Q31: =(F31)*11 -> 176 | R31: =0 -> 0 | S31: =MAX(700,700+(H31-64)*8) -> 700 | T31: =MAX(375,375+(I31-48)*8) -> 375 | U31: =MAX(900,900+(H31-86)*8) -> 900 | V31: =sum(M31:U31) -> 2991 | W31: 0 | X31: 0 | Y31: 87 | Z31: 0 | AA31: 0 | AB31: 0 | AC31: 64 | AD31: 48 | AE31: 86 | AF31: =sum(W31:AE31) -> 285 | AG31: =if(and(K31>0,AF31>0),K31/AF31,0) -> 0.75
A32: 45657 | B32: =IFERROR(__xludf.DUMMYFUNCTION("sumproduct(importrange($AI$2,""hours""),importrange($AI$2,""lessondate"")<=($A32),importrange($AI$2,""lessondate"")>($A31),importrange($AI$2,""teacher"")=B$2)"),0.0) -> 0 | C32: =IFERROR(__xludf.DUMMYFUNCTION("sumproduct(importrange($AI$2,""hours""),importrange($AI$2,""lessondate"")<=($A32),importrange($AI$2,""lessondate"")>($A31),importrange($AI$2,""teacher"")=C$2)"),0.0) -> 0 | D32: =IFERROR(__xludf.DUMMYFUNCTION("sumproduct(importrange($AI$2,""hours""),importrange($AI$2,""lessondate"")<=($A32),importrange($AI$2,""lessondate"")>($A31),importrange($AI$2,""teacher"")=D$2)"),43.25) -> 43.25 | E32: =IFERROR(__xludf.DUMMYFUNCTION("sumproduct(importrange($AI$2,""hours""),importrange($AI$2,""lessondate"")<=($A32),importrange($AI$2,""lessondate"")>($A31),importrange($AI$2,""teacher"")=E$2)"),0.0) -> 0 | F32: =IFERROR(__xludf.DUMMYFUNCTION("sumproduct(importrange($AI$2,""hours""),importrange($AI$2,""lessondate"")<=($A32),importrange($AI$2,""lessondate"")>($A31),importrange($AI$2,""teacher"")=F$2)"),12.0) -> 12 | G32: =IFERROR(__xludf.DUMMYFUNCTION("sumproduct(importrange($AI$2,""hours""),importrange($AI$2,""lessondate"")<=($A32),importrange($AI$2,""lessondate"")>($A31),importrange($AI$2,""teacher"")=G$2)"),0.0) -> 0 | H32: =IFERROR(__xludf.DUMMYFUNCTION("sumproduct(importrange($AI$2,""hours""),importrange($AI$2,""lessondate"")<=($A32),importrange($AI$2,""lessondate"")>($A31),importrange($AI$2,""teacher"")=H$2)"),42.0) -> 42 | I32: =IFERROR(__xludf.DUMMYFUNCTION("sumproduct(importrange($AI$2,""hours""),importrange($AI$2,""lessondate"")<=($A32),importrange($AI$2,""lessondate"")>($A31),importrange($AI$2,""teacher"")=I$2)"),10.0) -> 10 | J32: =IFERROR(__xludf.DUMMYFUNCTION("sumproduct(importrange($AI$2,""hours""),importrange($AI$2,""lessondate"")<=($A32),importrange($AI$2,""lessondate"")>($A31),importrange($AI$2,""teacher"")=J$2)"),69.75) -> 69.75 | K32: =SUM(B32:J32) -> 177 | L32: 15 | M32: =B32*$L32 -> 0 | N32: =C32*$L32 -> 0 | O32: =MAX(840,840+(H32-81.7)*8)+20 -> 860 | P32: 0 | Q32: =(F32)*11+20 -> 152 | R32: =0 -> 0 | S32: =MAX(700,700+(H32-64)*8)+20 -> 720 | T32: =MAX(375,375+(I32-48)*8)+20 -> 395 | U32: =MAX(900,900+(H32-86)*8)+20 -> 920 | V32: =sum(M32:U32) -> 3047 | W32: 0 | X32: 0 | Y32: 87 | Z32: 0 | AA32: 0 | AB32: 0 | AC32: 64 | AD32: 48 | AE32: 86 | AF32: =sum(W32:AE32) -> 285 | AG32: =if(and(K32>0,AF32>0),K32/AF32,0) -> 0.62105263
